Workbook

Sheet VUE GLOBAL
A1: SECTEUR | B1: NB DE DOSSIERS | C1: DRE KO | D1: VT A FAIRE | E1: A REMONTER | F1: RETOUR VT | G1: DOSS A REPRENDRE | H1: DOSS A MONTER | I1: ATT INFOS CAF REF | J1: ATT DEVIS ORANGE/RIP | K1: ATT DEVIS CLIENT | L1: ATT TRAVAUX CLIENT | M1: ATT PV | N1: ATT DTA | O1: ATT COMAC/CAPFT | P1: ATT MAJ SI | Q1: POI EN TRAVAUX | R1: AT RETOUR DOE | T1: ETAT 5
A2: MEN-ROD | B2: ='MEN-ROD'!E1 -> 445 | C2: =COUNTIF('MEN-ROD'!C:C,"<="&TODAY()) -> 55 | D2: =COUNTIF('MEN-ROD'!D:D,"*01 AT VT*") -> 19 | E2: =COUNTIF('MEN-ROD'!D:D,"*01.2 A REMONTER*") -> 9 | F2: =COUNTIF('MEN-ROD'!D:D,"*02 RETOUR VT*") -> 29 | G2: =COUNTIF('MEN-ROD'!D:D,"*03 DOSSIER A REPRENDRE*") -> 5 | H2: =COUNTIF('MEN-ROD'!D:D,"*04 DOSSIER A MONTER*") -> 13 | I2: =COUNTIF('MEN-ROD'!D:D,"*05 AT INFO CAF REF*") -> 26 | J2: =COUNTIF('MEN-ROD'!D:D,"*09 AT DEVIS ORANGE/RIP*") -> 67 | K2: =COUNTIF('MEN-ROD'!D:D,"*06 AT DEVIS CLIENT*") -> 10 | L2: =COUNTIF('MEN-ROD'!D:D,"*07 AT TRVX CLIENT*") -> 86 | M2: =COUNTIF('MEN-ROD'!D:D,"*10 AT PV*") -> 15 | N2: =COUNTIF('MEN-ROD'!D:D,"*11 AT DTA*") -> 4 | O2: =COUNTIF('MEN-ROD'!D:D,"*08 AT COMAC/CAPFT*") -> 0 | P2: =COUNTIF('MEN-ROD'!D:D,"*12 AT MAJ SI*") -> 6 | Q2: =COUNTIF('MEN-ROD'!D:D,"*14 POI EN TRAVAUX*") -> 146 | R2: =COUNTIF('MEN-ROD'!D:D,"*14.1 AT RETOUR DOE*") -> 0 | T2: =COUNTIF('MEN-ROD'!D:D,"*13 ETAT 5*") -> 6
A3: GDP AQ | B3: ='GDP AQ'!E1 -> 106 | C3: =COUNTIF('GDP AQ'!C:C,"<="&TODAY()) -> 8 | D3: =COUNTIF('GDP AQ'!D:D,"*01 AT VT*") -> 11 | E3: =COUNTIF('GDP AQ'!D:D, "*01.2 A REMONTER*") -> 3 | F3: =COUNTIF('GDP AQ'!D:D,"*02 RETOUR VT*") -> 5 | G3: =COUNTIF('GDP AQ'!D:D,"*03 DOSSIER A REPRENDRE*") -> 2 | H3: =COUNTIF('GDP AQ'!D:D,"*04 DOSSIER A MONTER*") -> 5 | I3: =COUNTIF('GDP AQ'!D:D,"*5 AT INFO CAF REF*") -> 12 | J3: =COUNTIF('GDP AQ'!D:D,"*09 AT DEVIS ORANGE/RIP*") -> 2 | K3: =COUNTIF('GDP AQ'!D:D,"*06 AT DEVIS CLIENT*") -> 1 | L3: =COUNTIF('GDP AQ'!D:D,"*07 AT TRVX CLIENT*") -> 26 | M3: =COUNTIF('GDP AQ'!D:D,"*10 AT PV*") -> 9 | N3: =COUNTIF('GDP AQ'!D:D,"*11 AT DTA*") -> 2 | O3: =COUNTIF('GDP AQ'!D:D,"*08 AT COMAC/CAPFT*") -> 0 | P3: =COUNTIF('GDP AQ'!D:D,"*12 AT MAJ SI*") -> 1 | Q3: =COUNTIF('GDP AQ'!D:D,"*14 POI EN TRAVAUX*") -> 20 | R3: =COUNTIF('GDP AQ'!D:D,"*14.1 AT RETOUR DOE*") -> 5 | T3: =COUNTIF('GDP AQ'!D:D,"*13 ETAT 5*") -> 0
A4: QPR-CRO | B4: ='QPR-CRO'!E1 -> 347 | C4: =COUNTIF('QPR-CRO'!C:C,"<="&TODAY()) -> 48 | D4: =COUNTIF('QPR-CRO'!D:D,"*01 AT VT*") -> 40 | E4: =COUNTIF('QPR-CRO'!D:D,"*01.2 A REMONTER*") -> 26 | F4: =COUNTIF('QPR-CRO'!D:D,"*02 RETOUR VT*") -> 29 | G4: =COUNTIF('QPR-CRO'!D:D,"*03 DOSSIER A REPRENDRE*") -> 0 | H4: =COUNTIF('QPR-CRO'!D:D,"*04 DOSSIER A MONTER*") -> 13 | I4: =COUNTIF('QPR-CRO'!D:D,"*05 AT INFO CAF REF*") -> 24 | J4: =COUNTIF('QPR-CRO'!D:D,"*09 AT DEVIS ORANGE/RIP*") -> 14 | K4: =COUNTIF('QPR-CRO'!D:D,"*06 AT DEVIS CLIENT*") -> 6 | L4: =COUNTIF('QPR-CRO'!D:D,"*07 AT TRVX CLIENT*") -> 46 | M4: =COUNTIF('QPR-CRO'!D:D,"*10 AT PV*") -> 6 | N4: =COUNTIF('QPR-CRO'!D:D,"*11 AT DTA*") -> 0 | O4: =COUNTIF('QPR-CRO'!D:D,"*08 AT COMAC/CAPFT*") -> 0 | P4: =COUNTIF('QPR-CRO'!D:D,"*12 AT MAJ SI*") -> 10 | Q4: =COUNTIF('QPR-CRO'!D:D,"*14 POI EN TRAVAUX*") -> 56 | R4: =COUNTIF('QPR-CRO'!D:D,"*14.1 AT RETOUR DOE*") -> 65 | T4: =COUNTIF('QPR-CRO'!D:D,"*13 ETAT 5*") -> 1
A5: SECTEUR | B5: NB DE DOSSIERS | C5: DRE KO | D5: VT A FAIRE | E5: A REMONTER | F5: RETOUR VT | G5: DOSS A REPRENDRE | H5: DOSS A MONTER | I5: ATT INFOS CAF REF | J5: ATT DEVIS ORANGE/RIP | M5: ATT PV | P5: ATT MAJ SI | Q5: POI EN TRAVAUX | R5: AT RETOUR DOE | S5: RECOL A FAIRE
A6: SPI AQ | B6: ='SPI AQ'!B1 -> 73 | D6: =COUNTIF('SPI AQ'!A:A,"*01 VT A FAIRE*") -> 4 | E6: =COUNTIF('SPI AQ'!A:A, "*1.2 A REMONTER*") -> 1 | F6: =COUNTIF('SPI AQ'!A:A,"*02 RETOUR VT*") -> 2 | G6: =COUNTIF('SPI AQ'!A:A,"*03 DOSSIER A REPRENDRE*") -> 0 | H6: =COUNTIF('SPI AQ'!A:A,"*04 DOSSIER A MONTER*") -> 0 | I6: =COUNTIF('SPI AQ'!A:A,"*07 AT INFO CAF REF*") -> 15 | J6: =COUNTIF('SPI AQ'!A:A,"*08 AT DEVIS ORANGE/RIP*") -> 5 | M6: =COUNTIF('SPI AQ'!A:A,"*05 AT PV*") -> 13 | P6: =COUNTIF('SPI AQ'!A:A,"*06 AT MAJ SI*") -> 1 | Q6: =COUNTIF('SPI AQ'!A:A,"*09 POI EN TRAVAUX*") -> 15 | R6: =COUNTIF('SPI AQ'!A:A,"*09.1 ATT DOE*") -> 8 | S6: =COUNTIF('SPI AQ'!A:A,"*11 RECOL A FAIRE*") -> 0
A8: GLOBAL | B8: =B2+B3+B4+B6 -> 971 | C8: =C2+C3+C4+C6 -> 111 | D8: =D2+D3+D4+D6 -> 74 | E8: =E2+E3+E4+E6 -> 39 | F8: =F2+F3+F4+F6 -> 65 | G8: =G2+G3+G4+G6 -> 7 | H8: =H2+H3+H4+H6 -> 31 | I8: =I2+I3+I4+I6 -> 77 | ... T8: =T2+T3+T4+T6 -> 7
A10: Taux Non Confirmité | B10: =G8/F8 -> 0.10769231
A14: DOSSIER MAIN BE | B14: DOSSIER MAIN CHAFF
A15: =E2+G2 -> 14 | B15: =F2+H2 -> 42 | C15: MEN-ROD
A16: =E3+G3 -> 5 | B16: =F3+H3 -> 10 | C16: GDP AQ
A17: =E4+G4 -> 26 | B17: =F4+H4 -> 42 | C17: QPR-CRO
A18: =E6+G6 -> 1 | B18: =F6+H6 -> 2 | C18: SPI AQ
A20: =SUM(A15:A18) -> 46 | B20: =SUM(B15:B18) -> 96

Sheet MEN-ROD
C1: =TODAY() -> 46076 | E1: =COUNTA(E3:E602) -> 445 | K1: A REMPLIR PAR LE BE OBLIGATOIRE
A2: Code OEIE | B2: DRE | C2: DRE | D2: ETAT | E2: POI | F2: SJ | G2: CAFF | H2: Mémo Chaf | I2: VILLE | J2: ADRESSE | K2: DATE VT | L2: COMMENTAIRES | M2: CTC
A3: ROD401264 | B3: 46091 | C3: =VLOOKUP(E3, $A$2:$E$822, 2, FALSE) -> #N/A | D3: 14 POI EN TRAVAUX | E3: ROD401938 | F3: V1 | G3: M | H3: DMS | I3: SALLES CURAN | J3: 8 RUE DU COUVENT | K3: 45680 | L3: 13/05:les travaux seront effectués dans 2 mois (lié au ROD401689) | M3: 682776141
A4: ROD401442 | B4: 46286 | C4: =VLOOKUP(E4, $A$2:$E$822, 2, FALSE) -> #N/A | D4: 14 POI EN TRAVAUX | E4: ROD402078 | F4: AZ | G4: M | I4: ROQUEFORT SUR SOULZON | J4: L AIRE VIEILLE
A5: ROD401602 | B5: 46097 | C5: =VLOOKUP(E5, $A$2:$E$822, 2, FALSE) -> #N/A | D5: 14 POI EN TRAVAUX | E5: ROD500031 | F5: 5S | I5: SAINT JEAN DELNOUS | J5: 38 PL SAINT JEAN | K5: 45672
A6: ROD401787 | B6: 46090 | C6: =VLOOKUP(E6, $A$2:$E$822, 2, FALSE) -> #N/A | D6: 14 POI EN TRAVAUX | E6: ROD500252 | F6: RI | G6: M | I6: SAINT JEAN DELNOUS | J6: 38 PL SAINT JEAN
A7: ROD401933 | B7: 46286 | C7: =VLOOKUP(E7, $A$2:$E$822, 2, FALSE) -> #N/A | D7: 14 POI EN TRAVAUX | E7: ROD500376 | F7: 5T | G7: M | I7: PONT DE SALARS | J7: CAMBOULAS
A8: ROD401967 | B8: 46111 | C8: =VLOOKUP(E8, $A$2:$E$822, 2, FALSE) -> #N/A | D8: 14 POI EN TRAVAUX | E8: ROD500597 | F8: CN | I8: BERTHOLENE | J8: RUE PONTS | L8: LIEE A LA ROD500598
A9: ROD402054 | B9: 46076 | C9: =VLOOKUP(E9, $A$2:$E$822, 2, FALSE) -> #N/A | D9: 14 POI EN TRAVAUX | E9: ROD500605 | F9: AZ | I9: AGUESSAC | J9: 21 ROUTE ST GERMAIN | K9: 45771
A10: ROD402079 | B10: 46035 | C10: =VLOOKUP(E10, $A$2:$E$822, 2, FALSE) -> #N/A | D10: 14 POI EN TRAVAUX | E10: ROD500621 | F10: OT | I10: VILLEFRANCHE DE PANAT | J10: 1 AVENUE DU SEGALA | K10: 45785
A11: ROD500238 | B11: 46079 | C11: =VLOOKUP(E11, $A$2:$E$822, 2, FALSE) -> #N/A | D11: 14 POI EN TRAVAUX | E11: ROD500717 | F11: CR | I11: BERTHOLENE | J11: RUE PONTS BERTHOLENE
A12: ROD500263 | B12: 45994 | C12: =VLOOKUP(E12, $A$2:$E$822, 2, FALSE) -> #N/A | D12: 14 POI EN TRAVAUX | E12: ROD500644 | F12: D3 | I12: LA CAVALERIE | J12: 603 AV SIMONE VEIL | K12: 45780
A13: ROD500269 | B13: 46072 | C13: =VLOOKUP(E13, $A$2:$E$822, 2, FALSE) -> #N/A | D13: 14 POI EN TRAVAUX | E13: ROD500797 | F13: DQ | G13: M | I13: SYLVANES | J13: Chemin de Maxels
A14: ROD500302 | B14: 46252 | C14: =VLOOKUP(E14, $A$2:$E$822, 2, FALSE) -> #N/A | D14: 14 POI EN TRAVAUX | E14: ROD500780 | F14: OI | G14: M | I14: BROMMAT | J14: Rue de la Grange | K14: en cours | M14: 680459771
A15: ROD500323 | B15: 46076 | C15: =VLOOKUP(E15, $A$2:$E$822, 2, FALSE) -> #N/A | D15: 14 POI EN TRAVAUX | E15: ROD501003 | F15: VX | G15: M | I15: BROMMAT | J15: RUE DE LA GRANGE | L15: ROD500780
A16: ROD500345 | B16: 46099 | C16: =VLOOKUP(E16, $A$2:$E$822, 2, FALSE) -> #N/A | D16: 14 POI EN TRAVAUX | E16: ROD401858 | F16: AZ | I16: LIOUJAS LA LOUBIERE | J16: IMP DU COMBAL
A17: ROD500346 | B17: 46031 | C17: =VLOOKUP(E17, $A$2:$E$822, 2, FALSE) -> #N/A | D17: 14 POI EN TRAVAUX | E17: ROD501105 | F17: P0 | G17: M | I17: VABRES L ABBAYE | J17: 505 CH DES CERISIERS
A18: ROD500362 | B18: 46044 | C18: =VLOOKUP(E18, $A$2:$E$822, 2, FALSE) -> #N/A | D18: 14 POI EN TRAVAUX | E18: ROD500905 | F18: D3 | I18: NANT | J18: LA MOULINE | K18: 45832
A19: ROD500391 | B19: 46101 | C19: =VLOOKUP(E19, $A$2:$E$822, 2, FALSE) -> #N/A | D19: 14 POI EN TRAVAUX | E19: ROD500122 | F19: D3 | I19: LAGUIOLE | J19: LA SOURCE
A20: ROD500442 | B20: 46091 | C20: =VLOOKUP(E20, $A$2:$E$822, 2, FALSE) -> #N/A | D20: 14 POI EN TRAVAUX | E20: ROD501153 | F20: CN | I20: SEVERAC D AVEYRON | J20: 2 RUE DE LA CROUZETTE | K20: 45874
A21: ROD500499 | B21: 46086 | C21: =VLOOKUP(E21, $A$2:$E$822, 2, FALSE) -> #N/A | D21: 14 POI EN TRAVAUX | E21: ROD501245 | F21: AZ | I21: MONTLAUR | J21: 166 CH DU MAS DE DAURELLE | K21: 45901 | L21: Demande DTA le 6/10
A22: ROD500519 | B22: 46020 | C22: =VLOOKUP(E22, $A$2:$E$822, 2, FALSE) -> #N/A | D22: 14 POI EN TRAVAUX | E22: ROD500756 | F22: 5I | I22: SAINT JEAN DU BRUEL | J22: RTE DE SEINGLEYS
A23: ROD500565 | B23: 46076 | C23: =VLOOKUP(E23, $A$2:$E$822, 2, FALSE) -> #N/A | D23: 14 POI EN TRAVAUX | E23: ROD501111 | F23: V1 | G23: C | I23: LE FEL | J23: 380 CH DU PUECH DE CASSOS
A24: ROD500627 | B24: 46086 | C24: =VLOOKUP(E24, $A$2:$E$822, 2, FALSE) -> #N/A | D24: 14 POI EN TRAVAUX | E24: ROD501229 | F24: D3 | G24: C | I24: SAINT JEAN DU BRUEL | J24: RTE NANT | K24: 45890
A25: ROD500638 | B25: 46078 | C25: =VLOOKUP(E25, $A$2:$E$822, 2, FALSE) -> #N/A | D25: 14 POI EN TRAVAUX | E25: ROD501747 | F25: GC | G25: M | I25: BROMMAT | J25: RUE DE LA GRANGE | L25: liée à la ROD501003
A26: ROD500708 | B26: 46086 | C26: =VLOOKUP(E26, $A$2:$E$822, 2, FALSE) -> #N/A | D26: 14 POI EN TRAVAUX | E26: ROD500610 | F26: 5S | I26: MILLAU | J26: 16B BD AYROLLE
A27: ROD500710 | B27: 46231 | C27: =VLOOKUP(E27, $A$2:$E$822, 2, FALSE) -> #N/A | D27: 14 POI EN TRAVAUX | E27: ROD500387 | F27: D3 | I27: SAINT AFFRIQUE | J27: 2 RUE JEAN BOUDOU
A28: ROD500727 | B28: 46272 | C28: =VLOOKUP(E28, $A$2:$E$822, 2, FALSE) -> #N/A | D28: 14 POI EN TRAVAUX | E28: ROD501175 | F28: D3 | G28: C | I28: VILLEFRANCHE DE PANAT | J28: 6 AV DE LA PLAGE | K28: 45876
A29: ROD500728 | B29: 46084 | C29: =VLOOKUP(E29, $A$2:$E$822, 2, FALSE) -> #N/A | D29: 14 POI EN TRAVAUX | E29: ROD500730 | F29: 5J | G29: M | I29: CAMBOULAS | J29: PONT DE SALARS
A30: ROD500755 | B30: 46087 | C30: =VLOOKUP(E30, $A$2:$E$822, 2, FALSE) -> #N/A | D30: 14 POI EN TRAVAUX | E30: ROD500423 | F30: D3 | G30: M | I30: CASSAGNES BEGONHES | J30: LE BOUYSSONIS
A31: ROD500771 | B31: 46213 | C31: =VLOOKUP(E31, $A$2:$E$822, 2, FALSE) -> #N/A | D31: 14 POI EN TRAVAUX | E31: ROD500273 | F31: OI | G31: M | I31: COUBISOU | J31: ROUTE DE LACAZE | K31: 45770
A32: ROD500783 | B32: 46091 | C32: =VLOOKUP(E32, $A$2:$E$822, 2, FALSE) -> #N/A | D32: 14 POI EN TRAVAUX | E32: ROD500496 | F32: OI | G32: M | I32: COUBISOU | J32: ROUTE DE LACAZE
A33: ROD500816 | B33: 46248 | C33: =VLOOKUP(E33, $A$2:$E$822, 2, FALSE) -> #N/A | D33: 14 POI EN TRAVAUX | E33: ROD501002 | F33: VX | G33: M | I33: COUBISOU | J33: ROUTE DE LACAZE | L33: ROD500273
A34: ROD500862 | B34: 46239 | C34: =VLOOKUP(E34, $A$2:$E$822, 2, FALSE) -> #N/A | D34: 14 POI EN TRAVAUX | E34: ROD500369 | F34: OI | G34: M | I34: MILLAU | J34: CHEMIN DES HAUTS DE PRIGNOLLES | K34: 20/03/2025 en cours | L34: 13/05: un mail a été envoyé | M34: 565608331
A35: ROD500885 | B35: 46079 | C35: =VLOOKUP(E35, $A$2:$E$822, 2, FALSE) -> #N/A | D35: 14 POI EN TRAVAUX | E35: ROD501131 | F35: 5S | G35: C | I35: BOZOULS | J35: AVENUE COMBE CROZES | L35: mail envoyé au client
A36: ROD500893 | B36: 46076 | C36: =VLOOKUP(E36, $A$2:$E$822, 2, FALSE) -> #N/A | D36: 14 POI EN TRAVAUX | E36: ROD501566 | F36: OT | G36: C | I36: CORNUS | J36: 76 RUE DE LA TRIVALLE | K36: 45951
A37: ROD500992 | B37: 46101 | C37: =VLOOKUP(E37, $A$2:$E$822, 2, FALSE) -> #N/A | D37: 14 POI EN TRAVAUX | E37: ROD500264 | F37: OI | G37: C | I37: CAMBOULAZET | J37: RTE DE LA RIVIERE | K37: 45715 | L37: FIN TVX: FIN JUIN 2025 | M37: 565451655
A38: ROD500998 | B38: 46106 | C38: =VLOOKUP(E38, $A$2:$E$822, 2, FALSE) -> #N/A | D38: 14 POI EN TRAVAUX | E38: ROD500144 | F38: OI | G38: M | I38: SAINT GENIEZ D OLT ET D AUBRAC | J38: 5802 PL GEN DE GAULLE | K38: 45692
A39: ROD501081 | B39: 46092 | C39: =VLOOKUP(E39, $A$2:$E$822, 2, FALSE) -> #N/A | D39: 14 POI EN TRAVAUX | E39: ROD501365 | F39: 5T | G39: C | H39: Att travaux ACF011 | I39: ESPEYRAC | J39: RTE NOLORGUES | K39: 45918
A40: ROD501101 | B40: 46092 | C40: =VLOOKUP(E40, $A$2:$E$822, 2, FALSE) -> #N/A | D40: 14 POI EN TRAVAUX | E40: ROD500574 | F40: 5J | G40: C | I40: LUC LA PRIMAUBE | J40: RTE DE LA BOISSONNADE | K40: 30/04/2025 9H
A41: ROD501142 | B41: 46078 | C41: =VLOOKUP(E41, $A$2:$E$822, 2, FALSE) -> #N/A | D41: 14 POI EN TRAVAUX | E41: ROD501280 | F41: OT | I41: SEVERAC D AVEYRON | J41: 1 COURRY | L41: Liée a la ROD500704
A42: ROD501148 | B42: 46252 | C42: =VLOOKUP(E42, $A$2:$E$822, 2, FALSE) -> #N/A | D42: 14 POI EN TRAVAUX | E42: ROD501449 | F42: 5S | I42: SAINT AFFRIQUE | J42: R SOUBAYROL
A43: ROD501160 | B43: 46090 | C43: =VLOOKUP(E43, $A$2:$E$822, 2, FALSE) -> #N/A | D43: 14 POI EN TRAVAUX | E43: ROD500525 | F43: D3 | I43: CORNUS | J43: 76 RUE DE LA TRIVALLE
A44: ROD501165 | B44: 46072 | C44: =VLOOKUP(E44, $A$2:$E$822, 2, FALSE) -> #N/A | D44: 14 POI EN TRAVAUX | E44: ROD401748 | F44: OI | G44: M | I44: MOUNES PROHENCOU | J44: 1 CH DE ROUZET | K44: Retour le 24/09 | L44: à refaire
A45: ROD501172 | B45: 46079 | C45: =VLOOKUP(E45, $A$2:$E$822, 2, FALSE) -> #N/A | D45: 14 POI EN TRAVAUX | E45: ROD501541 | F45: CC | J45: LA BORIE DE CAZES | K45: 45978 | L45: A remonter par chaima
A46: ROD501174 | B46: 46076 | C46: =VLOOKUP(E46, $A$2:$E$822, 2, FALSE) -> #N/A | D46: 14 POI EN TRAVAUX | E46: ROD500290 | F46: CC | J46: RTE DE BORN | K46: 45959 | L46: contacter les clients : 0565467019 // 0565467377: client injoinable , un rappel est fait le 4/11/ retour urgent
A47: ROD501190 | B47: 46104 | C47: =VLOOKUP(E47, $A$2:$E$822, 2, FALSE) -> #N/A | D47: 14 POI EN TRAVAUX | E47: ROD501928 | F47: VX | G47: M | I47: MILLAU | J47: CHEMIN DE PRIGNOLLES | L47: Pas besoin de VT
A48: ROD501270 | B48: 46090 | C48: =VLOOKUP(E48, $A$2:$E$822, 2, FALSE) -> #N/A | D48: 14 POI EN TRAVAUX | E48: ROD501040 | F48: L0 | G48: M | I48: BELMONT SUR RANCE | J48: 1190 RTE DE LA COMBE | K48: ROD501566
A49: ROD501318 | B49: 46083 | C49: =VLOOKUP(E49, $A$2:$E$822, 2, FALSE) -> #N/A | D49: 14 POI EN TRAVAUX | E49: ROD500526 | F49: CC | G49: C | H49: Manque reprise cable cuivre | I49: LA SELVE | J49: RTE DE VAYSSOUS | K49: 07/05/2025-Retour le 12/09
A50: ROD501323 | B50: 46092 | C50: =VLOOKUP(E50, $A$2:$E$822, 2, FALSE) -> #N/A | D50: 14 POI EN TRAVAUX | E50: ROD500004 | F50: CC | G50: C | I50: SAINT ROME DE TARN | J50: LD LES BOUZIGUES | L50: La region ou les appuis page 5 sont inaccessibles. de proche ou de loin
A51: ROD501332 | B51: 46218 | C51: =VLOOKUP(E51, $A$2:$E$822, 2, FALSE) -> #N/A | D51: 14 POI EN TRAVAUX | E51: ROD401945 | F51: VX | G51: M | I51: LUC LA PRIMAUBE | J51: RUE DES LANDES
A52: ROD501346 | B52: 46119 | C52: =VLOOKUP(E52, $A$2:$E$822, 2, FALSE) -> #N/A | D52: 14 POI EN TRAVAUX | E52: ROD500837 | F52: OI | G52: M | I52: BOZOULS | J52: 8 AV ARSENE | K52: 46000 | L52: Zohra
A53: ROD501348 | B53: 46079 | C53: =VLOOKUP(E53, $A$2:$E$822, 2, FALSE) -> #N/A | D53: 14 POI EN TRAVAUX | E53: ROD500267 | F53: V1 | G53: M | I53: ANGLARS SAINT FELIX | J53: 2 RTE DES ECOLIERS
A54: ROD501366 | B54: 46080 | C54: =VLOOKUP(E54, $A$2:$E$822, 2, FALSE) -> #N/A | D54: 14 POI EN TRAVAUX | E54: ROD501641 | F54: 5I | I54: SEVERAC D AVEYRON | J54: RUE DE LA CROUZETTE
A55: ROD501394 | B55: 46078 | C55: =VLOOKUP(E55, $A$2:$E$822, 2, FALSE) -> #N/A | D55: 14 POI EN TRAVAUX | E55: ROD501439 | F55: D3 | G55: C | I55: PRADINAS | J55: 490 ROUTE DE FONSALADE | K55: 45930 | L55: VT effectuée aujourd'hui, à remonter par sondos
A56: ROD501424 | B56: 46391 | C56: =VLOOKUP(E56, $A$2:$E$822, 2, FALSE) -> #N/A | D56: 14 POI EN TRAVAUX | E56: ROD501253 | F56: CC | I56: ESPALION | J56: LA REMISE | K56: 46000 | L56: GC términé par ENEDIS/44.51259 ; 2.73503
A57: ROD501437 | B57: 46090 | C57: =VLOOKUP(E57, $A$2:$E$822, 2, FALSE) -> #N/A | D57: 14 POI EN TRAVAUX | E57: ROD500237 | F57: 5S | I57: COMBRET | J57: LES BORIES
A58: ROD501438 | B58: 46076 | C58: =VLOOKUP(E58, $A$2:$E$822, 2, FALSE) -> #N/A | D58: 14 POI EN TRAVAUX | E58: ROD500588 | F58: D3 | I58: CAMJAC | J58: 1107 RTE DE LA BOULE
A59: ROD501453 | B59: 46092 | C59: =VLOOKUP(E59, $A$2:$E$822, 2, FALSE) -> #N/A | D59: 14 POI EN TRAVAUX | E59: ROD500778 | F59: OI | G59: M | I59: MILLAU | J59: Place Voultre | L59: travaux pas encore commencés /mail envoyé au client le 27/10
A60: ROD501475 | B60: 46240 | C60: =VLOOKUP(E60, $A$2:$E$822, 2, FALSE) -> #N/A | D60: 14 POI EN TRAVAUX | E60: ROD500831 | F60: VX | G60: M | I60: MILLAU | J60: 1 PL VOULTRE
A61: ROD501476 | B61: ----- | C61: =VLOOKUP(E61, $A$2:$E$822, 2, FALSE) -> #N/A | D61: 14 POI EN TRAVAUX | E61: ROD501258 | F61: DQ | G61: M | I61: LESTRADE ET THOUELS | J61: RUE DES LOISIRS | L61: Le VT a été effectué. Une nouvelle solution a été proposée par le piqueteur en raison de l’inexistence du PVC 45.Email explicatif sera fait
A62: ROD501492 | B62: 46090 | C62: =VLOOKUP(E62, $A$2:$E$822, 2, FALSE) -> #N/A | D62: 14 POI EN TRAVAUX | E62: ROD500124 | F62: RI | G62: M | I62: SAINT HIPPOLYTE | J62: LD LA CAPELLE | K62: 46022 | L62: 44.73827;2.59865 /SONDOS
A63: ROD501498 | B63: 46219 | C63: =VLOOKUP(E63, $A$2:$E$822, 2, FALSE) -> #N/A | D63: 14 POI EN TRAVAUX | E63: ROD401937 | F63: V1 | G63: M | I63: VILLEFRANCHE DE ROUERGUE | J63: 3 AV PAUL RAMADIER | K63: 45980 | L63: Photo poteau pour calcul de charge
A64: ROD501500 | B64: 46051 | C64: =VLOOKUP(E64, $A$2:$E$822, 2, FALSE) -> #N/A | D64: 14 POI EN TRAVAUX | E64: ROD500282 | F64: VX | G64: M | I64: SAINT GENIEZ D OLT ET D AUBRAC | J64: 5802 PL GEN DE GAULLE | L64: Dossier inexistant
A65: ROD501565 | B65: 46029 | C65: =VLOOKUP(E65, $A$2:$E$822, 2, FALSE) -> #N/A | D65: 14 POI EN TRAVAUX | E65: ROD400465 | F65: V1 | G65: M | I65: SAINT AFFRIQUE | J65: 5 R TRAUPONT | L65: D2:Pas besoin de VT
A66: ROD501581 | B66: 46231 | C66: =VLOOKUP(E66, $A$2:$E$822, 2, FALSE) -> #N/A | D66: 14 POI EN TRAVAUX | E66: ROD501407 | F66: 72 | G66: M | I66: LUC LA PRIMAUBE | J66: 335 RUE DU RUISSEAU | K66: 46035 | L66: vérif travaux avec RDV
A67: ROD501651 | B67: 46077 | C67: =VLOOKUP(E67, $A$2:$E$822, 2, FALSE) -> #N/A | D67: 14 POI EN TRAVAUX | E67: ROD501601 | F67: CN | I67: RIVIERE SUR TARN | J67: Place des Marie Louise | K67: 46020
A68: ROD501652 | B68: 46034 | C68: =VLOOKUP(E68, $A$2:$E$822, 2, FALSE) -> #N/A | D68: 14 POI EN TRAVAUX | E68: ROD500210 | F68: CC | G68: C | I68: SYLVANES | J68: LE SARROS
A69: ROD501656 | B69: 46069 | C69: =VLOOKUP(E69, $A$2:$E$822, 2, FALSE) -> #N/A | D69: 14 POI EN TRAVAUX | E69: ROD500096 | F69: CC | G69: C | H69: Att steph | I69: COMBRET | J69: LE LENIE
A70: ROD501676 | B70: 46195 | C70: =VLOOKUP(E70, $A$2:$E$822, 2, FALSE) -> #N/A | D70: 14 POI EN TRAVAUX | E70: ROD501151 | F70: V1 | G70: C | I70: SAINT-MARTIN-DE-LENNE | J70: IMP DE LAUZERAL | K70: 05/08/2025 / Retour le 17/09
A71: ROD501677 | B71: 46042 | C71: =VLOOKUP(E71, $A$2:$E$822, 2, FALSE) -> #N/A | D71: 14 POI EN TRAVAUX | E71: ROD501264 | F71: CC | G71: C | I71: CASTELNAU DE MANDAILLES | J71: Place des Aludiers | K71: 46034 | L71: sondos
A72: ROD501681 | B72: 46051 | C72: =VLOOKUP(E72, $A$2:$E$822, 2, FALSE) -> #N/A | D72: 14 POI EN TRAVAUX | E72: ROD501506 | F72: OT | I72: ESPALION | J72: RUE DU SELZET
A73: ROD501694 | B73: 46251 | C73: =VLOOKUP(E73, $A$2:$E$822, 2, FALSE) -> #N/A | D73: 14 POI EN TRAVAUX | E73: ROD501001 | F73: VX | G73: M | I73: BOZOULS | J73: 8 AV ARSENE RATIER | L73: ROD500837
A74: ROD501704 | B74: 46164 | C74: =VLOOKUP(E74, $A$2:$E$822, 2, FALSE) -> #N/A | D74: 14 POI EN TRAVAUX | E74: ROD300381 | F74: VX | G74: M | I74: MILLAU | J74: 180 RUE AUGUSTE MONJOLS | L74: Disponibilité PA + photos CAPFT
A75: ROD501705 | B75: 46241 | C75: =VLOOKUP(E75, $A$2:$E$822, 2, FALSE) -> #N/A | D75: 14 POI EN TRAVAUX | E75: ROD501521 | F75: RI | G75: M | I75: SAINT AFFRIQUE | J75: R SOUBAYROL
A76: ROD501725 | B76: 46090 | C76: =VLOOKUP(E76, $A$2:$E$822, 2, FALSE) -> #N/A | D76: 14 POI EN TRAVAUX | E76: ROD501828 | F76: 5I | I76: MILLAU | J76: BD AYROLLE | K76: 46037 | L76: controle cable existant sur façade selon la commune
A77: ROD501726 | B77: 46086 | C77: =VLOOKUP(E77, $A$2:$E$822, 2, FALSE) -> #N/A | D77: 14 POI EN TRAVAUX | E77: ROD600088 | F77: VZ | G77: M | I77: LUC LA PRIMAUBE | J77: RUE DU RUISSEAU DE CAYRAC | L77: pas besoin VT
A78: ROD501729 | B78: 46097 | C78: =VLOOKUP(E78, $A$2:$E$822, 2, FALSE) -> #N/A | D78: 14 POI EN TRAVAUX | E78: ROD500889 | F78: DQ | G78: M | I78: BELMONT SUR RANCE | J78: 2 R EGLISE
A79: ROD501764 | B79: 46087 | C79: =VLOOKUP(E79, $A$2:$E$822, 2, FALSE) -> #N/A | D79: 14 POI EN TRAVAUX | E79: ROD501926 | F79: D3 | I79: CALMONT | J79: 3869 ROUTE DE BARAQUEVILLE | K79: 45999 | L79: chaima
A80: ROD501766 | B80: 46223 | C80: =VLOOKUP(E80, $A$2:$E$822, 2, FALSE) -> #N/A | D80: 14 POI EN TRAVAUX | E80: ROD501463 | F80: D3 | I80: GAILLAC-D'AVEYRON | J80: 170 RUE DU PUECH | K80: 45937
A81: ROD501767 | B81: 46199 | C81: =VLOOKUP(E81, $A$2:$E$822, 2, FALSE) -> #N/A | D81: 14 POI EN TRAVAUX | E81: ROD502116 | F81: D3 | I81: CAMJAC | J81: 77 IMP DE LA TREMOLEDE | K81: 46030 | L81: SONDOS
A82: ROD501800 | B82: 46080 | C82: =VLOOKUP(E82, $A$2:$E$822, 2, FALSE) -> #N/A | D82: 14 POI EN TRAVAUX | E82: ROD501273 | F82: D3 | G82: C | I82: SALMIECH | J82: 512 AV GEORGES DESIRAT | K82: 45981 | L82: En attente réfus/acceptation par mairie(ralence faite le 02/01)
A83: ROD501801 | B83: 46069 | C83: =VLOOKUP(E83, $A$2:$E$822, 2, FALSE) -> #N/A | D83: 14 POI EN TRAVAUX | E83: ROD401450 | F83: OI | G83: M | I83: AGUESSAC | J83: LESTRADE | K83: 46064 | L83: zohra
A84: ROD501808 | B84: 46083 | C84: =VLOOKUP(E84, $A$2:$E$822, 2, FALSE) -> #N/A | D84: 14 POI EN TRAVAUX | E84: ROD600200 | F84: VX | G84: M | I84: RODEZ | J84: BD DENYS PUECH | K84: 46064 | L84: zohra
A85: ROD501817 | B85: 46090 | C85: =VLOOKUP(E85, $A$2:$E$822, 2, FALSE) -> #N/A | D85: 14 POI EN TRAVAUX | E85: ROD502024 | F85: 9I | G85: C | I85: LIOUJAS LA LOUBIERE | J85: 2223 ROUTE DES NAUCELATS | K85: 46029 | L85: RDV entre 8h et 9h
A86: ROD501821 | B86: 46062 | C86: =VLOOKUP(E86, $A$2:$E$822, 2, FALSE) -> #N/A | D86: 14 POI EN TRAVAUX | E86: ROD600181 | F86: 5S | G86: C | I86: LUC LA PRIMAUBE | J86: AV RODEZ | K86: 46052 | L86: ZOHRA | M86: +33 6 86 16 62 62
A87: ROD501823 | B87: 46083 | C87: =VLOOKUP(E87, $A$2:$E$822, 2, FALSE) -> #N/A | D87: 14 POI EN TRAVAUX | E87: ROD500822 | F87: D3 | H87: Retour de VT | I87: CURAN | J87: 103 CHEMIN DE TREBONS | K87: 46056 | L87: en att retour mail ou confirmation trvx appel fait le 04/02; sms reçus de confirmation / relance mail 09/02
A88: ROD501831 | B88: 46078 | C88: =VLOOKUP(E88, $A$3:$E$942, 2, FALSE) -> #N/A | D88: 14 POI EN TRAVAUX | E88: NIM500846 | F88: VX | G88: M | I88: REDESSAN | J88: LOT LE COURBOUSSOL
A89: ROD501843 | B89: 46254 | C89: =VLOOKUP(E89, $A$3:$E$942, 2, FALSE) -> #N/A | D89: 14 POI EN TRAVAUX | E89: NIM500791 | F89: VX | G89: M | I89: SAINT GERVASY | J89: RTE DE REDESSAN
A90: ROD501850 | B90: 46122 | C90: =VLOOKUP(E90, $A$3:$E$942, 2, FALSE) -> #N/A | D90: 14 POI EN TRAVAUX | E90: NIM500735 | F90: MI | G90: M | I90: NIMES | J90: 99 IMP DES HUPPES
A91: ROD501851 | B91: 46108 | C91: =VLOOKUP(E91, $A$3:$E$942, 2, FALSE) -> #N/A | D91: 14 POI EN TRAVAUX | E91: NIM401193 | F91: VX | G91: M | I91: CAVEIRAC | J91: 2 RTE DE NIMES
A92: ROD501871 | B92: 46195 | C92: =VLOOKUP(E92, $A$3:$E$942, 2, FALSE) -> #N/A | D92: 14 POI EN TRAVAUX | E92: MPL500844 | F92: VX | G92: C | I92: MONTPELLIER | J92: 47 R DE L AMANDIER | L92: Liée MPL500733
A93: ROD501874 | B93: 46083 | C93: =VLOOKUP(E93, $A$3:$E$942, 2, FALSE) -> #N/A | D93: 14 POI EN TRAVAUX | E93: MPL500641 | F93: VX | G93: M | I93: SETE | J93: 33 R GARENNE
A94: ROD501876 | B94: 46267 | C94: =VLOOKUP(E94, $A$3:$E$942, 2, FALSE) -> #N/A | D94: 14 POI EN TRAVAUX | E94: MPL500013 | F94: VZ | G94: C | I94: GRABELS | J94: 1227 RUE DE LA VALSIERE
A95: ROD501887 | B95: 46087 | C95: =VLOOKUP(E95, $A$3:$E$942, 2, FALSE) -> #N/A | D95: 14 POI EN TRAVAUX | E95: MPL401799 | F95: VZ | G95: C | I95: GRABELS | J95: 60 IMPASSE ANTOINE SAPORTA
A96: ROD501913 | B96: 46087 | C96: =VLOOKUP(E96, $A$3:$E$942, 2, FALSE) -> #N/A | D96: 14 POI EN TRAVAUX | E96: MPL401053 | F96: VX | G96: M | I96: MONTPELLIER | J96: 9 R ABERT
A97: ROD501914 | B97: 46072 | C97: =VLOOKUP(E97, $A$3:$E$942, 2, FALSE) -> #N/A | D97: 14 POI EN TRAVAUX | E97: MEN500648 | F97: 5I | G97: M | I97: FLORAC 3 RIVIERES | J97: 13B AV JEAN MONESTIER | L97: liée à MEN300765/ dépose de PB et pose dans chbre
A98: ROD501917 | B98: 46090 | C98: =VLOOKUP(E98, $A$3:$E$942, 2, FALSE) -> #N/A | D98: 14 POI EN TRAVAUX | E98: MEN500582 | F98: 5T | I98: ISSARLES | J98: 415 RTE DE LA ROUME
A99: ROD501933 | B99: 46097 | C99: =VLOOKUP(E99, $A$3:$E$942, 2, FALSE) -> #N/A | D99: 14 POI EN TRAVAUX | E99: MEN500581 | F99: OT | I99: BANASSAC CANILHAC | J99: ZONE ARTISANALE CAPJALAT | K99: 45982 | L99: A remonter par chaima/liée a la MEN500038
A100: ROD501939 | B100: 46084 | C100: =VLOOKUP(E100, $A$3:$E$942, 2, FALSE) -> #N/A | D100: 14 POI EN TRAVAUX | E100: MEN500510 | F100: RI | G100: C | I100: LACHAMP-RIBENNES | J100: CHASSAGNES | L100: MEN500416
...

Sheet QPR-CRO
A1: =TODAY() -> 46076 | E1: =COUNTA(E3:E672) -> 347 | J1: A REMPLIR PAR LE BE OBLIGATOIRE
A2: Code OEIE | B2: DRE | C2: DRE | D2: ETAT | E2: POI | F2: SJ | G2: Mémo Chaf | H2: VILLE | I2: ADRESSE | J2: DATE VT | K2: Chargé | L2: COMMENTAIRES
A3: QPR600247 | B3: 46083 | C3: =VLOOKUP(E3, $A$3:$E$704, 2, FALSE) -> #N/A | D3: 15 POI FACTU | E3: VAN004278 | F3: QQ | H3: Quiberon | I3: 7 QU OCEAN | J3: 45947 | L3: Same as VAN004277
C4: =VLOOKUP(E4, $A$3:$E$704, 2, FALSE) -> #N/A | D4: 15 POI FACTU | E4: VAN500832 | F4: B3 | G4: S04 CRASH | H4: NIVILLAC | I4: RUE JOSEPH SAUVEUR | J4: 46030 | K4: amrou
A5: QPR500885 | B5: 46192 | C5: =VLOOKUP(E5, $A$3:$E$704, 2, FALSE) -> #N/A | D5: 14.1 AT RETOUR DOE | E5: QPR500660 | F5: F9 | H5: Quimper | I5: 12 R BECQUEREL | J5: VT faite le 09/07
A6: LOR500732 | B6: 46080 | C6: =VLOOKUP(E6, $A$3:$E$704, 2, FALSE) -> #N/A | D6: 14.1 AT RETOUR DOE | E6: QPR500654 | F6: 5Y | G6: Att GEOREF | H6: Plogastel-Saint-Germain | I6: 12 STAN KELERON | J6: 45826
A7: RRE501172 | B7: 46072 | C7: =VLOOKUP(E7, $A$3:$E$704, 2, FALSE) -> #N/A | D7: 14.1 AT RETOUR DOE | E7: QPR501059 | F7: F9 | G7: proposition d'attachement | H7: Plouhinec, Finistère | I7: R DE LA CROIX DONNART | J7: VT faite le 09/07
A8: RRE501199 | B8: 46115 | C8: =VLOOKUP(E8, $A$3:$E$704, 2, FALSE) -> #N/A | D8: 14.1 AT RETOUR DOE | E8: QPR500784 | F8: JG | G8: Manque DOE + cloture LINE | H8: Loctudy | I8: 25 RUE DU PORT | J8: à remonter par ghada
A9: VAN501393 | B9: 46097 | C9: =VLOOKUP(E9, $A$3:$E$704, 2, FALSE) -> #N/A | D9: 14.1 AT RETOUR DOE | E9: QPR500679 | F9: 5Y | G9: Manque RT GCD020 GEO cloturé | H9: Plobannalec-Lesconil | I9: 2B RUE DE KARREK KREIZ | J9: 45825
A10: QPR500983 | B10: 46086 | C10: =VLOOKUP(E10, $A$3:$E$704, 2, FALSE) -> #N/A | D10: 14.1 AT RETOUR DOE | E10: QPR401859
A11: LOR500806 | B11: 46296 | C11: =VLOOKUP(E11, $A$3:$E$704, 2, FALSE) -> #N/A | D11: 14.1 AT RETOUR DOE | E11: QPR402292
A12: QPR501023 | B12: 46063 | C12: =VLOOKUP(E12, $A$3:$E$704, 2, FALSE) -> #N/A | D12: 14.1 AT RETOUR DOE | E12: QPR501038 | F12: 5S | H12: Quéménéven | I12: TY FORN | L12: urgent mail envoyé concernant
A13: LOR500883 | B13: 46149 | C13: =VLOOKUP(E13, $A$3:$E$704, 2, FALSE) -> #N/A | D13: 14.1 AT RETOUR DOE | E13: LOR400490 | F13: 5Y | G13: Factu a faire | H13: PLUMELIAU BIEUZY | I13: 10 IMP DES NENUPHARS
A14: VAN501638 | B14: 46084 | C14: =VLOOKUP(E14, $A$3:$E$704, 2, FALSE) -> #N/A | D14: 14.1 AT RETOUR DOE | E14: VAN401205 | G14: PAS Accès LINE CRASH
A15: LOR500901 | B15: 46063 | C15: =VLOOKUP(E15, $A$3:$E$704, 2, FALSE) -> #N/A | D15: 14.1 AT RETOUR DOE | E15: QPR300617 | G15: Cloture LINE
A16: LOR500925 | B16: 46119 | C16: =VLOOKUP(E16, $A$3:$E$704, 2, FALSE) -> #N/A | D16: 14.1 AT RETOUR DOE | E16: RRE400009 | G16: Attente DOE + Attachement
A17: RRE501484 | B17: 45985 | C17: =VLOOKUP(E17, $A$3:$E$704, 2, FALSE) -> #N/A | D17: 14.1 AT RETOUR DOE | E17: VAN202306 | G17: Attente DOE + Attachement CRASH
A18: RRE501518 | B18: 46045 | C18: =VLOOKUP(E18, $A$3:$E$704, 2, FALSE) -> #N/A | D18: 14.1 AT RETOUR DOE | E18: QPR402301 | G18: RECOL LINE TIGRE OK
A19: RRE501554 | B19: 46073 | C19: =VLOOKUP(E19, $A$3:$E$704, 2, FALSE) -> #N/A | D19: 14.1 AT RETOUR DOE | E19: VAN402909 | G19: RECOL LINE TIGRE OK
A20: VAN501849 | B20: 46084 | C20: =VLOOKUP(E20, $A$3:$E$704, 2, FALSE) -> #N/A | D20: 14.1 AT RETOUR DOE | E20: RRE402429 | G20: Attente DOE + Attachement
A21: LOR501020 | B21: 46087 | C21: =VLOOKUP(E21, $A$3:$E$704, 2, FALSE) -> #N/A | D21: 14.1 AT RETOUR DOE | E21: RRE401267 | G21: Att modif Attachement
A22: QPR501326 | B22: 46084 | C22: =VLOOKUP(E22, $A$3:$E$704, 2, FALSE) -> #N/A | D22: 14.1 AT RETOUR DOE | E22: LOR401481 | G22: Clôture LINE
A23: LOR501040 | B23: 46756 | C23: =VLOOKUP(E23, $A$3:$E$704, 2, FALSE) -> #N/A | D23: 14.1 AT RETOUR DOE | E23: RRE402093 | G23: Clôture LINE
A24: LOR501041 | B24: 46083 | C24: =VLOOKUP(E24, $A$3:$E$704, 2, FALSE) -> #N/A | D24: 14.1 AT RETOUR DOE | E24: LOR401381 | G24: Clôture LINE CRASH
A25: QPR501355 | B25: 46097 | C25: =VLOOKUP(E25, $A$3:$E$704, 2, FALSE) -> #N/A | D25: 14.1 AT RETOUR DOE | E25: LOR401177 | G25: Clôture LINE
... A55: QPR501901 | B55: 46050 | C55: =VLOOKUP(E55, $A$3:$E$704, 2, FALSE) -> #N/A | D55: 14.1 AT RETOUR DOE | E55: QPR400498 | G55: GEOREF EN ATT
A56: QPR501902 | B56: 46073 | C56: =VLOOKUP(E56, $A$3:$E$704, 2, FALSE) -> #N/A | D56: 14.1 AT RETOUR DOE | E56: QPR300168
A57: QPR501908 | B57: 46085 | C57: =VLOOKUP(E57, $A$3:$E$704, 2, FALSE) -> #N/A | D57: 14.1 AT RETOUR DOE | E57: QPR400186
A58: VAN502650 | B58: 46084 | C58: =VLOOKUP(E58, $A$3:$E$704, 2, FALSE) -> #N/A | D58: 14.1 AT RETOUR DOE | E58: QPR400286
A59: CRO500257 | B59: 46050 | C59: =VLOOKUP(E59, $A$3:$E$704, 2, FALSE) -> #N/A | D59: 14.1 AT RETOUR DOE | E59: BRS302246
A60: LOR501421 | B60: 46087 | C60: =VLOOKUP(E60, $A$3:$E$704, 2, FALSE) -> #N/A | D60: 14.1 AT RETOUR DOE | E60: QPR103602
A61: QPR501916 | B61: 46090 | C61: =VLOOKUP(E61, $A$3:$E$704, 2, FALSE) -> #N/A | D61: 14.1 AT RETOUR DOE | E61: QPR300274 | G61: REO ETUDE
A62: QPR501919 | B62: 46069 | C62: =VLOOKUP(E62, $A$3:$E$704, 2, FALSE) -> #N/A | D62: 14.1 AT RETOUR DOE | E62: QPR300167
A63: CRO500258 | B63: 46090 | C63: =VLOOKUP(E63, $A$3:$E$704, 2, FALSE) -> #N/A | D63: 14.1 AT RETOUR DOE | E63: VAN202637
A64: LOR501433 | B64: 46097 | C64: =VLOOKUP(E64, $A$3:$E$704, 2, FALSE) -> #N/A | D64: 14.1 AT RETOUR DOE | E64: RRE402217
A65: VAN502671 | B65: 46084 | C65: =VLOOKUP(E65, $A$3:$E$704, 2, FALSE) -> #N/A | D65: 14.1 AT RETOUR DOE | E65: RRE500820 | F65: KA | H65: Val-d'Izé | I65: LD LES NACHARDAIS | J65: Photos sur sharepoint
A66: CRO500259 | B66: 46091 | C66: =VLOOKUP(E66, $A$3:$E$704, 2, FALSE) -> #N/A | D66: 14.1 AT RETOUR DOE | E66: RRE400998 | F66: JG | G66: DOE + proposition att | H66: PIRE CHANCE | I66: R DE BOISTRUDAN | J66: ? | L66: tous les documents envoyées à cynthia ou stephane
A67: QPR501964 | B67: 46078 | C67: =VLOOKUP(E67, $A$3:$E$704, 2, FALSE) -> #N/A | D67: 14.1 AT RETOUR DOE | E67: VAN501004 | F67: KA | G67: Manque cloture ACF010 | H67: Le Cours | I67: KERBRANQUET | J67: à remonter par khadher
A68: QPR501965 | B68: 46076 | C68: =VLOOKUP(E68, $A$3:$E$704, 2, FALSE) -> #N/A | D68: 14.1 AT RETOUR DOE | E68: QPR500419 | F68: KA | G68: Manque cloture ACF010 + ACF011 + manque DMS + proposition attachement | H68: Pluguffan | I68: ROUTE DE LEUBIN | J68: 45854
A69: LOR501475 | B69: 46076 | C69: =VLOOKUP(E69, $A$3:$E$704, 2, FALSE) -> #N/A | D69: 14.1 AT RETOUR DOE | E69: QPR401299 | F69: 5Z | G69: Recollement a faire pas acces a LINE reesaye | H69: Audierne | I69: BOULEVARD JEAN MOULIN | J69: 45924
A70: LOR501031 | B70: 45953 | C70: =VLOOKUP(E70, $A$3:$E$704, 2, FALSE) -> #N/A | D70: 14 POI EN TRAVAUX | E70: LOR500521 | F70: KA | G70: Manque cloture ACF010 + manque transfert de cable sur appui 91501 et 91500 | H70: Saint-Caradec-Trégomel | I70: LANN ER MARECHAL | L70: à remonter par khadher
A71: LOR501442 | B71: 46097 | C71: =VLOOKUP(E71, $A$3:$E$704, 2, FALSE) -> #N/A | D71: 14 POI EN TRAVAUX | E71: VAN501000 | F71: KA | H71: Buléon | I71: KERGUIGNO | J71: 45848
A72: VAN502687 | B72: 46084 | C72: =VLOOKUP(E72, $A$3:$E$704, 2, FALSE) -> #N/A | D72: 14 POI EN TRAVAUX | E72: BRS402155 | F72: 5Y
A73: LOR501447 | B73: 46076 | C73: =VLOOKUP(E73, $A$3:$E$704, 2, FALSE) -> #N/A | D73: 14 POI EN TRAVAUX | E73: QPR401457
A74: VAN502694 | B74: 46084 | C74: =VLOOKUP(E74, $A$3:$E$704, 2, FALSE) -> #N/A | D74: 14 POI EN TRAVAUX | E74: LOR500542 | F74: ZJ | H74: Lorient | I74: 6 RUE EUGENE ANTHIOME | J74: 45849
A75: CRO500268 | B75: 46072 | C75: =VLOOKUP(E75, $A$3:$E$704, 2, FALSE) -> #N/A | D75: 14 POI EN TRAVAUX | E75: CRO500072 | F75: WY | H75: Lanvéoc | I75: 26 RUE DE TAL AR GROAS | J75: à refaire
A76: QPR501949 | B76: 46069 | C76: =VLOOKUP(E76, $A$3:$E$704, 2, FALSE) -> #N/A | D76: 14 POI EN TRAVAUX | E76: QPR401355 | F76: 5Z | H76: Plomeur | I76: RUE AR C HOAJOU | J76: à voir | L76: VOIR INFO SOGETREL
A77: VAN502718 | B77: 46090 | C77: =VLOOKUP(E77, $A$3:$E$704, 2, FALSE) -> #N/A | D77: 14 POI EN TRAVAUX | E77: RRE500282 | F77: QQ | H77: Retiers | I77: 6 LD LA GERARDAIS | J77: 23/07 à 8h
A78: VAN502724 | B78: 46084 | C78: =VLOOKUP(E78, $A$3:$E$704, 2, FALSE) -> #N/A | D78: 14 POI EN TRAVAUX | E78: VAN004276 | F78: QL | H78: Quiberon | I78: 7 QU OCEAN | L78: lié a la VAN00477 et VAN004278
A79: QPR501960 | B79: 46076 | C79: =VLOOKUP(E79, $A$3:$E$704, 2, FALSE) -> #N/A | D79: 14 POI EN TRAVAUX | E79: QPR501010 | F79: WY | H79: Plozévet | I79: 2 LD MENGLEUX | J79: 45874
A80: QPR501966 | B80: 46048 | C80: =VLOOKUP(E80, $A$3:$E$704, 2, FALSE) -> #N/A | D80: 14 POI EN TRAVAUX | E80: LOR500133 | F80: KA | G80: Manque cloture ACF010 + manque transfert de cable + proposition attachement | H80: Gourin | I80: CRANN PIPIDIC | J80: 45853
A81: QPR501981 | B81: 46008 | C81: =VLOOKUP(E81, $A$3:$E$704, 2, FALSE) -> #N/A | D81: 14 POI EN TRAVAUX | E81: QPR500887 | F81: F6 | H81: Briec | I81: PL DE RUTHIN | L81: mairie à contacter pour le clé
A82: LOR501477 | B82: 46076 | C82: =VLOOKUP(E82, $A$3:$E$704, 2, FALSE) -> #N/A | D82: 14 POI EN TRAVAUX | E82: QPR500994 | F82: F9 | H82: Névez | I82: 11 T LD KERSTANG | J82: 07/08/2025 l'apres-midi
A83: LOR501478 | B83: 46080 | C83: =VLOOKUP(E83, $A$3:$E$704, 2, FALSE) -> #N/A | D83: 14 POI EN TRAVAUX | E83: QPR500752 | F83: 5Y | H83: Treffiagat | I83: 16 AV DU 8 MAI 1945 | J83: 45826
A84: LOR501482 | B84: 46069 | C84: =VLOOKUP(E84, $A$3:$E$704, 2, FALSE) -> 45953 | D84: 14 POI EN TRAVAUX | E84: LOR501031 | F84: KA | H84: Malguénac | I84: LE SENCE | J84: 45917 | L84: à remonter par chaima
A85: QPR502001 | B85: 46114 | C85: =VLOOKUP(E85, $A$3:$E$704, 2, FALSE) -> #N/A | D85: 14 POI EN TRAVAUX | E85: LOR500508 | F85: KA | G85: Manque travaux cuivre + explication percution + proposition attachement | H85: Inguiniel | I85: BOTSCAVE | J85: Retour le 17/09 | L85: à remonter par Afek en cours
A86: QPR502010 | B86: 46084 | C86: =VLOOKUP(E86, $A$3:$E$704, 2, FALSE) -> #N/A | D86: 14 POI EN TRAVAUX | E86: RRE501420 | F86: KA | G86: Manquie cloture ACF + manque transfert de cables | H86: Avessac | I86: A CROIX DU BILAIS | J86: à refaire
A87: QPR502014 | B87: 46080 | C87: =VLOOKUP(E87, $A$3:$E$704, 2, FALSE) -> #N/A | D87: 14 POI EN TRAVAUX | E87: QPR501171 | F87: JG | H87: Pont-l'Abbé | I87: RUE JEANNE D ARC | J87: 45924 | L87: Travaux En cours | Plusieurs Chambres, regards enterrés | pas de contact pour savoir la date de fin des travaux
A88: CRO500279 | B88: 46059 | C88: =VLOOKUP(E88, $A$3:$E$704, 2, FALSE) -> #N/A | D88: 14 POI EN TRAVAUX | E88: LOR500509 | F88: KA | H88: Meslan | I88: KERVRECH NEVE | L88: à remonter par khadher
A89: LOR501512 | B89: 46086 | C89: =VLOOKUP(E89, $A$3:$E$704, 2, FALSE) -> #N/A | D89: 14 POI EN TRAVAUX | E89: LOR400923
A90: QPR502055 | B90: 46079 | C90: =VLOOKUP(E90, $A$3:$E$704, 2, FALSE) -> #N/A | D90: 14 POI EN TRAVAUX | E90: QPR402118 | F90: 5Y | H90: Plomeur | I90: 12 RUE DES JONQUILLES | J90: 45854 | L90: client injoignable
A91: LOR501534 | B91: 46077 | C91: =VLOOKUP(E91, $A$3:$E$704, 2, FALSE) -> #N/A | D91: 14 POI EN TRAVAUX | E91: LOR500820 | F91: B6 | H91: Caudan | I91: 1 RUE MARECHAL LECLERC | L91: à assurer par stephane
A92: CRO500293 | B92: 46079 | C92: =VLOOKUP(E92, $A$3:$E$704, 2, FALSE) -> #N/A | D92: 14 POI EN TRAVAUX | E92: BRS402663 | F92: B3 | H92: Saint-Nic | I92: 1 R PLAGE | J92: 45895 | L92: Tigre ok à modif
A93: LOR501552 | B93: 46042 | C93: =VLOOKUP(E93, $A$3:$E$704, 2, FALSE) -> #N/A | D93: 14 POI EN TRAVAUX | E93: QPR500963 | F93: 5Y | H93: Guilvinec | I93: 5B R DE MEJOU VEIL | L93: VT a refaire suite refus plantation
A94: QPR502092 | B94: 46080 | C94: =VLOOKUP(E94, $A$3:$E$704, 2, FALSE) -> #N/A | D94: 14 POI EN TRAVAUX | E94: RRE501894 | F94: KA | H94: Le Crouais | I94: BEL AIR | J94: 45946
A95: QPR502100 | B95: 46090 | C95: =VLOOKUP(E95, $A$3:$E$704, 2, FALSE) -> #N/A | D95: 14 POI EN TRAVAUX | E95: LOR501156 | F95: KA | H95: Saint-Caradec-Trégomel | I95: R DES ANEMONES | J95: 23/092025 | L95: à remonter par chaima
A96: QPR502114 | B96: 46076 | C96: =VLOOKUP(E96, $A$3:$E$704, 2, FALSE) -> #N/A | D96: 14 POI EN TRAVAUX | E96: LOR500350 | F96: B3 | H96: Caudan | I96: 1 RUE MARECHAL LECLERC | L96: à assurer par stephane
A97: QPR502116 | B97: 46080 | C97: =VLOOKUP(E97, $A$3:$E$704, 2, FALSE) -> #N/A | D97: 14 POI EN TRAVAUX | E97: QPR400016
A98: RRE502654 | B98: 46083 | C98: =VLOOKUP(E98, $A$3:$E$704, 2, FALSE) -> #N/A | D98: 14 POI EN TRAVAUX | E98: QPR501403 | F98: 5Y | H98: Trégunc | I98: 37B RTE MELGVEN | J98: 45924 | L98: liée a la QPR501676
A99: CRO500295 | B99: 46084 | C99: =VLOOKUP(E99, $A$3:$E$704, 2, FALSE) -> #N/A | D99: 14 POI EN TRAVAUX | E99: RRE501466 | F99: 5Y | H99: Rennes | I99: 95 BD VOLTAIRE | J99: 45911
A100: QPR502125 | B100: 46076 | C100: =VLOOKUP(E100, $A$3:$E$704, 2, FALSE) -> #N/A | D100: 14 POI EN TRAVAUX | E100: RRE501198 | F100: 5Y | H100: PIRE CHANCE | I100: 18 RUE DE CHATEAUGIRON | J100: x
A101: LOR501566 | B101: 46090 | C101: =VLOOKUP(E101, $A$3:$E$704, 2, FALSE) -> #N/A | D101: 14 POI EN TRAVAUX | E101: LOR501153 | F101: KA | H101: Locmalo | I101: PONT MEEN | J101: Sondos | L101: liée a la LOR501260
A102: LOR501571 | B102: 46080 | C102: =VLOOKUP(E102, $A$3:$E$704, 2, FALSE) -> #N/A | D102: 14 POI EN TRAVAUX | E102: LOR501260 | F102: KD | H102: Locmalo | I102: PONT MEEN | L102: liée a la LOR501153
A103: LOR501580 | B103: 46090 | C103: =VLOOKUP(E103, $A$3:$E$704, 2, FALSE) -> #N/A | D103: 14 POI EN TRAVAUX | E103: CRO500116 | F103: 5Y | H103: Cast, Finistère | I103: 7D RUE DE PEN AR PRAT | L103: à remonter par chaima
A104: QPR600020 | B104: 46087 | C104: =VLOOKUP(E104, $A$3:$E$704, 2, FALSE) -> #N/A | D104: 14 POI EN TRAVAUX | E104: QPR500928 | F104: JG | H104: Pleuven | I104: CHE KILOURIN | J104: 45950 | L104: à voir avec khadher
A105: QPR600035 | B105: 46079 | C105: =VLOOKUP(E105, $A$3:$E$704, 2, FALSE) -> #N/A | D105: 14 POI EN TRAVAUX | E105: QPR501406 | F105: 5Y | H105: Plouhinec, Finistère | I105: 7B CH DES TOURTERELLES | J105: 45939 | L105: mail envoyé pour cause retour
A106: QPR600046 | B106: 46076 | C106: =VLOOKUP(E106, $A$3:$E$704, 2, FALSE) -> #N/A | D106: 14 POI EN TRAVAUX | E106: QPR501989 | F106: ET | H106: Douarnenez | I106: RTE DE BREHUEL
A107: QPR600047 | B107: 46069 | C107: =VLOOKUP(E107, $A$3:$E$704, 2, FALSE) -> #N/A | D107: 14 POI EN TRAVAUX | E107: QPR501381 | F107: 93 | H107: Tréméoc | I107: ROSCELOU COZ | J107: 45950 | L107: Amrou
A108: VAN600068 | B108: 46069 | C108: =VLOOKUP(E108, $A$3:$E$704, 2, FALSE) -> #N/A | D108: 14 POI EN TRAVAUX | E108: QPR501918 | F108: KA | H108: Pont-Aven | I108: 1 KERNONEN | J108: 45986 | L108: AFEK
A109: LOR600042 | B109: 46069 | C109: =VLOOKUP(E109, $A$3:$E$704, 2, FALSE) -> #N/A | D109: 14 POI EN TRAVAUX | E109: LOR501425 | F109: ZJ | H109: Plouay | I109: 28 RUE DE KERNIVINEN | J109: 45989 | L109: Afek
A110: QPR600054 | B110: 46086 | C110: =VLOOKUP(E110, $A$3:$E$704, 2, FALSE) -> #N/A | D110: 14 POI EN TRAVAUX | E110: QPR502002 | F110: KA | H110: Plomeur | I110: KERIWA | J110: 45999 | L110: Attente retour ENEDIS
A111: VAN600074 | B111: 46092 | C111: =VLOOKUP(E111, $A$3:$E$704, 2, FALSE) -> #N/A | D111: 14 POI EN TRAVAUX | E111: CRO500153 | F111: KD | H111: Crozon | I111: LIEU DIT PERSUEL | L111: à remonter par khadher
A112: VAN600095 | B112: 46142 | C112: =VLOOKUP(E112, $A$3:$E$704, 2, FALSE) -> #N/A | D112: 14 POI EN TRAVAUX | E112: QPR501931 | F112: F6 | H112: Bannalec | I112: 10 BI ALL DU QUINQUIS | J112: 45994 | L112: khadher
A113: QPR600066 | B113: 46140 | C113: =VLOOKUP(E113, $A$3:$E$704, 2, FALSE) -> #N/A | D113: 14 POI EN TRAVAUX | E113: QPR501927 | F113: F6 | H113: Plouhinec, Finistère | I113: 32 R DE L OCEAN | J113: 45992 | L113: CRVT envoyé !!
A114: QPR600078 | B114: 46069 | C114: =VLOOKUP(E114, $A$3:$E$704, 2, FALSE) -> #N/A | D114: 14 POI EN TRAVAUX | E114: QPR501501 | F114: KA | H114: Poullan-sur-Mer | I114: KERANDRAON | J114: 45936
A115: QPR600079 | B115: 46087 | C115: =VLOOKUP(E115, $A$3:$E$704, 2, FALSE) -> #N/A | D115: 14 POI EN TRAVAUX | E115: QPR501939 | F115: 5Y | H115: Pluguffan | I115: 41 R DES KORRIGANS | J115: 45995 | L115: Amrou
A116: QPR600080 | B116: 46090 | C116: =VLOOKUP(E116, $A$3:$E$704, 2, FALSE) -> #N/A | D116: 14 POI EN TRAVAUX | E116: QPR500992 | F116: 5Q | H116: Plozévet | I116: RUE DES MESANGES | J116: 46049 | L116: GC en question verfié
A117: QPR600084 | B117: 46079 | C117: =VLOOKUP(E117, $A$3:$E$704, 2, FALSE) -> #N/A | D117: 14 POI EN TRAVAUX | E117: QPR501572 | F117: 5Y | H117: Moëlan-sur-Mer | I117: KERCARN | J117: 45939 | L117: rdv confirmé avec le client
A118: QPR600095 | B118: 46119 | C118: =VLOOKUP(E118, $A$3:$E$704, 2, FALSE) -> #N/A | D118: 14 POI EN TRAVAUX | E118: LOR500385 | F118: B3 | H118: Inzinzac-Lochrist | I118: MAIL FRANCOIS GIOVANELLI | J118: 46041
A119: VAN600141 | B119: 46237 | C119: =VLOOKUP(E119, $A$3:$E$704, 2, FALSE) -> #N/A | D119: 14 POI EN TRAVAUX | E119: LOR500511 | F119: B3 | H119: Inzinzac-Lochrist | I119: MAIL FRANCOIS GIOVANELLI
A120: QPR600101 | B120: 46062 | C120: =VLOOKUP(E120, $A$3:$E$704, 2, FALSE) -> #N/A | D120: 14 POI EN TRAVAUX | E120: CRO500261 | F120: 59 | H120: Crozon | I120: 3 IMP COZ DOUAR | J120: 45993 | L120: Amrou
A121: LOR600065 | B121: 46086 | C121: =VLOOKUP(E121, $A$3:$E$704, 2, FALSE) -> #N/A | D121: 14 POI EN TRAVAUX | E121: QPR402367 | F121: 5Y | H121: Plomeur | I121: 30A RUE SANT TREVEL | J121: 45956
A122: VAN600158 | B122: 46083 | C122: =VLOOKUP(E122, $A$3:$E$704, 2, FALSE) -> #N/A | D122: 14 POI EN TRAVAUX | E122: RRE501899 | F122: KA | H122: Bourg-des-Comptes | I122: LA GREE GUISSONNIERE | J122: 45946 | K122: KHADHER
A123: QPR600129 | B123: 46086 | C123: =VLOOKUP(E123, $A$3:$E$704, 2, FALSE) -> #N/A | D123: 14 POI EN TRAVAUX | E123: RRE502542 | F123: KD | H123: Bourg-des-Comptes | I123: LA GREE GUISSONNIERE
A124: VAN600303 | B124: 46087 | C124: =VLOOKUP(E124, $A$3:$E$704, 2, FALSE) -> 46080 | D124: 14 POI EN TRAVAUX | E124: QPR502092 | F124: 2P | H124: Plozévet | I124: RUE D AUDIERNE | J124: 46015 | L124: AMROU
C125: =VLOOKUP(E125, $A$3:$E$704, 2, FALSE) -> 46072 | D125: 14 POI EN TRAVAUX | E125: CRO500268 | F125: F6 | H125: Roscanvel | I125: 38 RTE DE KERINCUFF | J125: 45993 | K125: amrou
A126: VAN600185 | B126: 46064 | C126: =VLOOKUP(E126, $A$3:$E$704, 2, FALSE) -> #N/A | D126: 13 ETAT 5 | E126: QPR501995 | F126: KD | G126: ATT UPR | H126: Pont-Aven | I126: 1 KERNONEN
A127: VAN600198 | B127: 46064 | C127: =VLOOKUP(E127, $A$3:$E$704, 2, FALSE) -> #N/A | D127: 12 AT MAJ SI | E127: CRO500068 | F127: HP | G127: MAJ ok a monter | H127: Crozon | I127: LD PERSUEL | J127: 45863 | L127: 2
A128: LOR600119 | B128: 46076 | C128: =VLOOKUP(E128, $A$3:$E$704, 2, FALSE) -> #N/A | D128: 12 AT MAJ SI | E128: VAN500330 | F128: JG | G128: MAJ ok a monter | H128: Saint-Guyomard | I128: LAUN BIJUS | L128: à remonter par khadher
A129: QPR600138 | B129: 46087 | C129: =VLOOKUP(E129, $A$3:$E$704, 2, FALSE) -> 46063 | D129: 12 AT MAJ SI | E129: LOR500901 | F129: UG | G129: Att retour Alexis | H129: Ploemeur | I129: RUE MARIE HOUDE | J129: 45952 | L129: att CAPFT A monter ensemble Cynthia et Stephane
...

Sheet GDP AQ
A1: =TODAY() -> 46076 | E1: =COUNTA(E3:E745) -> 106 | J1: A REMPLIR PAR LE BE OBLIGATOIRE
A2: Code OEIE | B2: DRE | C2: DRE | D2: ETAT | E2: POI | F2: SJ | G2: Mémo Chaf | H2: VILLE | I2: ADRESSE | J2: DATE VT | K2: COMMENTAIRES
A3: MDM102429 | B3: 46111 | C3: =VLOOKUP(E3, $A$2:$E$822, 2, FALSE) -> #N/A | D3: 14.1 AT RETOUR DOE | E3: PAU400540 | F3: XR | G3: Manque classe A pour recol | H3: BUROS | I3: 2265 CHE ROUMIEU
A4: MDM103892 | B4: 46085 | C4: =VLOOKUP(E4, $A$2:$E$822, 2, FALSE) -> #N/A | D4: 14.1 AT RETOUR DOE | E4: PAU101592 | F4: CC | H4: HAGETAUBIN | I4: 1350 RTE ST MEDARD | K4: TVX FINIS
A5: MDM200033 | B5: 46084 | C5: =VLOOKUP(E5, $A$2:$E$822, 2, FALSE) -> #N/A | D5: 14.1 AT RETOUR DOE | E5: MDM300296 | F5: CC | H5: MONT DE MARSAN | I5: R PIERRE RISPAL
A6: MDM201114 | B6: 46083 | C6: =VLOOKUP(E6, $A$2:$E$822, 2, FALSE) -> #N/A | D6: 14.1 AT RETOUR DOE | E6: BAY400463 | F6: CC | H6: SAINT MARTIN DE HINX | I6: RTE VIGNERONS
A7: MDM300394 | B7: 46104 | C7: =VLOOKUP(E7, $A$2:$E$822, 2, FALSE) -> #N/A | D7: 14.1 AT RETOUR DOE | E7: MDM500515 | F7: CP | H7: GAMARDE LES BAINS | I7: ROUTE DE TENDURE | K7: a reprendre? pourquoi ????
A8: BAY300372 | B8: 46090 | C8: =VLOOKUP(E8, $A$2:$E$822, 2, FALSE) -> #N/A | D8: 14 POI EN TRAVAUX | E8: PAU400255 | F8: CC | H8: SAINT CASTIN | I8: RTE BUROS | J8: 45729
A9: BAY300536 | B9: 46084 | C9: =VLOOKUP(E9, $A$2:$E$822, 2, FALSE) -> #N/A | D9: 14 POI EN TRAVAUX | E9: PAU400058 | F9: RV | H9: GERDEREST | I9: CH DE MONASSUT | J9: ? | K9: pas de travaux client fibré déja
A10: MDM300689 | B10: 46119 | C10: =VLOOKUP(E10, $A$2:$E$822, 2, FALSE) -> #N/A | D10: 14 POI EN TRAVAUX | E10: PAU301083 | F10: DI | G10: DOSSIER A VALIDER | H10: JURANCON | I10: 1 RUE DE LA SCIERIE | J10: 45931 | K10: Pris en charge par stéphane
A11: MDM301155 | B11: 46090 | C11: =VLOOKUP(E11, $A$2:$E$822, 2, FALSE) -> #N/A | D11: 14 POI EN TRAVAUX | E11: PAU103623 | F11: CC | H11: MORLANNE | I11: ROUTE PERE
A12: PAU301084 | B12: 46162 | C12: =VLOOKUP(E12, $A$2:$E$822, 2, FALSE) -> #N/A | D12: 14 POI EN TRAVAUX | E12: MDM500332 | F12: CC | H12: BAHUS SOUBIRAN | I12: RTE DE DAMOULENS | J12: 45835 | K12: TRVX ENEDIS FAITES
A13: MDM301222 | B13: 46078 | C13: =VLOOKUP(E13, $A$2:$E$822, 2, FALSE) -> #N/A | D13: 14 POI EN TRAVAUX | E13: MDM500161 | F13: CC | H13: PONTENX LES FORGES | I13: 607 RTE MOUGNAN | K13: TVX OK
A14: PAU301245 | B14: 46080 | C14: =VLOOKUP(E14, $A$2:$E$822, 2, FALSE) -> #N/A | D14: 14 POI EN TRAVAUX | E14: MDM400853 | F14: XR | H14: BEGAAR | I14: 218 CHEMIN POUCHIOU
A15: MDM301401 | B15: 46188 | C15: =VLOOKUP(E15, $A$2:$E$822, 2, FALSE) -> #N/A | D15: 14 POI EN TRAVAUX | E15: MDM200689 | F15: DO | H15: AUREILHAN | I15: 21 RTE LACS
A16: MDM400167 | B16: 46079 | C16: =VLOOKUP(E16, $A$2:$E$822, 2, FALSE) -> #N/A | D16: 14 POI EN TRAVAUX | E16: MDM003509 | F16: DG | H16: GEAUNE | I16: R NAZ DE GUIT | J16: 45723
A17: PAU400195 | B17: 46090 | C17: =VLOOKUP(E17, $A$2:$E$822, 2, FALSE) -> #N/A | D17: 14 POI EN TRAVAUX | E17: DAX400043 | F17: DO | H17: PONTONX SUR L'ADOUR | I17: 81 CHE CASTERA
A18: MDM400322 | B18: 46097 | C18: =VLOOKUP(E18, $A$2:$E$822, 2, FALSE) -> #N/A | D18: 14 POI EN TRAVAUX | E18: DAX400041 | F18: DO | H18: PONTONX SUR L'ADOUR | I18: CH NOEL | J18: 45724
A19: PAU400369 | B19: 46083 | C19: =VLOOKUP(E19, $A$2:$E$822, 2, FALSE) -> #N/A | D19: 14 POI EN TRAVAUX | E19: BAY400353 | F19: CC | H19: TARNOS | I19: 781 CHE ANNELONGUE | J19: 45932
A20: MDM400398 | B20: 46086 | C20: =VLOOKUP(E20, $A$2:$E$822, 2, FALSE) -> #N/A | D20: 14 POI EN TRAVAUX | E20: BAY200287 | F20: DO | H20: LABENNE | I20: 1 ALL CHAMPAGNE
A21: MDM400427 | B21: 46128 | C21: =VLOOKUP(E21, $A$2:$E$822, 2, FALSE) -> #N/A | D21: 14 POI EN TRAVAUX | E21: ARC500883 | F21: CG | H21: GUJAN MESTRAS | I21: 8 ALL DU BOSQUET DES CIGALES | K21: amenagement
A22: BAY400496 | B22: 46084 | C22: =VLOOKUP(E22, $A$2:$E$822, 2, FALSE) -> #N/A | D22: 14 POI EN TRAVAUX | E22: MDM300753 | F22: BX | H22: SARBAZAN | I22: 683 POUY | K22: TVX OK (photos travaux sur share point)
A23: BAY400497 | B23: 46084 | C23: =VLOOKUP(E23, $A$2:$E$822, 2, FALSE) -> #N/A | D23: 14 POI EN TRAVAUX | E23: PAU300808 | F23: OI | H23: GELOS | I23: AVE HENRI FANFELLE | J23: 45950 | K23: j'ai vous transferé le mail du client ou il nous a confirmé que les travaux ont été terminés
A24: BAY400498 | B24: 46084 | C24: =VLOOKUP(E24, $A$2:$E$822, 2, FALSE) -> #N/A | D24: 14 POI EN TRAVAUX | E24: MDM500507 | F24: BW | H24: MUGRON | I24: 248 RTE DE POMAREZ | J24: 45937
A25: MDM400530 | B25: 46148 | C25: =VLOOKUP(E25, $A$2:$E$822, 2, FALSE) -> #N/A | D25: 14 POI EN TRAVAUX | E25: ARC500798 | F25: OG | H25: ARCACHON | I25: 38 AV DES GOELANDS
A26: MDM400881 | B26: 46090 | C26: =VLOOKUP(E26, $A$2:$E$822, 2, FALSE) -> #N/A | D26: 14 POI EN TRAVAUX | E26: MDM300446 | F26: CC | H26: CASTELNER | I26: LASSERRE | J26: 45950 | K26: Pas de dépose d'appui de notre part. | Appui ENEDIS déjà déposés
A27: MDM400978 | B27: 46099 | C27: =VLOOKUP(E27, $A$2:$E$822, 2, FALSE) -> #N/A | D27: 14 POI EN TRAVAUX | E27: PAU301246 | F27: DI | H27: MIREPEIX | I27: RUE BAREILLE | J27: 45937 | K27: lié a PAU301245
A28: MDM500002 | B28: 46078 | C28: =VLOOKUP(E28, $A$2:$E$822, 2, FALSE) -> 46076 | D28: 12 AT MAJ SI | E28: ARC600065 | F28: IN | H28: LE TEICH | I28: 48 RUE DES POISSONNIERS | J28: 46050
A29: MDM500310 | B29: 46083 | C29: =VLOOKUP(E29, $A$2:$E$822, 2, FALSE) -> 46077 | D29: 11 AT DTA | E29: ARC500878 | F29: IK | G29: Rapport d'ammiante existant ou non | H29: LE TEICH | I29: 1 ALL DE CANTELAUDE | K29: Besoin retour terrain
A30: MDM500366 | B30: 46146 | C30: =VLOOKUP(E30, $A$2:$E$822, 2, FALSE) -> 46077 | D30: 11 AT DTA | E30: ARC500965 | F30: IK | G30: Rapport d'ammiante existant ou non | H30: LE TEICH | I30: 1 ALL DE CANTELAUDE | J30: 46037
A31: MDM500477 | B31: 46078 | C31: =VLOOKUP(E31, $A$2:$E$822, 2, FALSE) -> 46078 | D31: 10 AT PV | E31: ARC500827 | F31: OG | H31: LA TESTE DE BUCH | I31: 7 SQ LUDWIG VAN BEETHOVEN
A32: MDM500499 | B32: 46078 | C32: =VLOOKUP(E32, $A$2:$E$822, 2, FALSE) -> 46078 | D32: 10 AT PV | E32: MDM301222 | F32: CC | G32: Recus | H32: SAINT PERDON | I32: RTE CALOY | J32: 45726
A33: MDM500500 | B33: 46078 | C33: =VLOOKUP(E33, $A$2:$E$822, 2, FALSE) -> 46078 | D33: 10 AT PV | E33: ARC500960 | F33: IN | G33: Pres PV | H33: SALLES | I33: CHEMIN DE GUERIN | J33: 46022
A34: MDM500532 | B34: 46078 | C34: =VLOOKUP(E34, $A$2:$E$822, 2, FALSE) -> 46080 | D34: 10 AT PV | E34: ARC500930 | F34: IN | H34: LA TESTE DE BUCH | I34: CHE DE PECHIC | J34: 46022
A35: MDM500538 | B35: 46086 | C35: =VLOOKUP(E35, $A$2:$E$822, 2, FALSE) -> 46078 | D35: 10 AT PV | E35: ARC600021 | F35: 59 | H35: GUJAN MESTRAS | I35: 12 B AV DE CESAREE | J35: On a passé déja ?
A36: ARC500708 | B36: 46127 | C36: =VLOOKUP(E36, $A$2:$E$822, 2, FALSE) -> 46083 | D36: 10 AT PV | E36: ARC600070 | F36: OG | G36: ETUDE FAISABILITE OK demande PV sur la ARC500902 | H36: LUGOS | I36: RUE DE L EGLISE
A37: ARC500728 | B37: 46072 | C37: =VLOOKUP(E37, $A$2:$E$822, 2, FALSE) -> 46076 | D37: 10 AT PV | E37: ARC600069 | F37: OG | G37: dossier liée a la ARC500728PV lancer | H37: SALLES | I37: ROUTE DE LA GARENNE
A38: ARC500733 | B38: 46083 | C38: =VLOOKUP(E38, $A$2:$E$822, 2, FALSE) -> 46078 | D38: 10 AT PV | E38: ARC600039 | F38: 9I | G38: tvx debut avril | H38: LE TEICH | I38: 1 E ALL DE CANTELAUDE | J38: 20/01 à 14h
A39: ARC500784 | B39: 46087 | C39: =VLOOKUP(E39, $A$2:$E$822, 2, FALSE) -> 46083 | D39: 10 AT PV | E39: ARC600003 | F39: 9I | H39: GUJAN MESTRAS | I39: 5 R DU CHATEAU | J39: 22/01 à 9h30
A40: ARC500802 | B40: 46084 | C40: =VLOOKUP(E40, $A$2:$E$822, 2, FALSE) -> 46073 | D40: 09 AT DEVIS ORANGE/RIP | E40: ARC500847 | F40: IN | G40: Etude de faisabilité | H40: LUGOS | I40: RUE DE L EGLISE
A41: ARC500812 | B41: 46041 | C41: =VLOOKUP(E41, $A$2:$E$822, 2, FALSE) -> 46072 | D41: 09 AT DEVIS ORANGE/RIP | E41: ARC500728 | F41: 72 | G41: Etude de faisabilité liée a la ARC600069 | H41: SALLES | I41: ROUTE DE LA GARENNE | J41: 45946
A42: ARC500827 | B42: 46078 | C42: =VLOOKUP(E42, $A$2:$E$822, 2, FALSE) -> 46083 | D42: 07 AT TRVX CLIENT | E42: ARC500931 | F42: 9I | G42: Att photo regard 30x30 | H42: LA TESTE DE BUCH | I42: 2 CHE DE PECHIC | J42: 26/12/2025 9h30 | K42: besoin rdv
A43: ARC500831 | B43: 46078 | C43: =VLOOKUP(E43, $A$2:$E$822, 2, FALSE) -> 46092 | D43: 07 AT TRVX CLIENT | E43: ARC500966 | F43: 9I | G43: 46063 | H43: LE TEICH | I43: 1 ALL DE CANTELAUDE | J43: 46387.604 | K43: besoin rdv
A44: ARC500836 | B44: 46083 | C44: =VLOOKUP(E44, $A$2:$E$822, 2, FALSE) -> 46083 | D44: 07 AT TRVX CLIENT | E44: PAU400369 | F44: BX | H44: MEILLON | I44: 7 COTE DE MAUHOURAT | J44: VENDREDI
A45: ARC500840 | B45: 46076 | C45: =VLOOKUP(E45, $A$2:$E$822, 2, FALSE) -> 46090 | D45: 07 AT TRVX CLIENT | E45: PAU400195 | F45: BX | G45: pas de tvx à lancer pour l'instant | H45: LESCAR | I45: RTE DE L AVIATION | J45: mardi
A46: ARC500843 | B46: 46160 | C46: =VLOOKUP(E46, $A$2:$E$822, 2, FALSE) -> 46162 | D46: 07 AT TRVX CLIENT | E46: PAU301084 | F46: DI | H46: JURANCON | I46: 1 RUE DE LA SCIERIE | J46: 45931 | K46: Pris en charge par stéphane
A47: ARC500847 | B47: 46073 | C47: =VLOOKUP(E47, $A$2:$E$822, 2, FALSE) -> 46146 | D47: 07 AT TRVX CLIENT | E47: MDM500366 | F47: E8 | G47: fin d'avril | H47: AUDIGNON | I47: RTE DU CHATEAU D EAU | K47: NE PAS PRENDRE
A48: ARC500862 | B48: 46084 | C48: =VLOOKUP(E48, $A$2:$E$822, 2, FALSE) -> 46083 | D48: 07 AT TRVX CLIENT | E48: MDM500310 | F48: CG | H48: ROQUEFORT | I48: 214 AV D'ALBRET
A49: ARC500872 | B49: 46083 | C49: =VLOOKUP(E49, $A$2:$E$822, 2, FALSE) -> 46099 | D49: 07 AT TRVX CLIENT | E49: MDM400978 | F49: XR | G49: manque contact | H49: MEZOS | I49: 94 CH DE DUGRAND | J49: 45937
A50: ARC500874 | B50: 46119 | C50: =VLOOKUP(E50, $A$2:$E$822, 2, FALSE) -> 46090 | D50: 07 AT TRVX CLIENT | E50: MDM400881 | F50: BX | G50: Att travaux NATHD | H50: ROQUEFORT | I50: 2290 CHE BAS DE HAUT | J50: 45722
A51: ARC500878 | B51: 46077 | C51: =VLOOKUP(E51, $A$2:$E$822, 2, FALSE) -> 46148 | D51: 07 AT TRVX CLIENT | E51: MDM400530 | F51: E8 | H51: MEZOS | I51: LA GARE
A52: ARC500911 | B52: 46125 | C52: =VLOOKUP(E52, $A$2:$E$822, 2, FALSE) -> 46128 | D52: 07 AT TRVX CLIENT | E52: MDM400427 | F52: BX | G52: TVX à 2026 pas de date précise | H52: LESGOR | I52: 1060 CH DU REY | J52: 45936 | K52: ATT RETOUR CLIENT
A53: LAN500514 | B53: 46083 | C53: =VLOOKUP(E53, $A$2:$E$822, 2, FALSE) -> 46086 | D53: 07 AT TRVX CLIENT | E53: MDM400398 | F53: CG | H53: SOUPROSSE | I53: RTE GUIRETTE
A54: ARC500930 | B54: 46080 | C54: =VLOOKUP(E54, $A$2:$E$822, 2, FALSE) -> 46188 | D54: 07 AT TRVX CLIENT | E54: MDM301401 | F54: CG | H54: VILLENEUVE DE MARSAN | I54: ALLS D HAUSSEZ
A55: ARC500931 | B55: 46083 | C55: =VLOOKUP(E55, $A$2:$E$822, 2, FALSE) -> 46119 | D55: 07 AT TRVX CLIENT | E55: MDM300689 | F55: DO | H55: CAMPAGNE | I55: 157 AV ECOLES
A56: ARC500947 | B56: 46128 | C56: =VLOOKUP(E56, $A$2:$E$822, 2, FALSE) -> 46111 | D56: 07 AT TRVX CLIENT | E56: MDM102429 | F56: DG | H56: LESPERON | I56: 277 R JULES FERRY
A57: ARC500948 | B57: 46083 | C57: =VLOOKUP(E57, $A$2:$E$822, 2, FALSE) -> 46084 | D57: 07 AT TRVX CLIENT | E57: BAY400498 | F57: E8 | H57: SAINT LAURENT DE GOSSE | I57: 419 RTE BELLEVUE
A58: ARC500952 | B58: 46342 | C58: =VLOOKUP(E58, $A$2:$E$822, 2, FALSE) -> 46084 | D58: 07 AT TRVX CLIENT | E58: BAY400497 | F58: E8 | H58: SAINT LAURENT DE GOSSE | I58: 419 RTE BELLEVUE
A59: ARC500960 | B59: 46078 | C59: =VLOOKUP(E59, $A$2:$E$822, 2, FALSE) -> 46084 | D59: 07 AT TRVX CLIENT | E59: BAY400496 | F59: E8 | H59: SAINT LAURENT DE GOSSE | I59: 419 RTE BELLEVUE
A60: ARC500965 | B60: 46077 | C60: =VLOOKUP(E60, $A$2:$E$822, 2, FALSE) -> 46119 | D60: 07 AT TRVX CLIENT | E60: ARC500874 | F60: CC | G60: Mi Juillet | H60: SALLES | I60: 61 ROUTE DE PEYBIDEAU | K60: 49/50
A61: ARC500966 | B61: 46092 | C61: =VLOOKUP(E61, $A$2:$E$822, 2, FALSE) -> 46083 | D61: 07 AT TRVX CLIENT | E61: ARC500872 | F61: 9I | G61: fin de fevrier | H61: GUJAN MESTRAS | I61: 13 ALL DES PINS VERTS | J61: 46000.448 | K61: CRVT à refaire 19/12
A62: ARC500969 | B62: 46083 | C62: =VLOOKUP(E62, $A$2:$E$822, 2, FALSE) -> 46084 | D62: 07 AT TRVX CLIENT | E62: ARC500862 | F62: 9I | G62: tvx toujours en cours | H62: GUJAN MESTRAS | I62: 12 AV DE CESAREE | J62: 15/12/2025 09h
A63: ARC600003 | B63: 46083 | C63: =VLOOKUP(E63, $A$2:$E$822, 2, FALSE) -> 46127 | D63: 07 AT TRVX CLIENT | E63: ARC500708 | F63: BX | G63: TVX pas encore commencés | H63: GUJAN MESTRAS | I63: 4 TER IMP DES COQUELICOTS | J63: 45943 | K63: d'apres la cliente il faut contacter ses voisins puisque c pas à elle de faire les tvx
A64: ARC600021 | B64: 46078 | C64: =VLOOKUP(E64, $A$2:$E$822, 2, FALSE) -> 46084 | D64: 07 AT TRVX CLIENT | E64: ARC600025 | F64: 9I | G64: 46235 | H64: GUJAN MESTRAS | I64: 70 LOT SAINTE CLOTILDE | J64: 20/01 16H30 pas avant
A65: ARC600025 | B65: 46084 | C65: =VLOOKUP(E65, $A$2:$E$822, 2, FALSE) -> 46125 | D65: 07 AT TRVX CLIENT | E65: ARC500911 | F65: VV | G65: S | H65: LA TESTE DE BUCH | I65: RUE MICHEL LABARTHE | J65: 18/12/2025 10H | K65: j'attends le retour du client
A66: ARC600031 | B66: 46080 | C66: =VLOOKUP(E66, $A$2:$E$822, 2, FALSE) -> 46183 | D66: 07 AT TRVX CLIENT | E66: ARC600054 | F66: 9I | G66: fin du chantier mi-juin | H66: GUJAN MESTRAS | I66: 9 D ALL DES PINS VERTS | J66: 46050
A67: ARC600033 | B67: 46076 | C67: =VLOOKUP(E67, $A$2:$E$822, 2, FALSE) -> 46235 | D67: 07 AT TRVX CLIENT | E67: ARC600041 | F67: 9I | G67: tvx 01/08/2026 | H67: LA TESTE DE BUCH | I67: 51 RUE DU MARECHAL LECLERC CAZAUX | J67: 22/01 10H30
A68: ARC600039 | B68: 46078 | C68: =VLOOKUP(E68, $A$2:$E$822, 2, FALSE) -> 46078 | D68: 06 AT DEVIS CLIENT | E68: MDM500477 | F68: DR | G68: Jusqu'au 4/03 | H68: LAGLORIEUSE | I68: 1880 RTE MONT DE MARSAN | J68: 45929 | K68: mail envoyé à stephane concernant
A69: ARC600041 | B69: 46235 | C69: =VLOOKUP(E69, $A$2:$E$822, 2, FALSE) -> 46041 | D69: 05.1 ETU TRANSMISE | E69: ARC500812 | F69: IN | H69: SALLES | I69: ROUTE DE JEAN ROUX
A70: ARC600051 | B70: 46085 | C70: =VLOOKUP(E70, $A$2:$E$822, 2, FALSE) -> 46080 | D70: 05.1 ETU TRANSMISE | E70: PAU301245 | F70: DI | H70: MIREPEIX | I70: 1 RUE DE LA BAREILHE | J70: 45937 | K70: mail envoyé concernant
C71: =VLOOKUP(E71, $A$2:$E$822, 2, FALSE) -> 46086 | D71: 05 AT INFO CAF REF | E71: MDM500538 | F71: DR | H71: POUYDESSEAUX | I71: RTE CORBLEU | J71: 45930
C72: =VLOOKUP(E72, $A$2:$E$822, 2, FALSE) -> 46078 | D72: 05 AT INFO CAF REF | E72: MDM500532 | F72: DR | H72: MONT DE MARSAN | I72: 1435 AV HOUGA | J72: 45930 | K72: rdv apres-midi
A73: ARC600054 | B73: 46183 | C73: =VLOOKUP(E73, $A$2:$E$822, 2, FALSE) -> 46342 | D73: 05 AT INFO CAF REF | E73: ARC500952 | F73: 9I | H73: GUJAN MESTRAS | I73: 2 BIS ALL DES GENETS | J73: 26/12/2025 11h | K73: CRVT en cours
A74: ARC600060 | B74: 46076 | C74: =VLOOKUP(E74, $A$2:$E$822, 2, FALSE) -> 46078 | D74: 05 AT INFO CAF REF | E74: MDM500500 | F74: E8 | H74: LABASTIDE D ARMAGNAC | I74: RTE DE LE FRECHE | J74: 45930
A75: ARC600063 | B75: 46078 | C75: =VLOOKUP(E75, $A$2:$E$822, 2, FALSE) -> 46078 | D75: 05 AT INFO CAF REF | E75: MDM500499 | F75: E8 | H75: LABASTIDE D ARMAGNAC | I75: RTE DE CAZAUBON | J75: 45930
A76: ARC600065 | B76: 46076 | C76: =VLOOKUP(E76, $A$2:$E$822, 2, FALSE) -> #N/A | D76: 05 AT INFO CAF REF | E76: MDM400873 | F76: CC | H76: DOAZIT | I76: RTE MUS | J76: 45940 | K76: Je vois qu'il y a toujours le câble sur l'appui 4, Dossier a reprendre Je ne vois pas de proposition pour reprendre le câble. Pas de plan ITI concernant sur ces appuis.
A77: ARC600069 | B77: 46076 | C77: =VLOOKUP(E77, $A$2:$E$822, 2, FALSE) -> 46104 | D77: 05 AT INFO CAF REF | E77: MDM300394 | F77: DO | H77: GEAUNE | I77: 23 R MONTMARTRE
A78: ARC600070 | B78: 46083 | C78: =VLOOKUP(E78, $A$2:$E$822, 2, FALSE) -> 46083 | D78: 05 AT INFO CAF REF | E78: MDM201114 | F78: CC | H78: SAINT MARTIN D'ONEY | I78: CHEMIN DE LABARRERE | J78: 45722
A79: ARC600091 | B79: 46080 | C79: =VLOOKUP(E79, $A$2:$E$822, 2, FALSE) -> 46084 | D79: 05 AT INFO CAF REF | E79: MDM200033 | F79: CC | H79: SAINT JUSTIN | I79: ROUTE DE ROQUEFORT | J79: 45722
A80: BOR600066 | B80: 46064 | C80: =VLOOKUP(E80, $A$2:$E$822, 2, FALSE) -> 46083 | D80: 05 AT INFO CAF REF | E80: ARC500948 | F80: OG | H80: LA TESTE DE BUCH | I80: 19 BD DU PYLA
A81: ARC600108 | B81: 46083 | C81: =VLOOKUP(E81, $A$2:$E$822, 2, FALSE) -> 46076 | D81: 05 AT INFO CAF REF | E81: ARC600033 | F81: 9I | H81: LA TESTE DE BUCH | I81: 7 RUE LAGRUA | J81: 22/01 13H30
A82: ARC600117 | B82: 46092 | C82: =VLOOKUP(E82, $A$2:$E$822, 2, FALSE) -> 46076 | D82: 05 AT INFO CAF REF | E82: ARC600060 | F82: IN | G82: Att valid etude faisabilité | H82: LE TEICH | I82: 48 BIS RUE DES POISSONNIERS | J82: 46050
A83: ARC600133 | B83: 46094 | C83: =VLOOKUP(E83, $A$2:$E$822, 2, FALSE) -> 46078 | D83: 04 DOSSIER A MONTER | E83: ARC500831 | F83: 9I | G83: PV A FAIRE | H83: SALLES | I83: 28B RUE PIERRE DEYCARD | J83: 18/12/2025 9h | K83: client n'a pas honoré le rdv capture texto dans dossier
A84: ARC600141 | B84: 46083 | C84: =VLOOKUP(E84, $A$2:$E$822, 2, FALSE) -> 46078 | D84: 04 DOSSIER A MONTER | E84: MDM500002 | F84: CC | G84: PV SP | H84: SANGUINET | I84: 457 CHE CAM NEOU | K84: URGENT Contre visite travaux depuis 7/10 (photos de la visite d'octobre sur sharepoint)
C85: =VLOOKUP(E85, $A$2:$E$822, 2, FALSE) -> 46090 | D85: 04 DOSSIER A MONTER | E85: MDM301155 | F85: VV | H85: LAGLORIEUSE | I85: 105 CHEMIN DU BARRADE | J85: 45726
C86: =VLOOKUP(E86, $A$2:$E$822, 2, FALSE) -> 46085 | D86: 04 DOSSIER A MONTER | E86: MDM103892 | F86: DO | H86: GAMARDE LES BAINS | I86: ROUTE DE CHANTEGRIT | J86: VT 25/06
C87: =VLOOKUP(E87, $A$2:$E$822, 2, FALSE) -> 46083 | D87: 04 DOSSIER A MONTER | E87: ARC500836 | F87: BX | H87: GUJAN MESTRAS | I87: 31 RUE DU DOCTEUR DUFOURG | K87: 49/50 à voir avec hajjej
C88: =VLOOKUP(E88, $A$2:$E$822, 2, FALSE) -> 46087 | D88: 03 DOSSIER A REPRENDRE | E88: ARC500784 | F88: VV | H88: LA TESTE DE BUCH | I88: 10 R DES HIPPOCAMPES
C89: =VLOOKUP(E89, $A$2:$E$822, 2, FALSE) -> 46083 | D89: 03 DOSSIER A REPRENDRE | E89: ARC500733 | F89: BW | H89: SALLES | I89: ROUTE DE LA GARENNE | J89: 45946 | K89: VU avec stephane et louay
C90: =VLOOKUP(E90, $A$2:$E$822, 2, FALSE) -> 46083 | D90: 02 RETOUR VT | E90: LAN500514 | F90: JJ | G90: S | H90: BOMMES | I90: 1 HAUT BOMMES | K90: dessim à remonter par afek
C91: =VLOOKUP(E91, $A$2:$E$822, 2, FALSE) -> 46128 | D91: 02 RETOUR VT | E91: ARC500947 | F91: BW | H91: LA TESTE DE BUCH | I91: 680 AV GUSTAVE EIFFEL | J91: 26/01 à 14h sans faute | K91: besoin rdv deplacement reseau
C92: =VLOOKUP(E92, $A$2:$E$822, 2, FALSE) -> 46078 | D92: 02 RETOUR VT | E92: ARC600063 | F92: IN | H92: GUJAN MESTRAS | I92: ALL DE MALPONT | J92: 46050
C93: =VLOOKUP(E93, $A$2:$E$822, 2, FALSE) -> 46079 | D93: 02 RETOUR VT | E93: MDM400167 | F93: CG | G93: tvx ok | H93: CERE | I93: RTE BROCAS | J93: 46056 | K93: TVX pas encoré réalisésmail envoyé
C94: =VLOOKUP(E94, $A$2:$E$822, 2, FALSE) -> #N/A | D94: 02 RETOUR VT | E94: MDM203023 | F94: CC | G94: APPUI 11 OU 12 AVEC TELECOM | H94: GAILLERES | I94: MENGELY | J94: 46056
C95: =VLOOKUP(E95, $A$2:$E$822, 2, FALSE) -> 46160 | D95: 01.2 A REMONTER | E95: ARC500843 | F95: CC | G95: Travaux ENEDIS S24 | H95: GUJAN MESTRAS | I95: ALL DE LA FORET | J95: 46006 | K95: TVX enedis seront terminés au mois de mars , une visite à faire apres cette date pour traitement du dossier
C96: =VLOOKUP(E96, $A$2:$E$822, 2, FALSE) -> 46097 | D96: 01.2 A REMONTER | E96: MDM400322 | F96: CC | G96: on a eu les contacts de 3 clients , attends retour | H96: POMAREZ | I96: AV BEARN | J96: 46056 | K96: ATT retour mairie , mail envoyé 23-12-2025, relance mail 29/12
C97: =VLOOKUP(E97, $A$2:$E$822, 2, FALSE) -> 46076 | D97: 01.2 A REMONTER | E97: ARC500840 | F97: CC | G97: Travaux ENEDIS fin Mars | H97: LA TESTE DE BUCH | I97: R JULES FERRY | J97: 46000 | K97: TVX enedis seront terminés au mois de mars , une visite à faire apres cette date pour traitement du dossier
C98: =VLOOKUP(E98, $A$2:$E$822, 2, FALSE) -> 46083 | D98: 01 AT VT | E98: ARC600108 | F98: HT | H98: LE TEICH | I98: AV DE CAMPS
C99: =VLOOKUP(E99, $A$2:$E$822, 2, FALSE) -> 46084 | D99: 01 AT VT | E99: BAY300536 | F99: OI | G99: Vérification travaux a faire | H99: USTARITZ | I99: RUE HARDOIA | J99: 45954 | K99: relance ok , à prendre contacte avec le client apres 4 janvier
C100: =VLOOKUP(E100, $A$2:$E$822, 2, FALSE) -> 46080 | D100: 01 AT VT | E100: ARC600031 | F100: 9I | G100: Besoin VLOC | H100: LA TESTE DE BUCH | I100: 26 CHE DE LA PROCESSION | J100: 22/01 11H30
...

Sheet PRESENTATION 
B1: SUIVI DOSSIER ETUDE

Sheet SPI AQ
A1: =TODAY() -> 46076 | B1: =COUNTA(B3:B774) -> 73 | I1: PV | M1: DTA
A2: ETAT | B2: RechercheSPI | C2: VILLE | D2: Adresse | E2: Date création | F2: Date VT | G2: Date VT <14j | H2: N° SAVOIR | I2: Date émision PV | J2: Relance | L2: Dat PV recu | M2: N°BANBOU | N2: Date émission DTA | O2: DATE RELANCE | P2: INFO CAF
A3: 09.1 ATT DOE | B3: IMI-VA-64122/00RM-1 | C3: BIARRITZ | D3: 31 PASSAGE MAZAGRAN | E3: 45755 | G3: =E3+14 -> 45769
A4: 09.1 ATT DOE | B4: IMI-VA-64122/02WK-1 | C4: BIARRITZ | D4: 36 AVENUE DE L IMPERATRICE | E4: 45658 | G4: =E4+14 -> 45672 | P4: PB AVEC TRAVAUX
A5: 09.1 ATT DOE | B5: IMI-VA-40114/017S-1 | C5: GOURBERA | D5: 2450 RTE DE HERM | E5: 45661 | G5: =E5+14 -> 45675 | P5: PB AVEC TRAVAUX
A6: 09.1 ATT DOE | B6: IMI-VA-40279/169O-1 | C6: ST PAUL les DAX | D6: 332 CHEMIN DES ARTIFICIERS | E6: 45780 | G6: =E6+14 -> 45794 | H6: 1080316 | I6: 45832 | L6: 45910
A7: 09.1 ATT DOE | B7: IMI-VA-64024/02WH-1 | C7: ANGLET | D7: 14 avenue du vallon | E7: 45690 | G7: =E7+14 -> 45704 | I7: 45824 | L7: 45905 | P7: A faire
A8: 09.1 ATT DOE | B8: IMI-VA-40234/0083-1 | C8: POUYDESSSEAUX | D8: ROUTE DE CORBLEU | E8: 45887 | G8: =E8+14 -> 45901 | I8: 45912 | L8: 45926
A9: 09.1 ATT DOE | B9: IMI-VA-40234/009R-1 | C9: POUYDESSSEAUX | D9: 1549 route de bostens | E9: 45926 | F9: 45936 | G9: =E9+14 -> 45940 | H9: 1088187 | I9: 45915 | L9: 45944 | P9: Att fiche GESPOT
A10: 09.1 ATT DOE | B10: IMI-VA-40179/00LQ-3 | C10: MEES | D10: ROUTE D ARDY | E10: 45658 | G10: =E10+14 -> 45672
A11: 09 POI EN TRAVAUX | B11: IMI-VA-64024/04RO-2 | C11: ANGLET | D11: 3 RUE DE GRAVILLE | E11: 45658 | G11: =E11+14 -> 45672
A12: 09 POI EN TRAVAUX | B12: IMI-VA-64125/02AH-1 | C12: BIDART | D12: chemin cartacan | E12: 45658 | G12: =E12+14 -> 45672
A13: 09 POI EN TRAVAUX | B13: IMI-VA-40139/006Y-1 | C13: LAGLORIEUSE | D13: 2711 ROUTE DE PUJO | E13: 45866 | G13: =E13+14 -> 45880 | I13: 45910 | L13: 45926
A14: 09 POI EN TRAVAUX | B14: IMI-VA-64024/06OS-1 | C14: ANGLET | D14: 108 PROMENADE DE LA BARRE | E14: 45918 | F14: 45932 | G14: =E14+14 -> 45932 | H14: 1093487 | I14: 45911 | L14: 45943
A15: 09 POI EN TRAVAUX | B15: IMI-VA-64102/01VV-1 | C15: BAYONNE | D15: 4 AVENUE MARTHE JEAN | E15: 45943 | F15: 45947 | G15: =E15+14 -> 45957 | I15: 45952 | L15: 45967
A16: 09 POI EN TRAVAUX | B16: IMI-VA-64024/02Y4-1 | C16: ANGLET | D16: 96 BOULEVARD DES PLAGES | E16: 45981 | G16: =E16+14 -> 45995 | H16: 1096785 | I16: 45992 | L16: 45995
A17: 09 POI EN TRAVAUX | B17: IMI-VA-40202/01WO-1 | C17: NARROSSE | D17: 944 ROUTE DE SORT | E17: 45960 | G17: =E17+14 -> 45974 | H17: 1095230 | I17: 45978 | L17: 45994
A18: 09 POI EN TRAVAUX | B18: IMI-VA-40123/01L0-1 | C18: HERM | D18: 1110 ROUTE DE CLUQUELARDIT | E18: 45876 | G18: =E18+14 -> 45890 | I18: 45901 | L18: NA
A19: 09 POI EN TRAVAUX | B19: IMI-VA-40125/00GJ-1 | C19: HEUGAS | D19: 2211 ROUTE DU BRAOU | E19: 45936 | F19: 45937 | G19: =E19+14 -> 45950 | I19: 45950 | L19: 45979
A20: 09 POI EN TRAVAUX | B20: IMI-VA-40314/01QH-1 | C20: TERCIS LES BAINS | D20: 122 CHEMIN DU TASTET | E20: 45866 | G20: =E20+14 -> 45880 | I20: 45874 | L20: 45911
A21: 09 POI EN TRAVAUX | B21: IMI-VA-40003/013O-1 | C21: ANGOUME | D21: ROUTE DE MEES | E21: 45999 | F21: 46003 | G21: =E21+14 -> 46013
A22: 09 POI EN TRAVAUX | B22: IMI-VA-40279/15MF-1 | C22: ST PAUL les DAX | D22: 5396 AVENUE DES LACS | E22: 45742 | G22: =E22+14 -> 45756 | H22: 1072498 | I22: 45755 | L22: 46006 | P22: PB AVEC TRAVAUX
A23: 09 POI EN TRAVAUX | B23: IMI-VA-64102/044Q-1 | C23: BAYONNE | D23: 38 RUE MAUBEC | E23: 45988 | G23: =E23+14 -> 46002 | H23: 1097537 | I23: 45999 | L23: 46017
A24: 09 POI EN TRAVAUX | B24: IMI-VA-40280/00C8-2 | C24: ST PERDON | D24: 1700 ROUTE DE TOINE | F24: 46051 | G24: =E24+14 -> 14
A25: 09 POI EN TRAVAUX | B25: IMI-VA-40192/053X-2 | C25: MONT DE MARSAN | D25: 93 AVENUE DU MARECHAL FOCH | E25: 45905 | G25: =E25+14 -> 45919 | H25: 1088223 | I25: 45912 | L25: 46022 | M25: 3069233 | N25: 46028 | O25: OK
A26: 08 AT DEVIS ORANGE/RIP | B26: IMI-VA-40114/017V-1 | C26: GOURBERA | D26: 2330 route de Herm | E26: 45658 | G26: =E26+14 -> 45672
A27: 08 AT DEVIS ORANGE/RIP | B27: IMI-VA-40114/018I-2 | C27: GOURBERA | D27: 3370 ROUTE DE CASTETS | E27: 45938 | F27: 45950 | G27: =E27+14 -> 45952 | I27: 45952 | L27: 45975
A28: 08 AT DEVIS ORANGE/RIP | B28: IMI-VA-40280/00HH-1 | C28: ST PERDON | D28: 1630 ROUTE DE JARDINOT | E28: 45924 | F28: 45929 | G28: =E28+14 -> 45938 | H28: 1086953 | I28: 45959 | L28: 45975
A29: 08 AT DEVIS ORANGE/RIP | B29: IMI-VE-40123/01PN-1 | C29: HERM | D29: 1403 Route de tachette | E29: 45974 | G29: =E29+14 -> 45988 | H29: 1095250 | I29: 45978 | L29: 45989
A30: 08 AT DEVIS ORANGE/RIP | B30: IMI-VA-40125/01VF-1 | C30: HEUGAS | D30: 2000 ROUTE DES BARTHES | E30: 45825 | G30: =E30+14 -> 45839 | H30: 1098250 | I30: 46006 | L30: 46042
A31: 07 AT INFO CAF REF | B31: IMI-VA-40123/01PE-1 | C31: HERM | D31: 111 CHEMIN DE LAGRANGE | E31: 45966 | G31: =E31+14 -> 45980 | I31: 45978 | L31: NA
A32: 07 AT INFO CAF REF | B32: IMI-VA-40234/007H-1 | C32: POUYDESSEAUX | D32: 78 ROUTE DE CORBLUE | E32: 45866 | G32: =E32+14 -> 45880 | P32: PB factu travaux réessayer
A33: 07 AT INFO CAF REF | B33: IMI-VA-64102/04XL-1 | C33: BAYONNE | D33: 7 rue du 49ème régiment d'infanterie | E33: 45658 | G33: =E33+14 -> 45672 | P33: PB factu travaux réessayer
A34: 07 AT INFO CAF REF | B34: IMI-VA-40283/11Q1-1 | C34: Saint vincent de paul | D34: 160 route de Gorges | E34: 45691 | G34: =E34+14 -> 45705 | H34: 1084874 | P34: Att retour Yannick
A35: 07 AT INFO CAF REF | B35: IMI-VA-40123/01KZ-1 | C35: HERM | D35: 1116 route de cluquelardit | E35: 45658 | G35: =E35+14 -> 45672 | I35: 45824 | L35: 45975 | P35: Att valid Orange trv
A36: 07 AT INFO CAF REF | B36: IMI-VA-64024/035M-3 | C36: ANGLET | D36: 3 impasse des glycines | E36: 45946 | G36: =E36+14 -> 45960 | M36: 2957114 / 3117706 | N36: 45954 | O36: OK | P36: Att valid Orange trv
A37: 07 AT INFO CAF REF | B37: IMI-VA-40114/018K-2 | C37: GOURBERA | D37: 3691 ROUTE DE CASTETS | E37: 45931 | F37: 45937 | G37: =E37+14 -> 45945 | I37: 45947 | L37: 45938 | M37: 2963583 / 3057191 | N37: 46020 | O37: OK | P37: Att valid Orange devis
A38: 07 AT INFO CAF REF | B38: IMI-VA-40088/17PG-2 | C38: DAX | D38: 76 ROUTE DE SAUBAGNACQ | E38: 46027 | G38: =E38+14 -> 46041 | I38: 46038 | L38: 46057
A39: 07 AT INFO CAF REF | B39: IMI-VA-40062/0053-1 | C39: CAMPET ET LAMOLERE | D39: 565 ROUTE DE LA TUILERIE | E39: 45875 | G39: =E39+14 -> 45889 | I39: 45901 | L39: 45902 | P39: Att valid Orange FAC
A40: 07 AT INFO CAF REF | B40: IMI-VA-64260/01SW-1 | C40: HENDAYE | D40: Rue PARCHETEGUIA | E40: 45964 | G40: =E40+14 -> 45978 | H40: 1095238 | I40: 45978 | L40: 46003 | M40: 3057219 / 3117673 | N40: 46020 | O40: OK | P40: Att valid Orange trv
A41: 07 AT INFO CAF REF | B41: IMI-VA-40061/005T-2 | C41: CAMPAGNE | D41: 630 ROUTE DE JEANBEYLET | E41: 46031 | G41: =E41+14 -> 46045 | P41: Att valid Orange FAC
A42: 07 AT INFO CAF REF | B42: IMI-VA-40062/0051-1 | C42: CAMPET ET LAMOLERE | D42: 650 Route de la tuilerie | E42: 45950 | G42: =E42+14 -> 45964 | H42: 1101078 | I42: 46038 | L42: 46050 | P42: Att valid Orange trv
A43: 07 AT INFO CAF REF | B43: IMI-VA-64122/048T-1 | C43: BIARRITZ | D43: 119 AVENUE DE VERDUN | E43: 45894 | G43: =E43+14 -> 45908 | H43: 1088230 | I43: 45912 | L43: 46037 | M43: 3094358 | N43: 46038 | O43: OK | P43: Att valid Orange trv
A44: 07 AT INFO CAF REF | B44: IMI-VA-40279/15NT-1 | C44: ST PAUL les DAX | D44: 1515 ALL D'ARDY | E44: 45633 | G44: =E44+14 -> 45647 | H44: 1097780 | I44: 45787 | L44: 46038 | M44: 3094573 | N44: 46038 | O44: OK
A45: 07 AT INFO CAF REF | B45: IMI-VA-40123/01O5-1 | C45: HERM | D45: 1958 route du marquis | E45: 45658 | G45: =E45+14 -> 45672 | P45: Att valid Orange FAC
A46: 06 AT MAJ SI | B46: IMI-VA-40234/00CO-1 | C46: POUYDESSSEAUX | D46: 124 CHEMIN DES FRERES BORDE | E46: 45874 | G46: =E46+14 -> 45888 | H46: 1038871 | I46: 45901 | L46: 45926 | P46: demande Banbou 3175513
A47: 05.1 AT DTA | B47: IMI-VA-64125/00OI-1 | C47: BIDART | D47: 1 AVENUE DES RUSSES | E47: 45988 | G47: =E47+14 -> 46002 | H47: 1099066 | I47: 46014 | L47: 46020 | M47: 3057191 | N47: 46038 | O47: =N47+30 -> 46068
A48: 05.1 AT DTA | B48: IMI-VA-64260/019I-1 | C48: HENDAYE | D48: Rue henri Barbusse | E48: 45985 | G48: =E48+14 -> 45999 | H48: 1096796 | I48: 45992 | L48: 45999 | M48: 3057213 / 3117675 | N48: 46020 | O48: =N48+30 -> 46050
A49: 05.1 AT DTA | B49: IMI-VA-40320/006M-1 | C49: UCHACQ ET PARENTIS | D49: ROUTE DE LOUBIT | E49: 45988 | G49: =E49+14 -> 46002 | H49: 1097544 | I49: 46000 | L49: 46010 | M49: 3046399 / 3117711 | N49: 46013 | O49: =N49+30 -> 46043
A50: 05.1 AT DTA | B50: IMI-VA-64024/02RM-1 | C50: ANGLET | D50: ALLEE DE BORDENAVE | E50: 46010 | G50: =E50+14 -> 46024 | I50: 46014 | L50: 46028 | M50: 3073095 | N50: 46050 | O50: =N50+30 -> 46080
A51: 05.1 AT DTA | B51: IMI-VA-64122/03DM-1 | C51: BIARRITZ | D51: DOMAINE DE MIGRON | E51: 46010 | G51: =E51+14 -> 46024 | H51: 1099076 | I51: 46014 | L51: 46038 | M51: 3094416 | N51: 46038 | O51: =N51+30 -> 46068
A52: 05.1 AT DTA | B52: IMI-VA-40050/0017-1 | C52: BOSTENS | D52: ROUTE DE GAILLERES | E52: 46010 | G52: =E52+14 -> 46024 | H52: 1099057 | I52: 46014 | L52: 46043 | M52: 3105797 | N52: 46044 | O52: =N52+30 -> 46074
A53: 05.1 AT DTA | B53: IMI-VA-64125/00AP-1 | C53: BIDART | D53: 7 RUE ERRETEGIA | E53: 46000 | G53: =E53+14 -> 46014 | H53: 1099079 | I53: 46014 | L53: 46050 | M53: 3158862 | N53: 46066 | O53: =N53+30 -> 46096
A54: 05.1 AT DTA | B54: IMI-VA-40192/0860-1 | C54: MONT DE MARSAN | D54: 2 RUE MADRAY | E54: 45981 | G54: =E54+14 -> 45995 | H54: 1096781 | I54: 45992 | L54: 46050 | M54: 3162230 | N54: 46066 | O54: =N54+30 -> 46096
A55: 05.1 AT DTA | B55: IMI-VA-40274/00KE-1 | C55: ST MARTIN D ONEY | D55: 329 RUE DE BAREYAT | E55: 46015 | G55: =E55+14 -> 46029 | H55: 1100494 | I55: 46035 | L55: 46050 | M55: 3162307 | N55: 46066 | O55: =N55+30 -> 46096
A56: 05 AT PV | B56: IMI-VA-64483/02AV-1 | C56: ST JEAN DE LUZ | D56: 31 RUE SAINT JACQUES | E56: 45951 | F56: 45953 | G56: =E56+14 -> 45965 | H56: 1094823 | I56: 45973 | J56: 46043 | K56: =J56+15 -> 46058 | P56: PV refaite le 16/01
A57: 05 AT PV | B57: IMI-VA-40202/025J-1 | C57: NARROSSE | D57: 11 B RUE DE LAVOISIER | E57: 46027 | G57: =E57+14 -> 46041 | H57: 1102273 | I57: 46050 | J57: =I57+15 -> 46065 | K57: =J57+15 -> 46080
A58: 05 AT PV | B58: IMI-VA-40320/004A-1 | C58: UCHACQ ET PARENTIS | D58: 812 ROUTE DE LA BASE | E58: 46049 | F58: 46051 | G58: =E58+14 -> 46063 | P58: Pres demande
A59: 05 AT PV | B59: IMI-VA-40139/0072-1 | C59: LAGLORIEUSE | D59: 2405 ROUTE DE PUJO | E59: 46049 | F59: 46051 | G59: =E59+14 -> 46063 | H59: 1103983 | I59: 46066 | J59: =I59+15 -> 46081 | K59: =J59+15 -> 46096
A60: 05 AT PV | B60: IMI-VA-40234/00E9-1 | C60: POUYDESSEAUX | D60: 383 ROUTE DE CORBLEU | E60: 46050 | F60: 46051 | G60: =E60+14 -> 46064 | H60: 1103994 | I60: 46066 | J60: =I60+15 -> 46081 | K60: =J60+15 -> 46096
A61: 05 AT PV | B61: IMI-VA-40123/01P6-1 | C61: HERM | D61: AVENUE HOSSELEYRE | E61: 46062 | G61: =E61+14 -> 46076 | H61: 1104014 | I61: 46066 | J61: =I61+15 -> 46081 | K61: =J61+15 -> 46096
A62: 05 AT PV | B62: IMI-VA-40279/15PU-1 | C62: ST PAUL LES DAX | D62: 1378 ROUTE DE HERM | E62: 46056 | G62: =E62+14 -> 46070 | H62: 1104021 | I62: 46066 | J62: =I62+15 -> 46081 | K62: =J62+15 -> 46096
A63: 05 AT PV | B63: IMI-VA-64483/00GZ-1 | C63: ST JEAN DE LUZ | D63: 3 ALLEE BEHEREKO BORDA | E63: 46050 | F63: 46051 | G63: 46056 | H63: 1104026 | I63: 46066 | J63: =I63+15 -> 46081 | K63: =J63+15 -> 46096
A64: 05 AT PV | B64: IMI-VA-64483/02I9-1 | C64: ST JEAN DE LUZ | D64: 78 BLVRD THIERS | E64: 46049 | F64: 46051 | G64: =E64+14 -> 46063 | H64: 1104031 | I64: 46066 | J64: =I64+15 -> 46081 | K64: =J64+15 -> 46096
A65: 05 AT PV | B65: IMI-VA-40088/06KT-1 | C65: DAX | D65: 53 RUE D ASPREMONT | E65: 46044 | F65: 46045 | G65: =E65+14 -> 46058 | H65: 1104037 | I65: 46066 | J65: =I65+15 -> 46081 | K65: =J65+15 -> 46096
A66: 05 AT PV | B66: IMI-VA-64024/03RO-1 | C66: ANGLET | D66: 16 RUE D AUGERON | E66: 46050 | F66: 46051 | G66: =E66+14 -> 46064 | H66: 1104044 | I66: 46066 | J66: =I66+15 -> 46081 | K66: =J66+15 -> 46096
A67: 05 AT PV | B67: IMI-VA-64024/07IQ-1 | C67: ANGLET | D67: IMPASSE DE MONTBRUN | E67: 45999 | G67: =E67+14 -> 46013 | H67: 1104054 | I67: 46066 | J67: =I67+15 -> 46081 | K67: =J67+15 -> 46096
A68: 05 AT PV | B68: IMI-VA-40279/055B-1 | C68: ST PAUL LES DAX | D68: 3 RUE DU BEARN | E68: 46050 | F68: 46051 | G68: =E68+14 -> 46064 | H68: 1104065 | I68: 46066 | J68: =I68+15 -> 46081 | K68: =J68+15 -> 46096
A69: 02 RETOUR VT | B69: IMI-VA-40114/017F-1 | C69: GOURBERA | D69: Chemin de pountinbeou | F69: 46045 | G69: 46056
A70: 02 RETOUR VT | B70: IMI-VA-40320/004W-1 | C70: UCHACQ ET PARENTIS | D70: RTE DE LA BASE | E70: 46062
A71: 01.2 A REMONTER | B71: IMI-VA-40280/00CS-1 | C71: ST PERDON | D71: 3100 ROUTE DE SAINT ORENS
A72: 01 VT A FAIRE | B72: IMI-VA-40279/15OX-1 | C72: ST PAUL LES DAX | D72: 1824 route des barthes | E72: 46058
A73: 01 VT A FAIRE | B73: IMI-VA-64125/00ZE-2 | C73: BIDART | D73: RUE HARGUIN ETCHEBERRY | E73: 46071
A74: 01 VT A FAIRE | B74: IMI-VA-64260/01UQ-1 | C74: HENDAYE | D74: 3 RUE DU PONT | E74: 46071
A75: 01 VT A FAIRE | B75: IMI-VA-64024/06GU-1 | C75: ANGLET | D75: 49 RUE DE L UNION | E75: 46071

Sheet BEIN
A1: DEPT | B1: ETAT | C1: SJ | D1: OEIE | E1: Date creation | F1: Date MAX pour CRVT 1 (9I) | G1: Date MAX pour CRVT 1 + OINE + APD (72) | H1: Date fin de travaux client | I1: CRVT3 Fin de travaux (9I et 72) | J1: Commentaire
A2: 12 | C2: 72 | D2: ROD600310 | E2: 46065 | F2: =E2+30 -> 46095 | G2: =E2+30 -> 46095

Sheet COMAC CAPFT
A1: ETAT | B1: POI | C1: COMAC/CAPFT | D1: NOMBRE D'APPUIS | E1: DATE CREATION | F1: DATE R ETUDE | G1: VILLE | H1: ADRESSE | I1: COMMENTAIRES
B2: MDM300296 | C2: COMAC | D2: 1
B3: MDM400362 | C3: COMAC | D3: 3
B4: MDM400881 | C4: COMAC | D4: 2
A5: 05 Dossier terminer | B5: NIM500036 | C5: COMAC | D5: 2
A6: 05 Dossier terminer | B6: NIM500036 | C6: CAPFT | D6: 10
A7: 05 Dossier terminer | B7: ROD400677 | C7: COMAC | D7: 1
A8: 05 Dossier terminer | B8: ROD400677 | C8: CAPFT | D8: 22
B9: ROD500059 | C9: COMAC | D9: 1 | F9: 45783 | G9: Cassagnes-Bégonhes | H9: 15 RUE DE CABRIERES
B10: ROD500237 | C10: COMAC | D10: 1
B11: ROD500352 | C11: CAPFT | D11: 15
B12: ROD500354 | C12: CAPFT | D12: 27
B13: MEN500269 | C13: CAPFT | D13: 13
B14: ROD401146 | C14: COMAC | D14: 5
B15: NIM401251
B16: MEN500305 | C16: COMAC | D16: 1
B17: ALE500143 | C17: COMAC
B18: ALE500143 | C18: CAPFT | D18: 11
B19: ROD500264 | C19: CAPFT | D19: 2
B20: RRE500282 | C20: CAPFT | D20: 5
B21: BEZ400612 | C21: CAPFT
B22: LOR500901 | C22: CAPFT | D22: 5
B23: DFE-DEP-SN-56158-0235-1 | C23: COMAC | D23: 1
B24: DFE-DEP-SN-56158-0235-1 | C24: CAPFT | D24: 3
B25: DEP-AN-56101-03HN-1 | C25: CAPFT | D25: 14
B26: DEP-AN-5615800NZ-1 | C26: CAPFT | D26: 28
A27: 04 Dossier à reprendre | B27: MEN300571 | C27: COMAC | D27: 2
A28: 05 Dossier terminer | B28: MPL301383 | C28: CAPFT | D28: 7 | E28: 45958 | F28: 45967 | G28: COURNONTERRAL | H28: 10 RUE BASTIDE DE L OULIEU
A29: 05 Dossier terminer | B29: ROD501511 | C29: COMAC | D29: 1 | G29: ESTAING | H29: 10 RUE BASTIDE DE L OULIEU
A30: 05 Dossier terminer | B30: ROD501511 | C30: CAPFT | D30: 156 | F30: 45965 | G30: ESTAING | H30: LIEU DIT SOLEILLAGES
A31: 05 Dossier terminer | B31: MEN400779 | C31: COMAC | D31: 1 | G31: MONTS DE RANDON | H31: 4 LOT LES HAUTS DE CHEYROUSES
A32: 05 Dossier terminer | B32: MEN400779 | C32: CAPFT | D32: 5 | F32: 45966 | G32: MONTS DE RANDON | H32: 4 LOT LES HAUTS DE CHEYROUSES
A33: 05 Dossier terminer | B33: ROD300381 | C33: CAPFT | D33: 23 | F33: 46041 | G33: MILLAU | H33: 90 RUE DE LA CROIX VIEILLE
A34: 05 Dossier terminer | B34: NIM500910 | C34: CAPFT | D34: 10 | F34: 45973 | G34: ST GILLES
A35: 05 Dossier terminer | B35: NIM500910 | C35: COMAC | D35: 4 | G35: ST GILLES
A36: 05 Dossier terminer | B36: LOR500901 | C36: CAPFT | D36: 10 | F36: 45974
A37: 05 Dossier terminer | B37: ROD401937 | C37: CAPFT | D37: 5 | F37: 46002 | G37: VILLEFRANCHE DE ROUERGUE | H37: 8 AVENUE PAUL RAMADIER
A38: 05 Dossier terminer | B38: NIM500846 | C38: CAPFT | D38: 2 | F38: 45996 | G38: REDESSAN | H38: 83 ROUTE DE BEAUCAIRE,
A39: 05 Dossier terminer | B39: NIM500735 | C39: CAPFT | D39: 2
A40: 05 Dossier terminer | B40: ROD502100 | C40: CAPFT | D40: 34 | F40: 46042
A41: 05 Dossier terminer | B41: MPL501398 | C41: CAPFT | D41: 1 | F41: 46041
A42: 05 Dossier terminer | B42: NIM500816 | C42: COMAC | D42: 2
A43: 05 Dossier terminer | B43: NIM500816 | C43: CAPFT | D43: 13 | F43: 46043 | H43: 1 RUE DU 8 MAI 1945
A44: 05 Dossier terminer | B44: MPL501398 | C44: COMAC | D44: 1
A45: 05 Dossier terminer | B45: ALE500147 | C45: CAPFT | D45: 11 | F45: 46045 | H45: 2 LOTISSEMENT LES CLOS
A46: 05 Dossier terminer | B46: ALE500147 | C46: COMAC | D46: 3
A47: 05 Dossier terminer | B47: MPL401457 | C47: COMAC | D47: 2
A48: 05 Dossier terminer | B48: MEN500707 | C48: CAPFT
A49: 01 Dossier à monter | B49: ROD600265 | C49: CAPFT | D49: 10
A50: 01 Dossier à monter | B50: ROD600265 | C50: COMAC | D50: 1
A51: 01 Dossier à monter | B51: QPR600185 | C51: COMAC | D51: 1

Sheet DETAIL SECTEUR
A1: MDM-DAX | C1: QPR-CRO | E1: SPI BRETAGNE | G1: BAY | I1: PAU | K1: ROD | M1: MEN | P1: Étiquettes de lignes | Q1: Somme de DRE KO | S1: Étiquettes de lignes | T1: Somme de NB DE DOSSIERS
C2: ETAT | D2: 01 AT VT | G2: ETAT | H2: POI EN TRAVAUX | I2: ETAT | J2: (Tous) | K2: ETAT | L2: (Tous) | M2: ETAT | N2: (Tous) | P2: MEN | Q2: 5 | S2: MEN | T2: 194
A3: DRE | B3: (Tous) | C3: SJ | D3: (Tous) | G3: SJ | H3: (Tous) | I3: SJ | J3: (Tous) | K3: SJ | L3: (Tous) | M3: SJ | N3: (Tous) | P3: QPR-CRO | Q3: 36 | S3: QPR-CRO | T3: 176
A4: SJ | B4: (Tous) | C4: DRE | D4: (Tous) | E4: ETAT | F4: (Tous) | G4: DRE | H4: (Tous) | I4: DRE | J4: (Tous) | K4: DRE | L4: (Tous) | M4: DRE | N4: (Tous) | P4: ROD | Q4: 7 | S4: ROD | T4: 255
A5: MOIS | B5: (Tous) | C5: MOIS | D5: (Tous) | E5: ANNEE | F5: (Tous) | G5: MOIS | H5: (Tous) | I5: mois | J5: (Tous) | K5: MOIS | L5: (Tous) | M5: MOIS | N5: (Tous) | P5: SPI BRETAGNE | S5: SPI BRETAGNE | T5: 188
A6: ANNEE | B6: (Tous) | C6: ANNEE | D6: (Tous) | E6: MOIS | F6: (Tous) | G6: ANNEE | H6: (Tous) | I6: annee | J6: (Tous) | K6: ANNEE | L6: (Tous) | M6: ANNEE | N6: (Tous) | P6: (vide) | S6: (vide)
A7: Total général | B7: =GETPIVOTDATA("POI",$B$8) -> 124 | C7: Total général | D7: =GETPIVOTDATA("POI",$C$8) -> 67 | E7: Total général | F7: =GETPIVOTDATA("COG",$E$8) -> 138 | G7: Total général | H7: =GETPIVOTDATA("POI",$G$8) -> 11 | I7: Total général | J7: =GETPIVOTDATA("POI",$I$8) -> 29 | K7: Total général | L7: =GETPIVOTDATA("POI",$K$8) -> 255 | M7: Total général | N7: =GETPIVOTDATA("POI",$M$8) -> 194 | P7: GDP AQ | Q7: 15 | S7: GDP AQ | T7: 117
A8: Étiquettes de lignes | B8: Nombre de POI | C8: Étiquettes de lignes | D8: Nombre de POI | E8: Étiquettes de lignes | F8: Nombre de COG | G8: Étiquettes de lignes | H8: Nombre de POI | I8: Étiquettes de lignes | J8: Nombre de POI | K8: Étiquettes de lignes | L8: Nombre de POI | M8: Étiquettes de lignes | N8: Nombre de POI | P8: SPI AQ | S8: SPI AQ | T8: 84
A9: AMOU | B9: 1 | C9: AUDIERNE | D9: 1 | E9: CAUDAN | F9: 1 | G9: ANGLET | H9: 3 | I9: ARAMITS | J9: 5 | K9: AURIAC-LAGAST | L9: 1 | M9: ARZENC DE RANDON | N9: 1 | P9: Total général | Q9: 63 | S9: Total général | T9: 1014
A10: ARGELOS | B10: 1 | C10: BENODET | D10: 2 | E10: CLEGUER | F10: 1 | G10: BAYONNE | H10: 2 | I10: ARTIGUELOUVE | J10: 1 | K10: BALAGUIER SUR RANCE | M10: GRABELS | N10: 1
A11: AUREILHAN | B11: 1 | C11: COMBRIT | D11: 2 | E11: ERGUE GABERIC | F11: 3 | G11: BIARRITZ | H11: 2 | I11: BUROS | J11: 1 | K11: LA BORIE DE POUJADE | L11: 1 | M11: NIMES | N11: 1
A12: BAHUS SOUBIRAN | B12: 1 | C12: PLOMEUR | D12: 3 | E12: HENNEBONT | F12: 1 | G12: BIDART | H12: 1 | I12: COARRAZE | J12: 1 | K12: BROMMAT | L12: 1 | M12: ALBARET LE COMTAL | N12: 1
A13: BEGAAR | B13: 1 | C13: PLONEOUR LANVERN | D13: 1 | E13: LANESTER | F13: 3 | G13: BOUCAU | H13: 1 | I13: DOAZON | J13: 1 | K13: ESPALION | L13: 1 | M13: ALBARET SAINTE MARIE | N13: 1
A14: BENESSE MAREMNE | B14: 1 | C14: PLOUHINEC | D14: 1 | E14: LOCMIQUELIC | F14: 1 | G14: LABENNE | H14: 1 | I14: GAN | J14: 2 | K14: LESTRADE ET THOUELS | M14: ALBARET STE MARIE | N14: 2
A15: BENQUET | B15: 3 | C15: PONT L ABBE | D15: 1 | E15: LORIENT | F15: 6 | G15: LAHONCE | H15: 1 | I15: GELOS | J15: 1 | K15: LD TAYSSES | L15: 1 | M15: ALES | N15: 1
A16: 570 AV MARSAN | B16: 1 | C16: RIEC SUR BELON | D16: 1 | E16: PLESCOP | F16: 1 | G16: Total général | H16: 11 | I16: GERDEREST | J16: 1 | K16: MILLAU | L16: 2 | M16: ALLENC | N16: 2
A17: 1076 RTE DE HAUT MAUCO | B17: 1 | C17: PLOEMEUR | D17: 1 | E17: PLOEMEUR | F17: 4 | I17: HAGETAUBIN | J17: 1 | K17: SAINT CHELY D AUBRAC | L17: 1 | M17: ARZENC DE RANDON | N17: 2
A18: 62 AVENUE DU MARSAN | B18: 1 | C18: LE CROISTY | D18: 1 | E18: PORT LOUIS | F18: 1 | I18: JURANCON | J18: 2 | K18: VERRIERES | M18: AUROUX | N18: 1
A19: BISCARROSSE | B19: 1 | C19: MESLAN | D19: 1 | E19: QUEVEN | F19: 1 | I19: LABATUT | J19: 1 | K19: 1 CONCLUS | L19: 1 | M19: BADAROUX | N19: 2
A20: BOUGUE | B20: 1 | C20: SAINT CARADEC TREGOMEL | D20: 1 | E20: QUIMPER | F20: 13 | I20: LALONGUE | J20: 1 | K20: VILLEFRANCHE DE PANAT | M20: BALSIEGES | N20: 3
A21: CAMPAGNE | B21: 2 | C21: QUIMPER | D21: 1 | E21: RENNES | F21: 90 | I21: LESCAR | J21: 1 | K21: 6 AV DE LA PLAGE | L21: 1 | M21: BANASSAC-CANILHAC | N21: 8
A22: CAMPET ET LAMOLERE | B22: 1 | C22: QUIBERON | D22: 5 | E22: ALLEE DE LA GARAYE | F22: 1 | I22: LOUVIE JUZON | J22: 1 | K22: AGUESSAC | L22: 6 | M22: BARJAC | N22: 3
A23: CASTELNER | B23: 1 | C23: THEIX NOYALO | D23: 1 | E23: ALLEE JEAN DE LA VARENDE | F23: 1 | I23: MEILLON | J23: 1 | K23: ALRANCE | L23: 3 | M23: BEL-AIR-VAL-D'ANCE | N23: 1
A24: CERE | B24: 1 | C24: BERRIC | D24: 1 | E24: AVENUE ANDRE MALRAUX | F24: 1 | I24: MIOSSENS | J24: 1 | K24: ARGENCE EN AUBRAC | L24: 1 | M24: BEZIERS | N24: 2
A25: DAX | B25: 2 | C25: MONTAUBAN DE BRETAGNE | D25: 3 | E25: AVENUE AUGUSTE BRIZEUX | F25: 1 | I25: MIREPEIX | J25: 2 | K25: ARVIEU | L25: 2 | M25: BORNE | N25: 1
A26: GAILLERES | B26: 1 | C26: PIRE CHANCE | D26: 2 | E26: AVENUE DES PAYS BAS | F26: 1 | I26: MORLANNE | J26: 1 | K26: AUBIN | M26: BOURGS SUR COLAGNE | N26: 6
A27: GAMARDE LES BAINS | B27: 1 | C27: GOURIN | D27: 1 | E27: AVENUE GROS MALHON | F27: 1 | I27: OGEU LES BAINS | J27: 1 | K27: 5 PL JEAN JAURES à AUBIN | L27: 1 | M27: BRENOUX | N27: 1
A28: GEAUNE | B28: 3 | C28: GOUESNACH | D28: 1 | E28: AVENUE JEAN JANVIER | F28: 2 | I28: ORTHEZ | J28: 1 | K28: AURIAC-LAGAST | L28: 1 | M28: CANS ET CEVENNES | N28: 2
A29: GOOS | B29: 1 | C29: HENT REUNIOU | D29: 1 | E29: AVENUE JORGE SEMPRUN | F29: 1 | I29: PAU | J29: 1 | K29: AUZITS | L29: 1 | M29: CASTELNAU LE LEZ | N29: 1
A30: GOURBERA | B30: 5 | C30: THORIGNE FOUILLARD | D30: 1 | E30: BOULEVARD ALBERT 1ER | F30: 1 | I30: SAINT CASTIN | J30: 1 | K30: BASSE CURVALLE | L30: 1 | M30: CAUSSES | N30: 1
A31: HABAS | B31: 1 | C31: 25 RUE NATIONALE 12 | D31: 1 | E31: BOULEVARD ALEXIS CARREL | F31: 1 | I31: (vide) | K31: BELMONT SUR RANCE | L31: 5 | M31: CHADENET | N31: 1
A32: HERM | B32: 22 | C32: RENNES | D32: 1 | E32: BOULEVARD DE BULGARIE | F32: 1 | I32: Total général | J32: 29 | K32: BERTHOLENE | L32: 3 | M32: CHANAC | N32: 2
A33: HORSARRIEU | B33: 1 | C33: BD LA TOUR D AUVERGNE | D33: 1 | E33: BOULEVARD DE CHEZY | F33: 1 | K33: BOZOULS | L33: 4 | M33: CHASTEL NOUVEL | N33: 1
A34: LAGLORIEUSE | B34: 2 | C34: REDON | D34: 1 | E34: BOULEVARD DE LA GUERINAIS | F34: 1 | K34: BRANDONNET | L34: 1 | M34: CHAULHAC | N34: 1
A35: LESGOR | B35: 1 | C35: RUE DU PARADET | D35: 1 | E35: BOULEVARD DE LA TOUR D AUVERGNE | F35: 1 | K35: BROMMAT | L35: 2 | M35: COUCOURON | N35: 1
A36: LESPERON | B36: 1 | C36: TREGUNC | D36: 1 | E36: BOULEVARD DE SEVIGNE | F36: 2 | K36: BROMMET | L36: 1 | M36: ESCLANEDES | N36: 1
A37: MAYLIS | B37: 1 | C37: 37B RTE MELGVEN | D37: 1 | E37: BOULEVARD JEANNE D ARC | F37: 1 | K37: BROUSSE LE CHATEAU | L37: 2 | M37: FLORAC | N37: 2
A38: MAZEROLLES | B38: 1 | C38: VITRE | D38: 1 | E38: BOULEVARD SAINT JEAN BAPTISTE DE LA SAL | F38: 1 | K38: CALMONT | M38: GENERAC | N38: 1
A39: MEES | B39: 2 | C39: R DU COLLEGE | D39: 1 | E39: LE PLESSIX LOUVEL | F39: 1 | K39: 689 ROUTE DE CATUSSE | L39: 1 | M39: GORGES DU TARN CAUSSES | N39: 1
A40: MEZOS | B40: 3 | C40: SAINT JEAN BREVELAY | D40: 1 | E40: MAIL FELIX LECLERC | F40: 1 | K40: LE PUECH SAINT AMANS | L40: 1 | M40: GRABELS | N40: 2
A41: MIMIZAN | B41: 1 | C41: RUE DE RENNES | D41: 1 | E41: MAIL FRANCOIS MITTERRAND | F41: 2 | K41: CAMBOULAS | L41: 1 | M41: 1227 RUE DE LA VALSIERE | N41: 1
A42: MIRAMONT SENSACQ | B42: 1 | C42: SURZUR | D42: 1 | E42: PLACE DE PRAGUE | F42: 2 | K42: CAMBOULAZET | L42: 2 | M42: 60 IMPASSE ANTOINE SAPORTA | N42: 1
A43: MONGET | B43: 3 | C43: 1 IMP DU KOH CAPIN | D43: 1 | E43: PLACE DE SERBIE | F43: 1 | K43: CAMJAC | L43: 1 | M43: GRANDRIEU | N43: 5
A44: MONT DE MARSAN | B44: 4 | C44: GUIDEL | D44: 1 | E44: PLACE DU MONTENEGRO | F44: 1 | K44: CAMPAGNAC | L44: 2 | M44: GREZES | N44: 3
A45: PERQUIE | B45: 1 | C45: 26 RUE EDOUARD CADIC | D45: 1 | E45: PLACE DU PARLEMENT DE BRETAGNE | F45: 1 | K45: CAMPUAC | L45: 4 | M45: ISPAGNAC | N45: 3
A46: PISSOS | B46: 2 | C46: AVESSAC | D46: 1 | E46: PLACE EUGENE AULNETTE | F46: 1 | K46: CASSAGNES BEGONHES | L46: 1 | M46: JULIANGES | N46: 2
A47: POMAREZ | B47: 1 | C47: A CROIX DU BILAIS | D47: 1 | E47: PLACE JULES VALLES | F47: 1 | K47: CASSUEJOULS | L47: 1 | M47: JUVIGNAC | N47: 1
A48: PONTENX LES FORGES | B48: 1 | C48: BRECH | D48: 2 | E48: PLACE MARECHAL JUIN | F48: 1 | K48: CASTELNAU DE MANDAILLES | L48: 4 | M48: LA CANOURGUE | N48: 6
A49: PONTONX SUR L'ADOUR | B49: 2 | C49: 50 RUE PIERRE ALLIO | D49: 2 | E49: QUAI DE LA PREVALAYE | F49: 1 | K49: CENTRES | L49: 1 | M49: LA CANOURGUE | N49: 1
A50: ROQUEFORT | B50: 3 | C50: TREAL | D50: 1 | E50: RUE AIMEE ANTIGNAC | F50: 1 | K50: CLAIRVAUX D AVEYRON | M50: LA FAGE MONTIVERNOUX | N50: 1
A51: SAINT JUSTIN | B51: 2 | C51: LA MARCHE | D51: 1 | E51: RUE ALPHONSE GUERIN | F51: 1 | K51: 9 RTE DU VALLON | L51: 1 | M51: LA MALENE | N51: 1
A52: SAINT MARTIN D'ONEY | B52: 2 | C52: SAINT GRAVE | D52: 1 | E52: RUE ARTHUR FONTAINE | F52: 1 | K52: COMBRET | L52: 3 | M52: LA PANOUSE | N52: 1
A53: SAINT PERDON | B53: 1 | C53: ZA LANVAUX | D53: 1 | E53: RUE CAPITAINE ALFRED DREYFUS | F53: 2 | K53: COMPEYRE | L53: 2 | M53: LA TIEULE | N53: 1
A54: SAINT PIERRE DU MONT | B54: 2 | C54: PLOUAY | D54: 1 | E54: RUE CARDINAL PAUL GOUYON | F54: 1 | K54: CONQUES EN ROUERGUE | L54: 2 | M54: LACHAMP-RIBENNES | N54: 1
A55: SAINT SEVER | B55: 1 | C55: KERPRAT | D55: 1 | E55: RUE D ANTRAIN | F55: 1 | K55: CORNUS | L55: 1 | M55: LANGOGNE | N55: 7
A56: Saint vincent de paul | B56: 1 | C56: QUEVEN | D56: 1 | E56: RUE DE BREST | F56: 4 | K56: COUBISOU | L56: 4 | M56: LAUBERT | N56: 1
A57: SANGUINET | B57: 1 | C57: 1 R EDOUARD HERRIOT | D57: 1 | E57: RUE DE DINAN | F57: 2 | K57: CRANSAC | L57: 2 | M57: LE MALZIEU VILLE | N57: 1
A58: SARBAZAN | B58: 2 | C58: CALAN | D58: 1 | E58: RUE DE LA CRECHE | F58: 1 | K58: CRESPIN | L58: 1 | M58: LES BESSONS | N58: 2
A59: SEYRESSE | B59: 1 | C59: 2 PLACE DE L EGLISE | D59: 1 | E59: RUE DE LA MONNAIE | F59: 1 | K59: CURAN | L59: 1 | M59: LES BONDONS | N59: 3
A60: SIEST | B60: 1 | C60: LARMOR PLAGE | D60: 2 | E60: RUE DE LA ROSAIS | F60: 1 | K60: DURENQUE | L60: 1 | M60: LES LAUBIES | N60: 1
A61: SOUPROSSE | B61: 1 | C61: 11 RUE DES ARCHITECTES | D61: 1 | E61: RUE DE LA SANTE | F61: 1 | K61: ESPALION | L61: 7 | M61: MARVEJOLS | N61: 6
A62: ST PAUL les DAX | B62: 7 | C62: 15 R DU VIEUX MOULIN | D62: 1 | E62: RUE DE LA TERRE ADELIE | F62: 1 | K62: ESPEYRAC | L62: 2 | M62: MASSEGROS CAUSSES GORGES | N62: 3
... A76: AUDIGNON | B76: 1 | C76: GUISCRIFF | D76: 1 | E76: RUE FRANCOIS LANNO | F76: 1 | K76: LAVAT ROQUECEZIERE | L76: 1 | M76: PREVENCHERES | N76: 3
A77: (vide) | C77: 5 CHEMINS | D77: 1 | E77: RUE GARENGEOT | F77: 1 | K77: LE FEL | L77: 1 | M77: RIMEIZE | N77: 2
A78: POUYDESSEAUX | B78: 1 | C78: MALGUENAC | D78: 1 | E78: RUE GUY ROPARTZ | F78: 1 | K78: LE NAYRAC | L78: 1 | M78: SAINT ALBAN LIMAGNOLE | N78: 2
A79: Total général | B79: 124 | C79: LE SENCE | D79: 1 | E79: RUE HOCHE | F79: 1 | K79: LE TRUEL | L79: 1 | M79: SAINT ANDRE CAPCEZE | N79: 2
C80: LANGUIDIC | D80: 2 | E80: RUE JEAN BRULELOU DIT BRITO | F80: 1 | K80: LEDERGUES | L80: 1 | M80: SAINT BONNET DE CHIRAC | N80: 1
C81: KERMIRIETTE | D81: 1 | E81: RUE JOSEPH SAUVEUR | F81: 1 | K81: LES ALBRES | M81: SAINT CHELY D APCHER | N81: 6
C82: BOTLEVENANT | D82: 1 | E82: RUE JOSEPH TURMEL | F82: 1 | K82: CHEMIN PIERRE BLANCHE | L82: 1 | M82: SAINT CHRISTOPHE D ALLIER | N82: 1
C83: PLEUVEN | D83: 1 | E83: RUE LE GUEN DE KERANGAL | F83: 1 | K83: LES COSTES GOZON | L83: 1 | M83: SAINT ETIENNE VAL FRANC | N83: 1
C84: CHE KILOURIN | D84: 1 | E84: RUE LEGRAVEREND | F84: 1 | K84: LESCURE JAOUL | L84: 1 | M84: SAINT GAL | N84: 2
C85: DOMALAIN | D85: 1 | E85: RUE LOUIS POSTEL | F85: 1 | K85: LESTRADE ET THOUELS | L85: 2 | M85: SAINT GERMAIN DE CALBERTE | N85: 2
C86: RUE NOTRE DAME DE LOURDES | D86: 1 | E86: RUE PAPU | F86: 1 | K86: LIOUJAS LA LOUBIERE | L86: 2 | M86: SAINT GERMAIN DU TEIL | N86: 1
C87: GUERN | D87: 1 | E87: RUE PAUL LOUIS COURIER | F87: 1 | K87: LIVINHAC LE HAUT | L87: 1 | M87: SAINT GILLES | N87: 1
C88: KERAURAY | D88: 1 | E88: RUE PIERRE AMYS | F88: 1 | K88: LUC LA PRIMAUBE | L88: 1 | M88: SAINT LAURENT DE MURET | N88: 1
C89: LOCMALO | D89: 1 | E89: RUE POULLAIN DUPARC | F89: 2 | K89: MANHAC | L89: 2 | M89: SAINT LAURENT DE VEYRES | N89: 1
C90: PONT MEEN | D90: 1 | E90: RUE RENE YVES CRESTON | F90: 1 | K90: MARCILLAC VALLON | L90: 2 | M90: SAINT MARTIN DE BOUBAUX | N90: 1
C91: LE CROUAIS | D91: 1 | E91: RUE SAINT HELIER | F91: 1 | K91: MELJAC | M91: SAINT PIERRE DES TRIPIERS | N91: 1
C92: BEL AIR | D92: 1 | E92: RUE SAINT MALO | F92: 3 | K92: 8 GRASCAZES BASSES | L92: 1 | M92: SAINT PRIVAT DU FAU | N92: 1
C93: BOURG DES COMPTES | D93: 1 | E93: RUE XAVIER GRALL | F93: 1 | K93: MILLAU | L93: 8 | M93: LE VILLARD GRAND | N93: 1
C94: LA GREE GUISSONNIERE | D94: 1 | E94: SQUARE DE GALICIE | F94: 1 | K94: MONJAUX | L94: 1 | M94: SAINT SAUVEUR DE GINESTOU | N94: 1
C95: Total général | D95: 67 | E95: SQUARE DU DOCTEUR GUERIN | F95: 3 | K95: MONTLAUR | L95: 3 | M95: SAINT SAUVEUR DE GINESTOUX | N95: 2
E96: SQUARE DU ROI ARTHUR | F96: 1 | K96: MONTOZIER | L96: 1 | M96: SAINTE CROIX VALLEE FRANCAISE | N96: 1
E97: SQUARE YVES MONTAND | F97: 1 | K97: MONTPEYROUX | L97: 1 | M97: SENT DE LA CALADE | N97: 1
E98: SENE | F98: 2 | K98: MONTROZIER | L98: 1 | M98: SERVERETTE | N98: 2
E99: ST AVE | F99: 1 | K99: MOUNES PROHENCOU | L99: 1 | M99: ST CHELY D APCHER | N99: 3
E100: SURZUR | F100: 1 | K100: MOURET | L100: 2 | M100: TERMES | N100: 2
E101: TREFFLEAN | F101: 1 | K101: MURET LE CHATEAU | L101: 1 | M101: TERRANJOU | N101: 1
E102: VANNES | F102: 7 | K102: NAJAC | M102: VEBRON | N102: 1
E103: Total général | F103: 138 | K103: 1 PL SAINT BARTHELEMY | L103: 1 | M103: MONTAGUT | N103: 1
K104: NANT | L104: 1 | M104: (vide)
K105: NAUCELLE | L105: 3 | M105: Total général | N105: 194
K106: OLEMPS
K107: 425 RTE DE CAYSSIOLET | L107: 1
K108: ONET LE CHATEAU
K109: 5 R LORIOTS | L109: 1
K110: ONET LE CHATEAU | L110: 1
K111: ONQUES EN ROUERGUE
K112: L'Horte | L112: 1
K113: PIERREFICHE
...

Sheet Feuil2
A1: 01 AT VT | D1: 01 VT A FAIRE | F1: 01 Dossier à monter
A2: 01.2 A REMONTER | D2: 01.2 A REMONTER | F2: 02 En cours
A3: 02 RETOUR VT | D3: 02 RETOUR VT | F3: 03 Att Infos
A4: 03 DOSSIER A REPRENDRE | D4: 03 DOSSIER A REPRENDRE | F4: 04 Dossier à reprendre
A5: 04 DOSSIER A MONTER | D5: 04 DOSSIER A MONTER | F5: 05 Dossier terminer
A6: 05 AT INFO CAF REF | D6: 05 AT PV
A7: 05.1 ETU TRANSMISE | D7: 05.1 AT DTA
A8: 06 AT DEVIS CLIENT | D8: 05.2 ATT DT
A9: 07 AT TRVX CLIENT | D9: 06 AT MAJ SI
A10: 08 AT COMAC/CAPFT | D10: 07 AT INFO CAF REF
A11: 09 AT DEVIS ORANGE/RIP | D11: 08 AT DEVIS ORANGE/RIP
A12: 10 AT PV | D12: 09 POI EN TRAVAUX
A13: 10.1 ATT DT | D13: 09.1 ATT DOE
A14: 11 AT DTA | D14: 10 POI EN FACTU
A15: 12 AT MAJ SI | D15: 11 RECOL A FAIRE
A16: 13 ETAT 5
A17: 14 POI EN TRAVAUX
A18: 14.1 AT RETOUR DOE
A19: 15 POI FACTU
A20: 16 DOSSIER PAYE

Sheet TP SWAN
A1: Act | B1: Département | C1: Ilot | D1: Centre | E1: Acteur | F1: Référence | G1: Commune | H1: besoin TP | I1: Date TP | J1: Etat/Plannif | K1: N° SWAN
A2: QRL | B2: 12 | C2: PV5 | D2: REQ | E2: FRAL TELECOM | F2: 12.TR210021-REQUISTA | G2: REQUISTA | H2: OUI | I2: 45910 | J2: Préparé | K2: T508176152
A3: QRL | B3: 12 | C3: PV5 | D3: LAG | E3: FRAL TELECOM | F3: CEOCE2502G80727=1 | H3: OUI | I3: 45911 | J3: Préparé | K3: T508195785
A4: QRL | B4: 12 | C4: PV5 | D4: RIG | E4: FRAL TELECOM | F4: CEOCE2502L30879=1 | G4: TR210007 | H4: OUI | I4: 45912 | J4: Préparé | K4: T508198605
A5: QRL | B5: 12 | C5: PV5 | D5: FOD | E5: FRAL TELECOM | F5: 12.TR190005-CORNUS | G5: FONDAMENTE | H5: OUI | I5: 45917 | J5: Préparé | K5: T508196045
A6: QRL | B6: 12 | C6: PV5 | D6: BE7 | E6: FRAL TELECOM | F6: 12.TR190096-BELMONT | G6: BELMONT SUR RANCE | H6: OUI | I6: 45918 | J6: Préparé | K6: T508216813
A7: QRL | B7: 12 | C7: PV5 | D7: STA | E7: FRAL TELECOM | F7: 12.TR200015-STAMANS | G7: ST AMANS DES COTS | H7: OUI | I7: 45919 | J7: Préparé | K7: T508227833
A8: QRL | B8: 12 | C8: PV5 | D8: CAV | E8: FRAL TELECOM | F8: CEOCE2502G93108=1 | H8: OUI | I8: 45924 | J8: Préparé | K8: T508228091
A9: QRL | B9: 12 | C9: PV5 | D9: BAR | E9: FRAL TELECOM | F9: CEOCE2503O13791=1 | H9: OUI | I9: 45925 | J9: Préparé | K9: T508228156
A10: QRL | B10: 12 | C10: PV5 | D10: MHH | E10: FRAL TELECOM | F10: R503642203A | H10: OUI | I10: 45926 | J10: Préparé | K10: T508228203
A11: QRL | B11: 12 | C11: PV5 | D11: FOD | E11: FRAL TELECOM | F11: 12.TR180006-LECLAPIER | G11: FONDAMENTE | H11: OUI | I11: 45931 | J11: Préparé | K11: T509084396
A12: QRL | B12: 48 | C12: PV5 | D12: GTE | E12: FRAL TELECOM | F12: ACC0050YEG1 | H12: OUI | I12: 45932 | J12: Préparé | K12: T508179899
A13: QRL | B13: 12 | C13: PV5 | D13: CBO | E13: FRAL TELECOM | F13: CEOCE2506T79802=1 | H13: OUI | I13: 45932 | J13: Préparé | K13: T509142602
A14: QRL | B14: 12 | C14: PV5 | D14: SCY | E14: FRAL TELECOM | F14: CEOCE2506V25832=1 | H14: OUI | I14: 45933 | J14: Préparé | K14: T509085631
A15: QRL | B15: 12 | F15: R507687771A | H15: OUI | I15: 45936 | J15: Préparé | K15: T509141071
A16: QRL | B16: 12 | C16: PV5 | E16: FRAL TELECOM | F16: R503644785A | I16: 45937 | J16: Préparé | K16: T509097195
A17: DPS | B17: 12 | C17: PV5 | D17: VEL | E17: FRAL TELECOM | F17: CEOCE2507H53654=1 | H17: OUI | I17: 45938 | J17: Préparé | K17: T509156405
A18: QRL | B18: 12 | C18: PV5 | D18: CN4 | E18: FRAL TELECOM | F18: R502635967A | G18: CORNUS | H18: OUI | I18: 45939 | J18: Préparé | K18: T509086008
B19: 12 | C19: PV5 | D19: CPI | E19: FRAL TELECOM | F19: CEOCE2507I41327=1 | H19: OUI | I19: 45940 | J19: Préparé | K19: T509156474
F20: R507688532A | H20: OUI | I20: 45943 | J20: Préparé | K20: T509143215
B21: 12 | C21: PV5 | D21: ENT | E21: FRAL TELECOM | F21: CEOCE2507F75413=1 | H21: OUI | I21: 45944 | J21: Préparé | K21: T509156539
A22: QRL | B22: 12 | C22: PV5 | D22: MPX | E22: FRAL TELECOM | F22: R503646300A | G22: Peux-et-Couffouleux 12360 | H22: OUI | I22: 45945 | J22: REJETE | K22: T509086131 | L22: ATT RETOUR
A23: QRL | B23: 12 | C23: PV5 | D23: AGU | E23: FRAL TELECOM | F23: 12.TR210048-RIVIERES | G23: AGUESSAC | H23: OUI | I23: 45946 | J23: Préparé | K23: T509090350
A24: QRL | B24: 12 | C24: PV5 | D24: LST | E24: FRAL TELECOM | F24: 12.TR190072-LASSOUTS | G24: LASSOUTS | H24: OUI | I24: 45947 | J24: Préparé | K24: T509090497
C25: PV5 | D25: MBZ | E25: FRAL TELECOM | F25: CEOCE2507K89152=1 | G25: MONTBAZENS | H25: OUI | I25: 45950 | J25: Préparé | K25: T509195999
A26: QRL | B26: 12 | C26: PV5 | D26: RTM | E26: FRAL TELECOM | F26: VIA01000000205321667 | H26: OUI | I26: 45950 | J26: Préparé | K26: T509226805 | L26: PRO$194335$2398$OK2800m CABLE L1092 24FO MODULO 6 FTTHtype de modification: POSE 1 PEO AVEC CHANGEMENT DE CABLEIdentifiant tronçon: Tr 200041Du PB Pt 000432 x 24 soudures au PEO Poteau n159182 x 24souduresCommentaires : Remplacer 800m de 24 fo m6 du pt 000432 aupoteau 159204 au poteau 159182 le remplacement englobe 2casseCommande : ROD501214
A27: QRL | B27: 12 | C27: PV5 | D27: ABB | E27: FRAL TELECOM | F27: R508700248A | H27: OUI | I27: 45951 | J27: Préparé | K27: T509226915 | L27: PRO$194110$1640$OK2 500m CABLE L1092 12FO MODULO 6 FTTHtype de modification: POSE 2 PEOIdentifiant tronçon: Tr 200221Du PEO Poteau n2125412 x 12 soudures au PEO Poteaun2125424 x 12 soudures
A28: QRL | B28: 12 | C28: PV5 | D28: SCU | E28: FRAL TELECOM | F28: CEOCE2508O85725=1 | G28: SALLE CURAN | H28: OUI | I28: 45951 | J28: Préparé | K28: T509226970 | L28: PRO$194485$2838$OK2 400m CABLE L1092 72FO MOD 12 FTTHtype de modification: POSE 2 PEOIdentifiant tronçon: Tr 18 0028Du PEO 21750 x 72 soudures au PEO 21736 x 72 soudures
A29: QRL | B29: 12 | C29: PV5 | D29: LRO | E29: FRAL TELECOM | F29: R506678556A | H29: OUI | I29: 45952 | J29: Préparé | K29: T509105640
A30: QRL | B30: 12 | C30: PV5 | D30: RUL | E30: FRAL TELECOM | F30: VIA01000000215839749 | H30: OUI | I30: 45952 | J30: Préparé | K30: T509227058 | L30: PRO$178237$1190$OK2 ý190m CABLE L1092 24FO MODULO 6 FTTHýtype de modification: POSE 2 PEOýIdentifiant tronçon: Tr 210144ýDu PEO Chambre 99987 x 24 soudures au PEO Poteau 2127896 xý24 souduresýCOMMANDE : ROD501027
A31: QRL | B31: 12 | C31: PV5 | D31: QUI | E31: FRAL TELECOM | F31: R412603424A | H31: OUI | I31: 45953 | J31: Préparé | K31: T509141025 | L31: Câble introuvable
A32: QRL | B32: 12 | C32: PV5 | D32: DRU | E32: FRAL TELECOM | F32: CEOCE2507H78827=1 | G32: DRUELLE | H32: OUI | I32: 45953 | J32: Préparé | K32: T509227106 | L32: PRO$191026$1912$OK2 300m CABLE L1092 36FO MOD 12 FTTHtype de modification: POSE 2 PEOIdentifiant tronon: TR 19 0007Du PEO 226271 x 36 soudures au PEO 226264 x 36 souduresCommentaires : 300m de 36FO L1092 M12 doit tre remplaceavec cration de 2 PEP, 1 sur le poteau 226271 et 1 sur lepoteau 226264. 2 poteau cass: 226269 et 226270 remplacs le 26/07/25 via GESTAR250717DRU4986251.Commande : ROD501217 | O32: PRO$191026$1912$OK2 300m CABLE L1092 36FO MOD 12 FTTHtype de modification: POSE 2 PEOIdentifiant tronon: TR 19 0007Du PEO 226271 x 36 soudures au PEO 226264 x 36 souduresCommentaires : 300m de 36FO L1092 M12 doit tre remplaceavec cration de 2 PEP, 1 sur le poteau 226271 et 1 sur lepoteau 226264. 2 poteau cass: 226269 et 226270 remplacs le 26/07/25 via GESTAR250717DRU4986251.Commande : ROD501217
A33: QRL | B33: 12 | C33: PV5 | D33: RIG | E33: FRAL TELECOM | F33: VIA01000000189767359 | H33: OUI | I33: 45954 | J33: Préparé | K33: T509114327
A34: QRL | B34: 12 | C34: PV5 | D34: SVI | E34: FRAL TELECOM | F34: CEOCE2508O31257 | H34: OUI | I34: 45954 | J34: Préparé | K34: T509227327 | L34: CEOCE2508O31257** TR200008 350M 72FO L1092 M12Du PEO 9867 x 72 soudures au PEO 9856 x 72 souduresPRO$194557$2682$OK2
A35: QRL | B35: 12 | C35: PV5 | D35: FIR | E35: FRAL TELECOM | F35: R503640957A | H35: OUI | I35: 45957 | J35: Préparé | K35: T509227496 | L35: NVORA*R503640957A* 200M 12FO L1092 M6 ýDu poteau 126740( création de boite ) au poteau 1033211(ýrécupération du pt 000603)ýplus remplacer poteau 2123499 VIA GESTAR250710FIR4978771ýCABLE DISPO A SALLES-LA-SOURCE EN SORTIE COMPTOIR. TR 20 0314
A36: QRL | B36: 12 | C36: PV5 | D36: SCH | E36: FRAL TELECOM | F36: CEOCE2507L39259=1 | H36: OUI | I36: 45957 | J36: Préparé | K36: T509227582 | L36: NVSOG**CEOCE2507L39259=1** TR190018 250M 36FO L1092 M12250m 36fom12 doit être remplacée avec creation de deux pep,1 sur le ptx 94556, 1 sur le ptx 94560.REO PRO validée avec modification d ingénierie. 250M de 36foDossier sur BO5PRO$192718$1795$OK2
A37: QRL | B37: 12 | C37: PV5 | D37: SLE | E37: FRAL TELECOM | F37: CEOCE2501T10797=1 | H37: OUI | I37: 45958 | J37: Préparé | K37: T509227628 | L37: NVORA**CEOCE2501T10797=1** 380m de L1092 24FO M6 du poteauý112466 a la chambre l2c code 00941/12270 + création 2 boitesý- 1 au poteau 112466 et l'autre dans la chambre l2c code n°ý00941/12270ýCommande de régul : ROD500828
A38: QRL | B38: 12 | C38: PV5 | D38: FOD | E38: FRAL TELECOM | F38: CEOCE2508O35486=1 | G38: FONDAMENTE | H38: OUI | I38: 45958 | J38: Préparé | K38: T509227664 | L38: NVFT**CEOCE2508O35486=1** TR180006 700M 36FO L1092 M6Du PEO Pt 000017 x 36 soudures au PEO Poteau 196194 x 36soudures700 m dz 36fo m12 a remplacer du pt 000017 au poteau 196194Sur le terrain nous n avons pas trouver le pt 000017 alorsil faudra crée la boîte pt 000017 au poteau 196207PRO$194746$2690$OK2
A39: QRL | B39: 12 | C39: PV5 | D39: EST | E39: FRAL TELECOM | F39: CEOCE2507F32934=1 | H39: OUI | I39: 45959 | J39: Préparé | K39: T509227739 | L39: PRO$189709$2882$OK2 500m CABLE L1092 72FO MOD 12 FTTHtype de modification: POSE 1 PEO AVEC CHANGEMENT DE CABLEIdentifiant tronçon: Tr200010Du PEP Pt 000008 x 72 soudures au PEO Ptx 3120203 x 72soudures
A40: QRL | B40: 48 | C40: PV5 | D40: SAM | E40: FRAL TELECOM | F40: CEOCE2503S05538=1 | H40: OUI | I40: 45960 | J40: Préparé | K40: T509114398
A41: QRL | B41: 12 | C41: PV5 | D41: VTJ | E41: FRAL TELECOM | F41: R506677623A | H41: OUI | I41: 45960 | J41: Préparé | K41: T510090046 | L41: PRO$183742$1414$OK2 DEMANDE SOGETRELý300m CABLE L1092 24FO MODULO 6 FTTH)ýType de modification: POSE 2 PEOýIdentifiant tronçon: TR 20 0288ýDu PEO 0166390 x 24 soudures au PEO 0166382 x 24 souduresýCommentaires : TR200288 L1092 24F0 M6 Câble arrachéýsuite chute d'arbre voire PJ, le dommage se situeýau FT/0166389ýCOMMANDE: ROD501049
A42: QRL | B42: 12 | C42: PV5 | D42: SC3 | E42: FRAL TELECOM | F42: R504651747A | H42: OUI | I42: 45961 | J42: Préparé | K42: T509114536
A43: QRL | B43: 12 | C43: PV5 | D43: STZ | E43: FRAL TELECOM | F43: CEOCE2507I58714=1 | H43: OUI | I43: 45961 | J43: Préparé | K43: T510114387 | L43: NVSOG**CEOCE2507I58714=1** TR190005 370M 36FO L1092 M12Du PEP Pt 000005 x 36 soudures au PEO 134596 x 36 souduresPRO$191005$1806$OK2Lié au GESTAR250721STZ4989394
A44: QRL | B44: 12 | C44: PV5 | D44: VLY | E44: FRAL TELECOM | F44: CEOCE2507H71729=1 | G44: VALADY | H44: OUI | I44: 45964 | J44: Préparé | K44: T510145679 | L44: PRO$191257$1704$OK2 550m CABLE L1092 24FO MODULO 6 FTTHtype de modification: PAS DE POSE PEOIdentifiant tronçon: TR 20 0097Du PA PT 000440 x 24 soudures au PB PT 000495 x 18 soudures
A45: QRL | B45: 12 | C45: PV5 | D45: BOZ | E45: FRAL TELECOM | F45: CEOCE2506A68287=1 | G45: BOZOULS | H45: OUI | I45: 45964 | J45: Préparé | K45: T510145841 | L45: CEOCE2506A68287=1** TR180005 450M 36FO L1092 M12Du PEP 000344 x 36 soudures au PEO Ptx 99566Reo pro validee avec modification d ingenierie, 450m de36FO. Dossier mis sur QR5.PRO$187015$1993$OK2Prestations MO : PCFO1 x 450, DCFO1 x 450, 4B430 x 1, RFA05x 72, FOP20 x 1, ISB03 x 2
A46: QRL | B46: 12 | C46: PV5 | D46: DEC | E46: FRAL TELECOM | F46: CEOCE2507C34929=1 | G46: DECAZEVILLE | H46: OUI | I46: 45965 | J46: Préparé | K46: T510145903 | L46: CEOCE2507C34929=1** TR180053 900M 36FO L1092 M6Du PA PT 000107 au PA PT 000117Reo PRO validée avec reconstruction à l identique. 900M de36fo.PRO$188191$2920$OK1Prestations MO : PCFO1 x 900, DCFO1 x 900, 4B430 x 2, RFA05x 72, ISB03 x 3
A47: QRL | B47: 12 | C47: PV5 | D47: DEC | E47: FRAL TELECOM | F47: CEOCE2507E97621=1 | G47: RIEUPEYROUX | H47: OUI | I47: 45965 | J47: Préparé | K47: T510145981 | L47: CEOCE2507E97621=1** TR180093 700M 12FO L1092 M6Du PEP Pt 000207-R1 au PEP Pt 000207-R1PRO$189715$1784$OK1Prestations MO : PCFO1 x 700, DCFO1 x 700, 4B430 x 2, RFA05x 24, ISB03 x 2
A48: QRL | B48: 48 | C48: PV5 | D48: BLE | E48: FRAL TELECOM | F48: CEOCE2507E53162=1 | H48: OUI | I48: 45966 | J48: Préparé | K48: T509114593 | L48: R200025 350M 36FO L1092 M12type de modification: POSE 1 PEO AVEC CHANGEMENT DE CABLEIdentifiant tronçon: Tr 20 0025Du PEP Pt 000276 x 36 soudures au PEO 57229 x 36 souduresPRO$196078$1759$OK2
A49: QRL | B49: 12 | C49: PV5 | D49: SEN | E49: FRAL TELECOM | F49: CEOCE2508S07994 | G49: SENERGUE | H49: OUI | I49: 45966 | J49: Préparé | K49: T510146041 | L49: CEOCE2508S07994=1** TR210015 350M 72FO L1092 M6type de modification: POSE 2 PEOIdentifiant tronçon: 12268/NGZ/TR 21 0015Du PEO Pot 38246 x 72 soudures au PEO Pot 5714725 x 72souduresPRO$196474$2630$OK2CABLE EN STOCKPrestations MO : PCFO1 x 350, DCFO1 x 350, RFA05 x 144,FOP20 x 2, ISB03 x 1Prestations Matériel : ML Cable1 x 350, MatPEO_estimate_7680x 2
A50: QRL | B50: 12 | C50: PV5 | D50: QUE | E50: FRAL TELECOM | F50: R507688837B | I50: 45967 | J50: Préparé | K50: T510146096 | L50: R507688837B** TR190015 700M 12FO L1092 M6du pb pt 000079 ( poteau 151559) au pb pt 000078 (poteau151541)PRO$189178$1742$OK2Prestations MO : PCFO1 x 700, DCFO1 x 700, 4B429 x 2, RFA05x 24, ISB03 x 1
A51: QRL | B51: 12 | C51: PV5 | D51: FOU | E51: FRAL TELECOM | F51: R507689597A | I51: 45967 | J51: Préparé | K51: T510173050 | L51: PRO$189139$1196$OK1350m CABLE L1092 12FO MODULO 6 FTTHIdentifiant tronçon: TR 20 0149Du PA PT 000225 x 12 soudures au PB PT 000285 x 6 souduresPB en cascade x 2Fibres client raccordées x 12Fibres en dérivation x 6Prestations MO : PCFO1 x 350, DCFO1 x 350, 4B430 x 1, 4B429x 3, RFA05 x 30, ISB03 x 2
A52: QRL | B52: 12 | C52: PV5 | D52: SAF | E52: FRAL TELECOM | F52: CEOCE2508U51547 | G52: SAINT AFFRIQUE | H52: OUI | I52: 45988 | J52: Préparé | K52: T510173268 | L52: CEOCE2508S07994=1** TR210015 350M 72FO L1092 M6type de modification: POSE 2 PEOIdentifiant tronçon: 12268/NGZ/TR 21 0015Du PEO Pot 38246 x 72 soudures au PEO Pot 5714725 x 72souduresPRO$196474$2630$OK2CABLE EN STOCKPrestations MO : PCFO1 x 350, DCFO1 x 350, RFA05 x 144,FOP20 x 2, ISB03 x 1Prestations Matériel : ML Cable1 x 350, MatPEO_estimate_7680x 2
A53: QRL | B53: 12 | C53: PV5 | D53: FLA | E53: FRAL TELECOM | F53: R504653343A | H53: OUI | I53: 45968 | J53: Préparé | K53: T509114643 | L53: *R508707887A** TR190021 350M 24FO L1092 M6type de modification: POSE 2 PEOIdentifiant tronçon: Tr 19 0021Du PEO 196210 x 24 soudures au PEO 196201 x 24 souduresPRO$196828$1528$OK2CABLE EN STOCKPrestations MO : PCFO1 x 350, DCFO1 x 350, RFA05 x 48, FOP10x 2, ISB03 x 1Prestations Matériel : ML Cable1 x 350, MatPEO_estimate_1966x 2
A54: QRL | B54: 12 | C54: PV5 | D54: OTB | E54: FRAL TELECOM | F54: R508708352A | G54: SAINT PARTHEM | H54: OUI | I54: 45968 | J54: Préparé | K54: T510173477 | L54: R508708352A** TR210046 700M 24FO L1092 M6type de modification: POSE 1 PEO AVEC CHANGEMENT DE CABLEIdentifiant tronçon: TR 21 0046Du PEO PT 355 x 24 soudures au PEO Poteau N72760 x 24souduresCommentaires : Tirage dans un chemin/champ 2 poteaux àremplacer Lié aux GESTAR250828OTB5029308 GESTAR2508288AA5029297PRO$197746$2234$OK2CABLE EN STOCKCommande de régul : ROD501291
A55: QRL | B55: 12 | C55: PV5 | D55: FOU | E55: FRAL TELECOM | F55: R503639617A | G55: LA FOUILLADE | H55: OUI | I55: 45971 | J55: Préparé | K55: T510173602
A56: QRL | B56: 12 | C56: PV5 | D56: ZOB | E56: FRAL TELECOM | F56: VIA01000000190873419 | G56: GALGAN | H56: OUI | I56: 45971 | J56: Préparé | K56: T510173707
A57: QRL | B57: 12 | C57: PV5 | D57: QUI | E57: FRAL TELECOM | F57: R503637236A | H57: OUI | I57: 45973 | J57: Préparé | K57: T509114728
A58: QRL | B58: 12 | C58: PV5 | D58: MTI | E58: FRAL TELECOM | F58: CEOCE2507H50386=1 | G58: SAVIGNAC | H58: OUI | I58: 45973 | J58: Préparé | K58: T510190909
A59: QRL | B59: 12 | C59: PV5 | D59: TSB | E59: FRAL TELECOM | F59: R509712901A | G59: BELCASTEL | H59: OUI | I59: 45974 | J59: Préparé | K59: T510191109
A60: QRL | B60: 12 | C60: PV5 | D60: SVP | E60: FRAL TELECOM | F60: R509713640A | G60: LA CAPELLE-BLEYS | H60: OUI | I60: 45974 | J60: Préparé | K60: T510218413
A61: QRL | B61: 12 | C61: PV5 | D61: SEN | E61: FRAL TELECOM | F61: CEOCE2505K79442=1 | H61: OUI | I61: 45975 | J61: Préparé | K61: T509114778
A62: QRL | B62: 12 | C62: PV5 | D62: FOD | E62: FRAL TELECOM | F62: 12.TR180006-LECLAPIER | G62: FONDAMENTE | H62: OUI | I62: 45974 | J62: Préparé | K62: T510218460
A63: QRL | B63: 12 | C63: PV5 | D63: LAG | E63: FRAL TELECOM | F63: ACCS508022458 | G63: LAGUIOLE | H63: OUI | I63: 45975 | J63: Préparé | K63: T510218483
A64: QRL | B64: 12 | C64: PV5 | D64: STZ | E64: FRAL TELECOM | F64: ACCS508022071 | G64: SAINT GENIEZ D'OLT | H64: OUI | I64: 45978 | J64: Préparé | K64: T510218531
A65: QRL | B65: 12 | C65: PV5 | D65: SZV | E65: FRAL TELECOM | F65: R508709510A | H65: OUI | I65: 45978 | J65: Préparé | K65: T510219785
A66: QRL | B66: 12 | C66: PV5 | D66: FNC | E66: FRAL TELECOM | F66: R509711901A | G66: FLAGNAC | H66: OUI | I66: 45979 | J66: Préparé | K66: T510219843
A67: QRL | B67: 12 | C67: PV5 | D67: FOU | E67: FRAL TELECOM | F67: R508705427A | G67: LA FOUILLADE | H67: OUI | I67: 45979 | J67: Préparé | K67: T510219813
A68: QRL | B68: 12 | C68: PV5 | D68: STZ | E68: FRAL TELECOM | F68: ACCS509040958 | G68: CAMPAGNAC | H68: OUI | I68: 45980 | J68: Préparé | K68: T510219880
A69: QRL | B69: 12 | C69: PV5 | D69: BOZ | E69: FRAL TELECOM | F69: CEOCE2509C36027=1 | G69: BOZOULS | H69: OUI | I69: 45980 | J69: Préparé | K69: T510219910
A70: QRL | B70: 12 | C70: PV5 | D70: VRO | E70: FRAL TELECOM | F70: CEOCE2506Q76119=1 | H70: OUI | I70: 45981 | J70: Préparé | K70: T509114818
A71: QRL | B71: 12 | C71: PV5 | D71: DEC | E71: FRAL TELECOM | F71: CEOCE2505L92059=1 | G71: DECAZEVILLE | H71: OUI | I71: 45981 | J71: Préparé | K71: T510219933
A72: QRL | B72: 48 | C72: PV5 | D72: 7JM | E72: FRAL TELECOM | F72: R509714683A | G72: GABRIAS | H72: OUI | I72: 45981 | J72: Préparé | K72: T510219990
A73: QRL | B73: 12 | C73: PV5 | D73: STA | E73: FRAL TELECOM | F73: CEOCE2508S29908=1 | H73: OUI | I73: 45982 | J73: Préparé | K73: T510220079
A74: QRL | B74: 12 | C74: PV5 | D74: MBZ | E74: FRAL TELECOM | F74: CEOCE2508T24333 | G74: MONTBAZENS | H74: OUI | I74: 45985 | J74: Préparé | K74: T510220283
A75: QRL | B75: 12 | C75: PV5 | D75: LCL | E75: FRAL TELECOM | F75: R508707887A | G75: LE CLAPIER | H75: OUI | I75: 45985 | J75: Préparé | K75: T510220318
A76: QRL | B76: 12 | C76: PV5 | D76: RYX | E76: FRAL TELECOM | F76: R508704454A | G76: RIEUPEYROUX | H76: OUI | I76: 45989 | J76: Préparé | K76: T510220578
A77: QRL | B77: 12 | C77: PV5 | D77: 8BE | E77: FRAL TELECOM | F77: 12.TR190339-GZD | G77: SAINT GENIEZ D'OLT | H77: OUI | I77: 45986 | J77: Préparé | K77: T510220369
A78: QRL | B78: 12 | C78: PV5 | D78: LAG | E78: FRAL TELECOM | F78: CEOCE2509F21865 | G78: LAGUIOL | H78: OUI | I78: 45986 | J78: Préparé | K78: T510220405
A79: QRL | B79: 12 | C79: PV5 | D79: LAI | E79: FRAL TELECOM | F79: CEOCE2510L44195=1 | G79: LAISSAC | H79: OUI | I79: 45987 | J79: Préparé | K79: T510220498
A80: QRL | B80: 12 | C80: PV5 | D80: RIG | E80: FRAL TELECOM | F80: CEOCE2507K28399=1 | G80: RIGNAC | H80: OUI | I80: 45988 | J80: Préparé | K80: T510220519
A81: QRL | B81: 12 | C81: PV5 | D81: VVE | E81: FRAL TELECOM | F81: CEOCE2510O75854=1 | G81: VILENEUVE | H81: OUI | I81: 45989 | J81: Préparé | K81: T510220619
A82: QRL | B82: 12 | C82: PV5 | D82: LCB | E82: FRAL TELECOM | F82: CEOCE2510L79469=1 | G82: LACROIX-BARREZ | H82: OUI | I82: 45992 | J82: Préparé | K82: T510220642
A83: QRL | B83: 12 | C83: PV5 | D83: VIL | E83: FRAL TELECOM | F83: VIA01000000221574224 | G83: LE BAS SEGALA | H83: OUI | I83: 45992 | J83: Préparé | K83: T510220683
A84: QRL | B84: 12 | C84: PV5 | D84: PSA | E84: FRAL TELECOM | F84: CEOCE2510Q93235=1 | G84: PONT DE SALARS | H84: OUI | I84: 45993 | J84: Préparé | K84: T511109402
A85: QRL | B85: 30 | C85: PV5 | D85: CAV | E85: BCL TELECOM | F85: CEOCE2510T15932 | G85: CLARENSAC | H85: OUI | I85: 45971 | J85: Préparé | K85: T511114576
... A90: QRL | B90: 12 | C90: PV5 | D90: svi | E90: FRAL TELECOM | F90: R510735230A | G90: SAINT VICTOR ET MELVIEUX | H90: OUI | I90: 46000 | J90: Préparé | K90: T511153940
A91: QRL | B91: 12 | C91: PV5 | D91: BRO | E91: FRAL TELECOM | F91: CEOCE2508W26161=1 | H91: OUI | I91: 46000 | J91: Préparé | K91: T511153965
A92: QRL | B92: 48 | C92: PV5 | D92: GTE | E92: FRAL TELECOM | F92: CEOCE2510V07149=1 | G92: PIERRE DE NOGARET | H92: OUI | I92: 46001 | J92: Préparé | K92: T511153991
A93: QRL | B93: 12 | C93: PV5 | D93: SCH | E93: FRAL TELECOM | F93: CEOCE2507G02205=1 | G93: SAINT COME D'OLT | H93: OUI | I93: 46001 | J93: Préparé | K93: T511154024
A94: QRL | B94: 12 | C94: PV5 | D94: FOU | E94: FRAL TELECOM | F94: R507689597A | H94: OUI | I94: 46002 | J94: Préparé | K94: T511154052
A95: QRL | B95: 12 | C95: PV5 | D95: FAY | E95: FRAL TELECOM | F95: CEOCE2510V52173=1 | G95: MONTAGNOL | H95: OUI | I95: 46006 | J95: Préparé | K95: T511154078
A96: QRL | B96: 12 | C96: PV5 | D96: STZ | E96: FRAL TELECOM | F96: CEOCE2510V24525=1 | G96: SAINT GENIEZ D'OLT | H96: OUI | I96: 46006 | J96: Préparé | K96: T511154116
A97: QRL | B97: 12 | C97: PV6 | D97: BOU | E97: FRAL TELECOM | F97: F510735987A | G97: SAINT AFFRIQUE | H97: OUI | I97: 46007 | J97: Préparé | K97: T511154127
A98: QRL | B98: 12 | C98: PV5 | D98: AGR | E98: FRAL TELECOM | F98: CEOCE2510S90976 | G98: SAINT PARTHEM | H98: OUI | I98: 46007 | J98: Préparé | K98: T511154142
A99: QRL | B99: 12 | C99: PV5 | D99: AGR | E99: FRAL TELECOM | F99: P-G-FI30189007P-1 | G99: NIMES | H99: OUI | I99: 46002 | J99: Préparé | K99: T511173373
A100: QRL | B100: 12 | C100: PV5 | D100: FOU | E100: FRAL TELECOM | F100: R508705427A | G100: LA FOUILLADE | H100: OUI | I100: 46008 | J100: Préparé | K100: T511185071
A101: QRL | B101: 12 | C101: PV5 | D101: BOZ | E101: FRAL TELECOM | F101: R511740541A | G101: ESTAING | H101: OUI | I101: 46008 | J101: Préparé | K101: T511185139
A102: QRL | B102: 30 | F102: 466058389 | G102: NIMES | H102: OUI | I102: 45992 | J102: Préparé | K102: T511210284
A103: QRL | B103: 30 | C103: PV5 | D103: SER | E103: KB TELECOM | F103: CEOCE2508O98877 | G103: VALRAS PLAGE | H103: OUI | I103: 46007 | J103: Préparé | K103: T512096297
A104: QRL | B104: 12 | C104: PV5 | D104: PSA | E104: FRAL TELECOM | F104: CEOCE2510Q93235=1 | G104: PONT DE SALARS | H104: OUI | I104: 46027 | J104: Préparé | K104: T512196545
...

Sheet SPI Bretagne
B1: =COUNTA(B3:B844) -> 158
A2: ETAT | B2: COG | C2: INSEE | D2: Ville | E2: ADRESSE | F2: Commentaire
A3: Dossier Envoyé | B3: IMI-VS-35238/JGJH-1 | C3: 35238 | D3: RENNES | E3: AVENUE JEAN JANVIER | G3: Dossier Payé
A4: Dossier Envoyé | B4: IMI-VS-35238/JQPB-1 | C4: 35238 | D4: RENNES | E4: PLACE DE SERBIE | G4: Dossier Envoyé
A5: Dossier Envoyé | B5: IMI-VS-35238/JS1G-1 | C5: 35238 | D5: RENNES | E5: ALLEE DE LA GARAYE | G5: Dossier Bloqué
A6: Dossier Envoyé | B6: IMI-VS-35238/JSDA-1 | C6: 35238 | D6: RENNES | E6: SQUARE YVES MONTAND | G6: Dossier Affecté
A7: Dossier Envoyé | B7: IMI-VS-35238/JUKE-1 | C7: 35238 | D7: RENNES | E7: SQUARE DU ROI ARTHUR | G7: Dosseir en Retour
A8: Dossier Envoyé | B8: IMI-VS-35238/JW4I-1 | C8: 35238 | D8: RENNES | E8: PLACE MARECHAL JUIN | G8: Etude Terminé
A9: Dossier Envoyé | B9: IMI-VS-35238/JMYV-1 | C9: 35238 | D9: RENNES | E9: RUE LOUIS POSTEL
A10: Dossier Envoyé | B10: IMI-VS-35238/JU6I-1 | C10: 35238 | D10: RENNES | E10: AVENUE GROS MALHON
A11: Dossier Envoyé | B11: IMI-VS-35238/JEWQ-1 | C11: 35238 | D11: RENNES | E11: QUAI DE LA PREVALAYE
A12: Dossier Envoyé | B12: IMI-VS-35238/JF3Y-1 | C12: 35238 | D12: RENNES | E12: RUE DES TRENTE
A13: Dossier Envoyé | B13: IMI-VS-35238/JFE4-1 | C13: 35238 | D13: RENNES | E13: RUE LEGRAVEREND
A14: Dossier Envoyé | B14: IMI-VS-35238/JMR9-1 | C14: 35238 | D14: RENNES | E14: RUE DE LA CRECHE
A15: Dossier Envoyé | B15: IMI-VS-35238/JUEJ-1 | C15: 35238 | D15: RENNES | E15: RUE DE LEON
A16: Dossier Envoyé | B16: IMI-VS-35238/JUUS-1 | C16: 35238 | D16: RENNES | E16: PLACE DU MONTENEGRO
A17: Dossier Envoyé | B17: IMI-VS-35238/JW0C-2 | C17: 35238 | D17: RENNES | E17: RUE FRANCOIS LANNO
A18: Dossier Envoyé | B18: IMI-VS-35238/JX0J-1 | C18: 35238 | D18: RENNES | E18: BOULEVARD JEANNE D ARC
A19: Dossier Envoyé | B19: IMI-VS-35238/JX98-1 | C19: 35238 | D19: RENNES | E19: MAIL FRANCOIS MITTERRAND
A20: Dossier Envoyé | B20: IMI-VS-35238/JWUD-1 | C20: 35238 | D20: RENNES | E20: RUE EDOUARD JORDAN
... A22: Dossier Envoyé | B22: IMI-VS-35238/JGWC-1 | C22: 35238 | D22: RENNES | E22: RUE JOSEPH SAUVEUR
A23: Dossier Bloqué | C23: 35238 | D23: RENNES | E23: AVENUE JORGE SEMPRUN | F23: Dossier retiré par Sogtrel
A24: Dossier Envoyé | B24: IMI-VS-35238/JQUC-3 | C24: 35238 | D24: RENNES | E24: BOULEVARD DE BULGARIE
A25: Dossier Envoyé | B25: IMI-VS-35238/JR18-1 | C25: 35238 | D25: RENNES | E25: RUE SAINT MALO
A26: Dossier Envoyé | B26: IMI-VS-35238/JTVL-1 | C26: 35238 | D26: RENNES | E26: RUE DE BREST
A27: Dossier Envoyé | B27: IMI-VS-35238/JU9S-1 | C27: 35238 | D27: RENNES | E27: RUE ARTHUR FONTAINE
A28: Dossier Envoyé | B28: IMI-VS-35238/JVAW-1 | C28: 35238 | D28: RENNES | E28: RUE DE LA SANTE
A29: Dossier Envoyé | B29: IMI-VS-35238/01SP-1 | C29: 35238 | D29: RENNES | E29: RUE DE NORMANDIE
A30: Dossier Envoyé | B30: IMI-VS-35238/JGPR-1 | C30: 35238 | D30: RENNES | E30: BOULEVARD DE SEVIGNE
A31: Dossier Envoyé | B31: IMI-VS-35238/00P2-1 | C31: 35238 | D31: RENNES | E31: ALLEE JEAN DE LA VARENDE
A32: Dossier Envoyé | B32: IMI-VS-35238/JKVR-1 | C32: 35238 | D32: RENNES | E32: RUE ETIENNE PINAULT
A33: Dossier Envoyé | B33: IMI-VS-35238/JTFQ-1 | C33: 35238 | D33: RENNES | E33: RUE DE BREST
A34: Dossier Envoyé | B34: IMI-VS-35238/00YY-1 | C34: 35238 | D34: RENNES | E34: RUE D ANTRAIN
A35: Dossier Envoyé | B35: IMI-VS-35238/JIP8-1 | C35: 35238 | D35: RENNES | E35: RUE LE GUEN DE KERANGAL
... A123: Dossier Envoyé | B123: IMI-VS-29232/0995-2 | C123: 29232 | D123: QUIMPER | E123: RUE ETIENNE GOURMELEN
A124: Dossier Envoyé | B124: IMI-VE-35238/JF7A-1 | C124: 35238 | D124: RENNES | E124: 13, R . Monnaie, 35000, RENNES
A125: Dossier Envoyé | B125: DEP-AN-29232/028Q-1
A126: Dossier Envoyé | B126: DEP-AN-35144/00JE-1 | C126: 35144 | D126: Langan | E126: 14 Impasse Bernard Moitessier 35850 Langan
A127: Dossier Bloqué | B127: DEP-AN-29232/0JB3-1 | E127: 4 Rue du Palais 29000 Quimper | F127: MAIL POUR RDV
A128: Etude Terminé | B128: DEP-AN-29232/03U7-1 | E128: 9 Rue de l'Île d'Houât - Quimper
A129: Dossier Bloqué | B129: DEP-AN-29170/01R8-1 | F129: ATT retour SOGETREL
A130: Dossier Envoyé | B130: DEP-AN-29232/0JB5-1
A131: Dossier Envoyé | B131: DEP-SN-29134-00A2-2
A132: Dossier Envoyé | B132: DEP-SN-29066/007H-1
A133: Dossier Envoyé | B133: DEP-SN-29216/019Z-1
A134: Dossier Envoyé | B134: DEP-AN-35144/00JE-1
A135: Dossier Envoyé | B135: DEP-SN-35210/00U6-1
A136: Dossier Envoyé | B136: DEP-SN-35334/00WD-1
A137: Etude Terminé | B137: DEP-SN-35353/004G-1 | F137: Att Validation Devis
A138: Dossier Envoyé | B138: DEP-SN-35051/04JF-1
A139: Dossier Envoyé | B139: DEP-SN-35238/JN1X-1
A140: Dossier Envoyé | B140: DEP-SN-35120/004P-1
A141: Dossier Envoyé | B141: DEP-SN-35238/00G3-1
A142: Dossier Envoyé | B142: DEP-SN-35275/002I-1
A143: Dossier Envoyé | B143: DEP-AN-56260/0CVV-1
A144: Dossier Envoyé | B144: DEP-AN-56137/01CA-1
A145: Dossier Envoyé | B145: DEP-AN-56121/0BKO-1
A146: Dossier Envoyé | B146: DEP-AN-56158/00NZ-1
A147: Dossier Envoyé | B147: DEP-AN-56121/04UR-1
A148: Dossier Envoyé | B148: DEP-AN-56101/03HN-1
A149: Dossier Envoyé | B149: DEP-SN-56098-03F0-1
... A155: Dossier Envoyé | B155: DEP-SN-56260/0CX9-1
A156: Etude Terminé | B156: DEP-SN-56137/01BR-1 | F156: ATT retour Enedis
A157: Dossier Envoyé | B157: DEP-SN-56098/0667-1
A158: Dossier Envoyé | B158: DEP-SN-56063/00DO-1
A159: Dossier Envoyé | B159: DEP-AN-56164/00X3-1
A160: Dossier Envoyé | B160: DEP-SN-56121/02NR-1
A161: Dossier Envoyé | B161: DEP-AN-56158/018L-1

Sheet DEMANDE DT
A1: INFORMATIONS GENERAL | F1: CONCESSIONAIRE
A2: POI | B2: COMMUNE | C2: ADRESSE | D2: COORDONEE GPS | E2: N°REF DT | F2: ENEDIS | G2: GRDF | H2: EAU | I2: MAIRIE | J2: SYNDICAT ENERGIE | K2: DEPARTEMENT | L2: INFRA
A3: MEN400681 | B3: Saint-Laurent-de-Veyrès | C3: Village | D3: 44.77531717412041, 3.133627254156568 | E3: 2024121100559TEU | F3: OK | G3: N/C | H3: N/C | I3: N/C | J3: N/C | K3: N/C | L3: N/C
A4: MEN400685 | B4: CHATEAUNEUF DE RANDON | C4: 3 ROUTE DU PONT RODIER | D4: 44.63415889866625, 3.6752155378601734 | E4: 2024121000466T0D | F4: OK | G4: N/C | K4: OK
A5: ROD401860 | B5: SAINT SERNIN SUR RANCE | C5: 22 CHEMIN DE LAVAL | D5: 43.88032959324717, 2.60623579330839 | E5: 2024120500225TFZ | F5: OK | G5: N/C | H5: OK | I5: N/C | J5: N/C | K5: N/C | L5: N/C
A6: ROD401858 | B6: LA LOUBIERE | C6: IMP DU COMBAL | D6: 44.40716 ; 2.63976 | E6: 2024121600193TDF | F6: OK | G6: OK | H6: OK | I6: OK | J6: OK | K6: N/C | L6: OK (altitude)
A7: ROD402081 | B7: SAINT SERNIN SUR RANCE | C7: 22 CHEMIN DE LAVAL | D7: 43.880314057028876, 2.6062056722738514 | E7: 2024121600166TIA | F7: OK | G7: N/C | H7: OK | I7: N/C | J7: N/C | K7: N/C | L7: N/C
A8: ROD402078 | B8: ROQUEFORT SUR SOULZON | C8: L AIRE VIEILLE | D8: 43.97273 ; 2.95984 | E8: 2024121600531TPV | F8: OK | G8: OK | H8: N/C | I8: OK | J8: N/C | K8: N/C | L8: N/C
A9: MEN400754 | B9: LA MALENE | C9: ROUTE DE CAUQUENAS | D9: 44.32049 ; 3.30010 | E9: 2024121600807TIY | F9: OK | G9: N/C | H9: N/C | I9: N/C | J9: N/C | K9: N/C | L9: N/C
A10: ROD402113 | B10: ALRANCE | C10: 2 CITE EDF | D10: 44.12151 ; 2.68751 | E10: 2024121700826TQX | F10: OK | G10: N/C | H10: OK | I10: N/C | J10: N/C | K10: N/C | L10: OK
A11: ROD400178 | B11: GABRIAC | C11: LD LE JALOUS | D11: 44.45969820887255, 2.8107440949066063 | E11: 2024121801016TIA | F11: OK | G11: N/C | H11: OK | I11: N/C | J11: N/C | K11: N/C | L11: N/C
A12: ROD401914 | B12: ESPALION | C12: 2 RTE DU CHATEAU | D12: 44.51633 ; 2.74983 | E12: 2024121900250TTP | F12: OK | G12: N/C | H12: OK | I12: N/C | J12: OK | K12: OK | L12: OK (THD)
A13: ROD401723 | B13: SALLES CURAN | C13: MAS DE COURNET | D13: 44,19259; 2,79324 | E13: 2024122000221T6G | F13: OK | G13: N/C | H13: OK | I13: N/C | J13: N/C | K13: N/C | L13: OK (THD)
A14: ROD402136 | B14: VEZINS DE LEVEZOU | C14: LE ROUCOUS | D14: 44,23546.2,91437 | E14: 2024122000270TZN | F14: OK | G14: N/C | H14: OK | I14: N/C | J14: N/C | K14: N/C | L14: N/C
A15: ROD402051 | B15: MAS DE MOULIS | C15: LA COUVERTOIRADE | D15: 43.95992275551356, 3.27257346943218 | E15: 2024122001338TFH | F15: OK | G15: N/C | H15: OK | I15: OK | J15: N/C | K15: N/C | L15: OK (THD)
A16: MEN400633 | B16: LA LUNE | C16: Saint-Martin-de-Boubaux | D16: 44.17775166725317, 3.9615716686258167 | E16: 2024122200116T3M | F16: OK | G16: N/C | H16: N/C | I16: N/C | J16: N/C | K16: N/C | L16: N/C
... A20: MEN400766 | B20: PEYRE EN AUBRAC | C20: 980 AV DE LA MERIDIENNE | D20: 44.740901421872316, 3.290475985469584 | E20: 2025010300231TOI | F20: OK | G20: N/C | H20: N/C | I20: N/C | J20: N/C | K20: N/C | L20: N/C
A21: ROD402177 | B21: 12450 FLAVIN | C21: 26 AVENUE DU SEGALA | D21: 44.28607 ; 2.60205 | E21: 2025010300267TFT | F21: OK | G21: OK | I21: N/C | J21: OK | K21: N/C | L21: N/C
A22: ROD402198 | B22: SEVERAC D AVEYRON | C22: 28 AV RESISTANTS | D22: 44,318589 ; 3,073771 | E22: 2025011301241TXW | F22: N/C | G22: N/C | I22: N/C | J22: OK | K22: N/C | L22: N/C
A23: ROD402199 | B23: NAUCELLE | C23: LA BALAGE | D23: 44,18606 ; 2,33262 | E23: 2025010700154TQP | F23: OK | G23: OK | H23: OK | I23: OK | J23: OK | K23: OK | L23: OK
A24: ROD402208 | B24: ESTAING | C24: 3801 RTE D ANNAT | D24: 44,572511;2,686937 | E24: 2025010700294THP | F24: OK | G24: N/C | H24: OK | I24: N/C | J24: OK | K24: N/C | L24: N/C
A25: ROD500001 | B25: BOZOULS | C25: 14 IMP DU CAYROU | D25: 44.44472 ; 2.72745 | E25: 2025010701494T1L | F25: OK | G25: N/C | H25: OK | I25: N/C | K25: OK | L25: N/C
A26: MEN500002 | B26: ISPAGNAC | C26: CH DE LA LECHE | D26: 44.37293406137982, 3.5326079731380604 | E26: 2025011001487TXO | F26: OK | G26: N/C | H26: OK | I26: N/C | J26: N/C | K26: OK | L26: N/C
A27: ROD402180 | B27: AGUESSAC | C27: CHE DES PRADES | D27: 44.153361508820936, 3.0988152025228377 | E27: 2025011400196TTM | F27: OK | G27: N/C | H27: OK | I27: N/C | J27: N/C | K27: OK | L27: OK
A28: ROD401781 | B28: Flavin | C28: 1 RUE DE LA SOUQUETTE | D28: 44.281944, 2.607778 | E28: 2025011501235TW0 | F28: OK | G28: OK | L28: OK
A29: MEN500001 | B29: BADAROUX | C29: 17 CH DES ROUVIERES | D29: 44.537251169193276, 3.5418958404348873 | E29: 2025011700402TNS | F29: OK | G29: N/C | I29: N/C | J29: N/C | K29: N/C
A30: ROD500061 | B30: NAUCELLE | C30: AV RODEZ | D30: 44.20027657822796, 2.3450987184957257 | E30: 2025013101281TRY | F30: OK | G30: N/C | H30: OK | I30: N/C | J30: OK | K30: N/C | L30: N/C
A31: ROD401579 | B31: SALLES CURAN | C31: 19 RTE VERNHES | D31: 44.20074 ; 2.77632 | E31: 2025012101321TNI | F31: ok | H31: ok
A32: ROD400348 | B32: SAINT HIPPOLYTE | C32: LD LA CAPELLE | D32: 44.73830 ; 2.59832 | E32: 2025012101562TIZ | F32: ok
A33: ROD401786 | B33: SALLES CURAN | C33: LE PRE VIBAL | D33: 44.18815 ; 2.78964 | E33: 2025012200594TKE | F33: OK | G33: N/C | H33: OK | I33: N/C | J33: N/C | K33: N/C | L33: N/C
A34: ROD401863 | B34: VERSOLS ET LAPEYRE | C34: 69 RUE DU CHAMP DE RAMONDE | D34: 43.895945 2.933176 | E34: 2025012300691TZH | F34: OK | G34: N/C | H34: N/C | I34: N/C | J34: N/C | K34: N/C
A35: ROD402209 | B35: LIOUJAS LA LOUBIERE | C35: 4B IMP DU COMBAL | D35: 44.40681224432121, 2.6397060339356972 | E35: 2025012700199T5O | F35: OK | G35: OK | H35: OK | I35: OK | J35: ok | L35: OK
A36: ROD401103 | B36: VERRIERES | C36: ROUASSAS | D36: 44,195222; 3,086316 | E36: 2025012700916TBQ | F36: OK | G36: N/C | H36: OK | I36: N/C | J36: N/C | K36: N/C | L36: N/C
A37: ROD302439/ROD402055 | B37: Gabriac | C37: Fraysse | D37: 44.4896170357722, 2.7920292945935046 | E37: MEN400685 | F37: OK | G37: N/C | I37: OK | J37: N/C | L37: N/C
A38: ROD401316 | B38: SAINT ROME DE CERNON | C38: REVAYROL | D38: 44.01036459671738, 2.9774961739895924 | E38: 2025013000386TY7 | F38: OK | G38: N/C | H38: N/C | J38: N/C | K38: N/C
A39: ROD400125 | B39: BOZOULS | C39: 133 RTE D ESPALION | D39: 44.47099 ; 2.72976 | E39: 2025013100172TPK | F39: OK | G39: N/C | H39: OK | I39: OK | L39: OK
A40: ROD402099 | B40: CASSAGNES BEGONHES | C40: LE BOUSQUET DE CEOR | D40: 44.16160446591406, 2.5032503886982926 | E40: 2025020300130TLV | F40: OK | G40: N/C | H40: OK | I40: N/C | J40: N/C | K40: N/C | L40: N/C
A41: MEN500045 | B41: LD CASSAGNES | C41: SAINT PIERRE DES TRIPIERS | D41: 44.201105253794296, 3.2733391215454906 | E41: 2025020300575TNZ | F41: OK | G41: N/C | J41: N/C | K41: OK | L41: N/C
A42: ROD500052 | B42: MILLAU | C42: 11 RUE DE FONTENAY | D42: 44.11684860959319, 3.0850478230789156 | E42: 2025020400258TAV | F42: OK | G42: OK | H42: OK | K42: N/C | L42: N/C
A43: ROD401960 | B43: LASSOUTS | C43: 87 ROUTE DE COUPIAC | D43: 44.48822 ; 2.85486 | E43: 2025020500428TZZ | F43: OK | G43: N/C | H43: N/C | I43: N/C | J43: N/C | K43: OK | L43: N/C
A44: MEN400731 | B44: Saint-Pierre-des-Tripiers | C44: Le Truel | D44: 44.20289987738929, 3.2663001409130312 | E44: 2025020701630TIK | F44: OK | G44: N/C | H44: N/C | I44: N/C | J44: N/C | K44: OK | L44: N/C
A45: MEN400751 | B45: CANOURGUE | C45: LE BOULAY | D45: 44.43559 ; 3.24237 | E45: 2025021101966TTK | F45: OK | G45: OK | H45: N/C | J45: N/C | K45: N/C
A46: ROD500049 | B46: LEDERGUES | C46: 808 RTE DE LA MASSEYRIE | D46: 44.07070, 2.42297 | E46: 2025021101279T6L | F46: OK | G46: N/C | H46: OK | I46: N/C | J46: N/C | K46: N/C
A47: ROD401680 | B47: BRANDONNET | C47: PASSERAT | D47: 44.397345509002335, 2.1432397338962446 | E47: 2025021300501TPT | F47: OK | L47: OK (THD)
A48: ROD401868 | B48: SAINT AMANS DES COTS | C48: LD TOULUCH | D48: 44.66806799446049, 2.7050379507328586 | E48: 2025021300736TDB | F48: OK | H48: OK
A49: ROD401940 | B49: BERTHOLENE | C49: COUDERC BANC | D49: 44.429622270936974, 2.7832271251816514 | E49: 2025021301025TLQ | F49: OK | H49: OK | I49: OK
A50: ROD400033 | B50: 27 NIGRESSERRE | C50: THERONDELS | D50: 44.87941659607553, 2.69678102967247 | E50: 2025021301244TAW | F50: OK | H50: OK | L50: OK
A51: ROD402163 | B51: 1 LES INFRUTS | C51: LA COUVERTOIRADE | D51: 43.90481185892479, 3.2639689803759815 | E51: 2025021400889TG4 | F51: OK | H51: OK | I51: OK | L51: OK
A52: ROD500018 | B52: LA PALISSE | C52: BROUSSE LE CHATEAU | D52: 44.00236 ; 2.66768 | E52: 2025021401327TYB | F52: OK | G52: N/C | H52: OK | I52: N/C | J52: N/C | K52: N/C | L52: N/C
A53: ROD401725 | B53: CAMPUAC | C53: FERRIEZ | D53: 44.54491706113055, 2.6089295080535826 | E53: 2025021401329T3K | F53: OK | G53: N/C | H53: OK | I53: OK | J53: N/C | K53: N/C | L53: N/C
A54: MEN400695 | B54: LES BONDONS | C54: LD LE CROUZET | D54: 44.38422 ; 3.62222 | E54: 2025021700213TXS | F54: OK | G54: N/C | H54: N/C | I54: N/C | J54: N/C | K54: N/C
A55: ROD402173 | B55: SYLVANES | C55: AVENUE LE SARROS | D55: 43.82773407333799, 2.9449696699251 | E55: 2025021700343T5A | F55: OK | G55: N/C | H55: N/C | I55: N/C | J55: N/C | K55: N/C
A56: MEN400647 | B56: SAINT GERMAIN DE CALBERTE | C56: LD REVOLTE | D56: 44.1992874529561, 3.807847060038247 | E56: 2025021700846TRE | F56: OK | G56: N/C | H56: N/C | I56: N/C | J56: N/C | K56: N/C
A57: ROD500226 | B57: MONTEZIC | C57: 21 RUE PRINCIPALE | D57: 44.70830 ; 2.63808 | E57: 2025021701184TVT | F57: OK | G57: N/C | H57: OK | I57: N/C | J57: N/C | K57: N/C
A58: ROD500117 | B58: MONTPEYROUX | C58: RTE DE SOUBEYROLLES | D58: 44.65595, 2.758675 | E58: 2025021701565TDY | F58: OK | G58: N/C | H58: N/C | I58: N/C | J58: N/C | K58: N/C
A59: ROD402156 | B59: RTE BESSIERES | C59: ARGENCE EN AUBRAC | D59: 44.80740323246903, 2.7900457129062963 | E59: 2025021701772TVL | G59: N/C | H59: OK | I59: N/C | J59: N/C | K59: N/C
A60: MEN500062 | B60: MARVEJOLS | C60: 2 R DES PENITENTS | D60: 44.554223485372994, 3.2914665307126985 | E60: 2025021800715TWA | G60: N/C | I60: N/C | J60: N/C | K60: N/C | L60: N/C
A61: MEN400746 | B61: ESCLANEDES | C61: RTE DE LA ROCHEROUSSE | D61: 44.49897303403482, 3.354680334316488 | E61: 2025021801688TPL | F61: OK | G61: N/C | H61: N/C | I61: N/C | J61: N/C | K61: N/C
A62: ROD401902 | B62: COMBRET | C62: LE LENIE | D62: 43.7885624232473, 2.66077094597189 | E62: 2025021801771TL4 | F62: OK | G62: N/C | I62: N/C | J62: N/C | K62: N/C
A63: ROD401835 | B63: SAINT JEAN ET SAINT PAUL | C63: ST PAUL DES FONTS | D63: 43.930947692276845, 3.0703941606371803 | E63: 2025022000408TU3 | G63: N/C | H63: N/C | J63: N/C | K63: N/C
A64: MEN500073 | B64: LES BONDONS | C64: ROUTE DE LOZERETTE | D64: 44.383655, 3.622800 | E64: 2025021800278T5N | G64: N/C | I64: N/C | J64: N/C | K64: OK
A65: ROD500199 | B65: LIOUJAS LA LOUBIERE | C65: CHEMIN DU PLO | D65: 44.3870303750701, 2.6342955928968608 | E65: 2025022100543TC0 | F65: OK | G65: N/C | I65: OK | J65: OK | K65: N/C | L65: N/C
A66: ROD500227 | B66: SAINT GENIEZ D OLT ET D AUBRAC | C66: PL GEN DE GAULLE | D66: 44.464943023038465, 2.975282775971485 | E66: 2025022100800TZP | F66: OK | G66: N/C | J66: OK | K66: N/C | L66: N/C
A67: ROD500139 | B67: LAVAL ROQUECEZIERE | C67: ROUTE DES PERES, | D67: 43.83995998713012, 2.6350243469331467 | E67: R | F67: OK | G67: N/C | H67: N/C | J67: N/C | K67: N/C | L67: N/C
A68: ROD402083 | B68: LACROIX BARREZ | C68: AVENUE ROBERT LAURENS | D68: 44.774849725962895, 2.6269953290989325 | E68: 2025022500811TQL | F68: OK | G68: N/C | H68: OK | I68: OK | J68: N/C | K68: N/C | L68: OK (THD)
A69: MEN500024 | B69: PONT DE MONVERT-SUD MT LOZERE | C69: SENT DE LA CALADE | D69: 44.34406724564879, 3.800268878556202 | E69: 2025022600541T6I | F69: OK | G69: N/C | H69: N/C | I69: N/C | J69: N/C | K69: N/C | L69: N/C
A70: MEN500019 | B70: LANARCE | C70: LA SAGNIERE | D70: 44.71094877969228, 3.997848884304428 | E70: 2025022800798T7C | F70: OK | G70: N/C | H70: N/C | I70: N/C | J70: N/C | K70: N/C | L70: N/C
A71: MEN500044 | B71: NASBINALS | C71: CH DE MERDARIC | D71: 44.657062601931806, 3.0519761032978905 | E71: 2025022801360TZC | F71: OK | G71: N/C | H71: N/C | I71: N/C | J71: N/C | K71: N/C | L71: N/C
A72: ROD500265 | B72: SAINTE RADEGONDE | C72: 12 R PATUS COMMUN | D72: 44.33770737730425, 2.625944067250777 | E72: 2025030300243TXK | F72: OK | G72: OK | I72: N/C | J72: OK | K72: N/C | L72: OK
A73: ROD500232 | B73: QUINS | C73: RUE DU BOIS | D73: 44.22749115812674, 2.398000735887416 | E73: 2025030300843TS5 | F73: OK | G73: N/C | I73: N/C | J73: N/C | K73: N/C
A74: IMI-VA-40123/01PL-1 | B74: HERM | C74: route de tachette | D74: 43.79601 ; -1.11469 | E74: 2025030301957TAA | F74: OK | L74: OK
A75: ROD500260 | B75: MELAGUES | C75: Saint Pierre des Cats | D75: 43.72500538862308, 2.9848785951492927 | E75: 2025030401676TDU | F75: OK | G75: N/C | H75: N/C | I75: N/C | J75: N/C | K75: N/C | L75: N/C
A76: ROD500260 | B76: MELAGUES | C76: Saint Pierre des Cats | D76: 43.72353826372651, 2.9855543242330307 | E76: 2025030401745T4W | F76: OK | G76: N/C | H76: N/C | I76: N/C | J76: N/C | K76: N/C | L76: N/C
A77: ROD500260 | B77: MELAGUES | C77: Raunier | D77: 43.73117438925133, 3.0026834375546883 | E77: 2025030401800TVN | F77: OK | G77: N/C | H77: N/C | I77: N/C | J77: N/C | K77: N/C | L77: N/C
A78: MEN500043 | B78: SAINT CHELY D APCHER | C78: LD CIVERGOLS | D78: 44.81030 ; 3.30126 | E78: 2025030401775TL2 | F78: OK | H78: OK
A79: ROD500260 | B79: MELAGUES | C79: D52 | D79: 43.73792420852484, 3.018809500762322 | E79: 2025030401855T7A | F79: OK | G79: N/C | H79: N/C | I79: N/C | J79: N/C | K79: N/C | L79: OK (THD)
A80: ROD500260 | B80: MELAGUES | C80: D53 | D80: 43.74773614801901, 3.014908104913595 | E80: 2025030402067TJB | F80: OK | G80: N/C | H80: N/C | I80: N/C | J80: N/C | K80: N/C | L80: N/C
A81: IMI-VA-40281-028A-1 | B81: ST PIERRE DU MONT | C81: 4 IMPASSE DU MONT D | D81: 43.87083 ; -0.50958 | E81: 2025030501167TFI | F81: OK | G81: OK | H81: OK | J81: OK | K81: OK
A82: ROD402081 | B82: SAINT SERNIN SUR RANCE | C82: 22 CHE DE LAVAL | D82: 43.880324713027015, 2.606190109497783 | E82: 2025030501870TIK | F82: OK | G82: N/C | J82: N/C | K82: N/C
A83: MDM400853 | B83: Bégaar | C83: 218 CHEMIN POUCHIOU | D83: 43.82838506859258, -0.8640265936280924 | E83: 2025030601132TVZ | F83: OK | G83: N/C | I83: N/C | J83: OK | K83: N/C | L83: OK
A84: ROD402052 | B84: SAINT IZAIRE | C84: CH DE SOLAGES | D84: 43.937780229798044, 2.7111514098565466 | E84: 2025030701707TH7 | F84: OK | G84: N/C | H84: OK | I84: N/C | J84: N/C | K84: N/C
A85: IMI-VA-40192/09AT-1 | B85: Mont-de-Marsan | C85: RUE GABRIEL CABANNES | D85: 43.88390 ; -0.49815 | E85: 2025030700981TMS | F85: OK | G85: OK | H85: OK | J85: OK | L85: OK
A86: IMI-VA-40123/01LF-1 | B86: Herm | C86: chemin de Maisonnave | D86: 43.80456 ; -1.12251 | E86: 2025031101545TF1 | F86: OK | K86: OK
A87: MEN500082 | B87: MOLEZON | C87: TRABASSAC HAUT | D87: 44.22880113880481, 3.7047792357238425 | E87: 2025031200318TUA | G87: N/C | H87: N/C | I87: N/C | J87: N/C | K87: N/C | L87: N/C
A88: IMI-VA-40123/01KO-1 | B88: HERM | C88: ROUTE DE CLUQUELARDIT | D88: 43.80797 ; -1.11105 | E88: 2025031200952TU7 | F88: OK | G88: N/C | H88: OK | I88: N/C | J88: N/C | K88: N/C | L88: N/C
A89: MEN500027 | B89: BANASSAC-CANILHAC | C89: 21 RUE DU COULAS à | D89: 44.43575 ; 3.20072 | E89: 2025031102125T3C | F89: OK | G89: N/C | H89: OK | I89: OK | J89: N/C | K89: N/C | L89: N/C
A90: IMI-VA-40123/01KM-1 | B90: HERM | C90: ROUTE DE CLUQUELARDIT | D90: 43.80824 ; -1.11019 | E90: 2025031200996TIK | F90: OK | H90: OK
A91: IMI-VA-40037/005W-1 | D91: 43.85605 ; -0.51790 | E91: 2025031201456TY6 | F91: OK | H91: OK | I91: OK
A92: ROD500376 | B92: PONT DE SALARS | C92: CAMBOULAS | D92: 44.27262 ; 2.67851 | E92: 2025031401644TZS | F92: OK | G92: N/C | H92: N/C | I92: N/C | J92: N/C | K92: N/C | L92: N/C
A93: ROD500410 | B93: VILLEFRANCHE DE PANAT | C93: IMP DU CHAMP GRAND | D93: 44.0925143592649, 2.7102325227736763 | E93: 2025031600138TKQ | F93: N/C | G93: N/C | H93: N/C | I93: N/C | J93: N/C | K93: N/C | L93: OK
A94: ROD500348 | B94: SAINT HIPPOLYTE | C94: 6033 PL DE LA SAINT LUNDI | D94: 44.71706416916687, 2.5515288160619076 | E94: 2025031701104TLN | F94: OK | G94: N/C | H94: OK | J94: OK | K94: OK | L94: N/C
A95: ROD40270 | B95: QUINS | C95: 9 CH DU CROUP | D95: 44.21952724730215, 2.3770648776295333 | E95: 2025031702219T2K | F95: OK | G95: N/C | I95: N/C | J95: N/C | K95: N/C | L95: N/C
A96: MEN400252 | B96: SAINT CHELY D APCHER | C96: LD CIVERGOLS | D96: 44.815404954827514, 3.2976982429175843 | E96: 2025031801111T1I | F96: OK | G96: N/C | H96: OK | J96: N/C | K96: OK | L96: N/C
A97: MEN500058 | B97: VIALAS | C97: 5078 LD LIBOURETTE | D97: 44.3309555080191, 3.8895332177411146 | E97: 2025031801799TUO | F97: OK | G97: N/C | H97: N/C | J97: N/C | K97: N/C | L97: N/C
A98: IMI-VA-40123/01LD-1 | B98: HERM | C98: 82 ch de maisonnave | D98: 43.8053664832443, -1.1228832054724973 | E98: 2025031901074T3D | F98: OK | K98: OK | L98: OK
A99: MEN500048 | B99: BANASSAC-CANILHAC | C99: 21 RUE DU COULAS | D99: 44.43574424021764, 3.200718014034537 | E99: 2025032000245TBB | F99: OK | G99: N/C | I99: OK | J99: N/C | K99: N/C | L99: N/C
A100: ROD500378 | B100: TAUSSAC | C100: 1200 RTE DE PEYRAT | D100: 44.85694 ; 2.64371 | E100: 2025032000367TFR | F100: N/C | G100: N/C | H100: N/C | J100: N/C | K100: N/C | L100: N/C
A101: MEN500162 | B101: MONTS DE RANDON | C101: LE VILLAGE | D101: 44.61204 ; 3.42225 | E101: 2025032100646T0N | F101: OK | G101: N/C | H101: N/C | I101: OK | J101: N/C | K101: OK | L101: OK
A102: MEN500128 | B102: Cans et Cévennes | C102: LD MIJAVOLS | D102: 44.31503 ; 3.69848 | E102: 2025032001378TTU | F102: OK | G102: N/C | I102: N/C | J102: N/C | K102: N/C | L102: N/C
A103: ROD500331 | B103: SAINT JEAN D ALCAPIES | C103: ALCAPIES | D103: 43.95116 ; 2.97391 | E103: 2025032701554TAQ
...
